Workbook
Name ScenarioIndex: 'Cashflows'!$C$5
Name DiscountRate: 'Model Inputs'!$C11
Name License_Y1: 'Model Inputs'!$C74
Name Impl_Y1: 'Model Inputs'!$C81
Name License_Y2: 'Model Inputs'!$C75
Name Impl_Y2: 'Model Inputs'!$C82
Name License_Y3: 'Model Inputs'!$C76
Name Impl_Y3: 'Model Inputs'!$C83
Name License_Y4: 'Model Inputs'!$C77
Name Impl_Y4: 'Model Inputs'!$C84
Name License_Y5: 'Model Inputs'!$C78
Name Impl_Y5: 'Model Inputs'!$C85

Sheet Cover Page
B5: Return on Investment Calculator
B7: Value Consulting - Business Case
B10: Client Name: | C10: WSFS Bank (Wilmington Savings Fund Society)
B12: Date: | C12: 2026-02-27
B14: Currency: | C14: USD
B16: Analysis Period: | C16: 5 Years
B18: Selected Scenario: | C18: Moderate
B20: Discount Rate: | C20: 12.0%
B24: DATA SOURCE LEGEND
B26: Green | C26: From transcript/client data
B27: Yellow | C27: Estimate - requires validation
B28: Blue | C28: Backbase benchmark
B29: Red border | C29: Low confidence - critical validation

Sheet Instructions
B2: ROI Model Instructions
B5: THIS IS A LIVE MODEL — all calculations use Excel formulas.
B6: Changing any input on 'Model Inputs' will automatically recalculate all sheets.
B8: SCENARIO SWITCHING
B9: • Go to 'Model Inputs' sheet, cell C5
B10: • Select: 1 = Conservative, 2 = Moderate, 3 = Aggressive
B11: • All curves, impacts, and downstream calculations will update instantly
B13: EDITING INPUTS
B14: • Blue-shaded cells on 'Model Inputs' are editable — change volumes, rates, costs
B15: • Yellow cells are estimates that should be validated with client data
B16: • Green cells are from transcript — highest confidence
B18: SHEET ARCHITECTURE
... B28: • LOW - Estimate based on typical patterns - REQUIRES VALIDATION

Sheet Table of Contents
B3: Table of Contents
B5: Input Layer | C5: Model Inputs — editable parameters
C6: Scenario Data — Conservative / Moderate / Aggressive
B7: Calculation | C7: Servicing Detail — task-level breakdown
C8: Lever: Digital Onboarding — Consumer Abandonment Recovery
C9: Lever: Branch & Call Center Deflection
C10: Lever: Customer Retention — Digital Engagement & Churn Reduction
C11: Lever: SMB Digital Onboarding — Manual Process Efficiency
C12: Lever: Cross-sell & Product Deepening — Revenue Uplift
C13: Cashflows — 5-year projection
B14: Output Layer | C14: Results Dashboard — NPV, IRR, Payback, ROI
B15: Reference | C15: Assumptions Register
C16: Data Gaps for Validation

Sheet Cashflows
B1: 5 Year Cashflows & ROI
B3: All values are live formulas. Change the scenario below — Journey Analysis and Cashflows update automatically.
B4: SCENARIO SELECTOR
B5: Active Scenario (1=Conservative, 2=Moderate, 3=Aggressive) | C5: 2
B6: =IF(C5=1,"Conservative — slower adoption, cautious assumptions",IF(C5=2,"Moderate — base case, phased rollout","Aggressive — fast adoption, full benefit"))
C8: Year 1 | D8: Year 2 | E8: Year 3 | F8: Year 4 | G8: Year 5 | H8: Total
B9: CASH INFLOWS (Benefits)
B10: Digital Onboarding — Consumer Abandonment Recovery | C10: ='Journey Analysis'!C17*'Model Inputs'!C91*'Model Inputs'!C97 | D10: ='Journey Analysis'!C17*'Model Inputs'!C92*'Model Inputs'!C98 | E10: ='Journey Analysis'!C17*'Model Inputs'!C93*'Model Inputs'!C99 | F10: ='Journey Analysis'!C17*'Model Inputs'!C94*'Model Inputs'!C100 | G10: ='Journey Analysis'!C17*'Model Inputs'!C95*'Model Inputs'!C101 | H10: =SUM(C10:G10)
B11: Branch & Call Center Deflection | C11: ='Journey Analysis'!C35*'Model Inputs'!C130*'Model Inputs'!C136 | D11: ='Journey Analysis'!C35*'Model Inputs'!C131*'Model Inputs'!C137 | E11: ='Journey Analysis'!C35*'Model Inputs'!C132*'Model Inputs'!C138 | F11: ='Journey Analysis'!C35*'Model Inputs'!C133*'Model Inputs'!C139 | G11: ='Journey Analysis'!C35*'Model Inputs'!C134*'Model Inputs'!C140 | H11: =SUM(C11:G11)
B12: Customer Retention — Digital Engagement & Churn Reduction | C12: ='Journey Analysis'!C50*'Model Inputs'!C117*'Model Inputs'!C123 | D12: ='Journey Analysis'!C50*'Model Inputs'!C118*'Model Inputs'!C124 | E12: ='Journey Analysis'!C50*'Model Inputs'!C119*'Model Inputs'!C125 | F12: ='Journey Analysis'!C50*'Model Inputs'!C120*'Model Inputs'!C126 | G12: ='Journey Analysis'!C50*'Model Inputs'!C121*'Model Inputs'!C127 | H12: =SUM(C12:G12)
B13: SMB Digital Onboarding — Manual Process Efficiency | C13: ='Journey Analysis'!C65*'Model Inputs'!C91*'Model Inputs'!C97 | D13: ='Journey Analysis'!C65*'Model Inputs'!C92*'Model Inputs'!C98 | E13: ='Journey Analysis'!C65*'Model Inputs'!C93*'Model Inputs'!C99 | F13: ='Journey Analysis'!C65*'Model Inputs'!C94*'Model Inputs'!C100 | G13: ='Journey Analysis'!C65*'Model Inputs'!C95*'Model Inputs'!C101 | H13: =SUM(C13:G13)
B14: Cross-sell & Product Deepening — Revenue Uplift | C14: ='Journey Analysis'!C81*'Model Inputs'!C91*'Model Inputs'!C97 | D14: ='Journey Analysis'!C81*'Model Inputs'!C92*'Model Inputs'!C98 | E14: ='Journey Analysis'!C81*'Model Inputs'!C93*'Model Inputs'!C99 | F14: ='Journey Analysis'!C81*'Model Inputs'!C94*'Model Inputs'!C100 | G14: ='Journey Analysis'!C81*'Model Inputs'!C95*'Model Inputs'!C101 | H14: =SUM(C14:G14)
B16: Total Cash Inflow | C16: =SUM(C10:C14) | D16: =SUM(D10:D14) | E16: =SUM(E10:E14) | F16: =SUM(F10:F14) | G16: =SUM(G10:G14) | H16: =SUM(H10:H14)
B19: CASH OUTFLOWS (Investment)
B20: License | C20: ='Model Inputs'!C74 | D20: ='Model Inputs'!C75 | E20: ='Model Inputs'!C76 | F20: ='Model Inputs'!C77 | G20: ='Model Inputs'!C78 | H20: =SUM(C20:G20)
B21: Implementation | C21: ='Model Inputs'!C81 | D21: ='Model Inputs'!C82 | E21: ='Model Inputs'!C83 | F21: ='Model Inputs'!C84 | G21: ='Model Inputs'!C85 | H21: =SUM(C21:G21)
B22: Total Cash Outflow | C22: =C20+C21 | D22: =D20+D21 | E22: =E20+E21 | F22: =F20+F21 | G22: =G20+G21 | H22: =H20+H21
B25: NET CASHFLOW | C25: =C16-C22 | D25: =D16-D22 | E25: =E16-E22 | F25: =F16-F22 | G25: =G16-G22 | H25: =SUM(C25:G25)
B26: Cumulative Cashflow | C26: =C25 | D26: =C26+D25 | E26: =D26+E25 | F26: =E26+F25 | G26: =F26+G25
B30: FINANCIAL METRICS
B31: Discount Rate (WACC) | C31: ='Model Inputs'!C11
B32: Total 5-Year Benefits | C32: =H16
B33: Total 5-Year Investment | C33: =H22
B34: Net Benefit | C34: =C32-C33
B35: ROI % | C35: =IFERROR((C32-C33)/C33,0)
B36: Net Present Value (NPV) | C36: =NPV(C31,C25:G25)
B37: Internal Rate of Return (IRR) | C37: =IFERROR(IRR(C25:G25),"N/A")
B38: Payback Period (Years) | C38: =IF(C26>=0,1-((C26-C25)/C25),IF(D26>=0,2-((D26-D25)/D25),IF(E26>=0,3-((E26-E25)/E25),IF(F26>=0,4-((F26-F25)/F25),IF(G26>=0,5-((G26-G25)/G25),"N/A")))))
B42: BENEFITS BY LEVER (Annual Steady State)
B44: Lever Group | C44: Lifecycle Stage | D44: Annual Benefit
B45: Digital Onboarding — Consumer Abandonment Recovery | D45: ='Journey Analysis'!C17
B46: Branch & Call Center Deflection | D46: ='Journey Analysis'!C35
B47: Customer Retention — Digital Engagement & Churn Reduction | D47: ='Journey Analysis'!C50
B48: SMB Digital Onboarding — Manual Process Efficiency | D48: ='Journey Analysis'!C65
B49: Cross-sell & Product Deepening — Revenue Uplift | D49: ='Journey Analysis'!C81
B50: TOTAL | D50: =SUM(D45:D49)

Sheet Journey Analysis
B1: Journey Analysis — Benefit Calculation Chain
B2: Active Scenario: | C2: =IF('Cashflows'!$C$5=1,"Conservative",IF('Cashflows'!$C$5=2,"Moderate","Aggressive")) | D2: (Change on Cashflows sheet)
B3: Each lever: input factors → Baseline (formula) → × Backbase Impact → Annual Benefit. Change scenario on Cashflows to update scenario-linked impacts.
B5: Digital Onboarding — Consumer Abandonment Recovery
B6: Evidence: T-001, T-002
B7: Revenue Generation
B8: Consumer App Abandonment Recovery | D8: Revenue
B9: Factor | C9: Value | D9: Unit
B10: Annual Lost Apps | C10: ='Model Inputs'!C18 | D10: applications/year
B11: Revenue Per Customer Relationship | C11: ='Model Inputs'!C19 | D11: USD/customer/year
B12: Baseline | C12: =C10 * C11 | D12: USD/year
B13: Backbase Impact | C13: ='Model Inputs'!C20 | D13: % of baseline captured by Backbase
B14: Annual Benefit | C14: =C12*C13 | D14: USD/year (scenario-adjusted)
B17: Total: Digital Onboarding — Consumer Abandonment Recovery | C17: =C14
B20: Branch & Call Center Deflection
B21: Evidence: T-003, T-004, T-005
B22: Cost Reduction
B23: Consumer & SMB Servicing Cost Avoidance | D23: Cost
B24: Factor | C24: Value | D24: Unit
B25: Consumer Call Center Baseline | C25: ='Model Inputs'!C27 | D25: USD/year
B26: Branch Visits Baseline | C26: ='Model Inputs'!C28 | D26: USD/year
B27: Smb Servicing Baseline | C27: ='Model Inputs'!C29 | D27: USD/year
B28: Baseline | C28: =C25 + C26 + C27 | D28: USD/year
B29: Backbase Impact | C29: ='Model Inputs'!C30 | D29: % of baseline captured by Backbase
B30: Annual Benefit | C30: =C28*C29 | D30: USD/year (scenario-adjusted)
B32: Servicing Cost Avoidance
B33: Servicing Total (see Servicing Detail sheet) | C33: ='Servicing Detail'!K22
B35: Total: Branch & Call Center Deflection | C35: =C30+C33
B38: Customer Retention — Digital Engagement & Churn Reduction
B39: Evidence: T-006, T-007
B40: Revenue Generation
B41: Consumer Attrition Reduction | D41: Revenue
B42: Factor | C42: Value | D42: Unit
B43: Annual Churning Customers | C43: ='Model Inputs'!C37 | D43: customers/year
B44: Full Relationship Value | C44: ='Model Inputs'!C38 | D44: USD/customer/year
B45: Baseline | C45: =C43 * C44 | D45: USD/year
B46: Backbase Impact | C46: ='Model Inputs'!C39 | D46: % of baseline captured by Backbase
B47: Annual Benefit | C47: =C45*C46 | D47: USD/year (scenario-adjusted)
B50: Total: Customer Retention — Digital Engagement & Churn Reduction | C50: =C47
B53: SMB Digital Onboarding — Manual Process Efficiency
B54: Evidence: T-008, T-009
B55: Cost Reduction
B56: SMB Onboarding Labor Cost Reduction | D56: Cost
B57: Factor | C57: Value | D57: Unit
B58: Annual New Smb Accounts | C58: ='Model Inputs'!C46 | D58: accounts/year
B59: Avg Onboarding Cost Per Account | C59: ='Model Inputs'!C47 | D59: USD/account
B60: Baseline | C60: =C58 * C59 | D60: USD/year
B61: Backbase Impact | C61: ='Model Inputs'!C48 | D61: % of baseline captured by Backbase
B62: Annual Benefit | C62: =C60*C61 | D62: USD/year (scenario-adjusted)
B65: Total: SMB Digital Onboarding — Manual Process Efficiency | C65: =C62
B68: Cross-sell & Product Deepening — Revenue Uplift
B69: Evidence: T-010, T-011
B70: Revenue Generation
B71: Products-per-Customer Uplift via Digital Engagement | D71: Revenue
B72: Factor | C72: Value | D72: Unit
B73: Addressable Customers | C73: ='Model Inputs'!C55 | D73: customers
B74: Products Gap Per Customer | C74: ='Model Inputs'!C56 | D74: products/customer
B75: Avg Product Revenue Per Year | C75: ='Model Inputs'!C57 | D75: USD/product/year
B76: Baseline | C76: =C73 * C74 * C75 | D76: USD/year
B77: Backbase Impact | C77: ='Model Inputs'!C58 | D77: % of baseline captured by Backbase
B78: Annual Benefit | C78: =C76*C77 | D78: USD/year (scenario-adjusted)
B81: Total: Cross-sell & Product Deepening — Revenue Uplift | C81: =C78
B84: GRAND TOTAL — ALL LEVERS
C85: Annual Benefit
B86: Total Annual Benefit (Scenario-Adjusted, Steady State) | C86: =C17+C35+C50+C65+C81

Sheet Servicing Detail
B1: Customer Servicing — Channel Analysis
B3: Vol Saving = Baseline × Vol Deflection. Time Saving = Remaining Vol × Time × Time Reduction × Rate. Total = Vol + Time Saving.
B5: Task | C5: Volume | D5: Time (hrs) | E5: Rate | F5: Baseline | G5: Vol Deflection | H5: Time Reduction | I5: Vol Saving | J5: Time Saving | K5: Total Saved | L5: Source
B6: Evidence: T-003, T-004, T-005
B8: Branch
B9: Credit Card Payments / Simple Transfers | C9: 55000 | D9: 0.25 | E9: 20 | F9: =C9*D9*E9 | G9: 0.55 | H9: 0.2 | I9: =F9*G9 | J9: =C9*(1-G9)*D9*H9*E9 | K9: =I9+J9
B10: Account Maintenance (address, preferences) | C10: 30000 | D10: 0.25 | E10: 20 | F10: =C10*D10*E10 | G10: 0.5 | H10: 0.15 | I10: =F10*G10 | J10: =C10*(1-G10)*D10*H10*E10 | K10: =I10+J10
B11: Statement / Document Requests | C11: 18000 | D11: 0.167 | E11: 20 | F11: =C11*D11*E11 | G11: 0.6 | H11: 0.25 | I11: =F11*G11 | J11: =C11*(1-G11)*D11*H11*E11 | K11: =I11+J11
B12: Branch Subtotal | C12: =SUM(C9:C11) | F12: =SUM(F9:F11) | I12: =SUM(I9:I11) | J12: =SUM(J9:J11) | K12: =SUM(K9:K11)
B14: Call Center
B15: Balance/Transaction Inquiries | C15: 150000 | D15: 0.083 | E15: 20 | F15: =C15*D15*E15 | G15: 0.6 | H15: 0.25 | I15: =F15*G15 | J15: =C15*(1-G15)*D15*H15*E15 | K15: =I15+J15
B16: Bill Pay Support / Wire Initiation | C16: 80000 | D16: 0.25 | E16: 20 | F16: =C16*D16*E16 | G16: 0.4 | H16: 0.3 | I16: =F16*G16 | J16: =C16*(1-G16)*D16*H16*E16 | K16: =I16+J16
B17: Account Profile Changes (address, alerts, user ID) | C17: 60000 | D17: 0.167 | E17: 20 | F17: =C17*D17*E17 | G17: 0.5 | H17: 0.2 | I17: =F17*G17 | J17: =C17*(1-G17)*D17*H17*E17 | K17: =I17+J17
B18: Fraud / Card Management | C18: 40000 | D18: 0.333 | E18: 22 | F18: =C18*D18*E18 | G18: 0.2 | H18: 0.2 | I18: =F18*G18 | J18: =C18*(1-G18)*D18*H18*E18 | K18: =I18+J18
B19: Loan Inquiry / Payment Support | C19: 30000 | D19: 0.25 | E19: 20 | F19: =C19*D19*E19 | G19: 0.35 | H19: 0.25 | I19: =F19*G19 | J19: =C19*(1-G19)*D19*H19*E19 | K19: =I19+J19
B20: Call Center Subtotal | C20: =SUM(C15:C19) | F20: =SUM(F15:F19) | I20: =SUM(I15:I19) | J20: =SUM(J15:J19) | K20: =SUM(K15:K19)
B22: TOTAL SERVICING SAVINGS | F22: =SUM(F12,F20) | I22: =I12+I20 | J22: =J12+J20 | K22: =K12+K20

Sheet Model Inputs
B2: Model Inputs
B3: Blue cells are editable. Change values and the model recalculates.
B5: Active Scenario | C5: =IF('Cashflows'!$C$5=1,"Conservative",IF('Cashflows'!$C$5=2,"Moderate","Aggressive")) | D5: (Change scenario on Cashflows sheet)
B7: BASIC INFORMATION
B8: Input | C8: Value | D8: Conf. | E8: Assumption/Comment | F8: Source
B10: FINANCIAL PARAMETERS
B11: Discount Rate (WACC) | C11: 0.12
B12: Analysis Period (Years) | C12: 5
B13: YoY Growth Rate | C13: 0.08
B15: LEVER GROUP INPUTS
B16: Digital Onboarding — Consumer Abandonment Recovery
B17: Consumer App Abandonment Recovery
B18: Annual Lost Apps | C18: 17520 | D18: HIGH | E18: 1,600 app starts/month - 140 funded/month = 1,460 abandoned/month × 12 = 17,520/year. Tom Holdren cited 91% abandonment rate at 00:45:36 in Nov 14 demo. | F18: CLIENT DATA
B19: Revenue Per Customer Relationship | C19: 700 | D19: MEDIUM | E19: Full relationship value: $8.27B consumer deposits × 3.0% NIM / 344K accounts ≈ $721; rounded to $700 conservative. NOTE: CLIENT DATA states $350/year net revenue — the higher figure reflects NIM contribution which is the economic case for retention. Validate with CFO. | F19: DERIVED
B20: Backbase Impact | C20: =INDEX('Scenario Data'!$C$80:$E$80,1,'Cashflows'!$C$5) | D20: MEDIUM | E20: Gap-based: Client current funded rate = 8.75% (140/1,600). Best-in-class digital onboarding funded rate = 60% (neobanks/DBS). Gap = (60%-8.75%)/60% = 85.4%. Capture rate = 0.18 (conservative — WSFS fraud dial is set very conservatively per transcript; behavior change takes time; not all abandoned apps are recoverable intent). backbase_impact = 85.4% × 0.18 ≈ 0.15. This means Backbase helps convert ~2,628 additional accounts/year (15% of 17,520 lost). Backbase enabler: Digital Onboarding journeys with pre-filled KYC via Alloy integration, streamlined mobile-first application flow. | F20: GAP-BASED CALCULATION
B21: Baseline Annual | C21: =C18 * C19
B22: Annual Benefit (Steady State) | C22: =C21*C20
B25: Branch & Call Center Deflection
B26: Consumer & SMB Servicing Cost Avoidance
B27: Consumer Call Center Baseline | C27: 3600000 | D27: MEDIUM | E27: 220,000 digitally active consumers × 35% annual call propensity × 3 calls/year = 231,000 calls + non-digital base: total ~360,000 calls/year. Fully loaded cost $10/call (8 min × $15/hr FTE + overhead). Baseline = $3,600,000. SOURCE: Bailey DeLellis confirmed 'customer support is primarily call center driven, lacking live chat or secure messaging' (00:22:00). Validate call volume with Operations. | F27: ESTIMATE
B28: Branch Visits Baseline | C28: 1545000 | D28: MEDIUM | E28: 344,000 accounts × 15% visit for simple tasks × 2 visits/year = 103,200 branch visits/year for deflectable tasks (paying credit cards, account inquiries, simple changes). Cost per visit $15 (15 min at $30/hr staff + overhead). Bailey DeLellis cited 'high volume of branch visits for simple transactional tasks like paying credit cards' (00:39:35). | F28: ESTIMATE
B29: Smb Servicing Baseline | C29: 1080000 | D29: HIGH | E29: 4,500 SMB servicing requests/month (midpoint of 4,000-5,000 CLIENT DATA) × 12 = 54,000/year. Average handling time 15 min at $40/hr (ops FTE rate) = $10/request. Baseline = $540,000 ops cost. Wire issues frequently require support request per transcript (00:15:16). Using $20/request to account for RM escalation = $1,080,000/year. | F29: CLIENT DATA
B30: Backbase Impact | C30: =INDEX('Scenario Data'!$C$83:$E$83,1,'Cashflows'!$C$5) | D30: MEDIUM | E30: Gap-based: WSFS current digital self-service rate ~20% (call-center-driven, minimal live chat/secure messaging per transcript). Best-in-class community banks with digital banking: 65% self-service rate. Gap = (65%-20%)/65% = 69.2%. Capture rate = 0.36. backbase_impact = 69.2% × 0.36 ≈ 0.25. Servicing curve ramps faster as it's operationally driven. Backbase enabler: Self-service journeys (account management, payments, wire initiation), push notifications, secure messaging, in-app card management — addressing transcript pain points: bill pay complexity, wire initiation friction, no push notifications (00:16:31). | F30: GAP-BASED CALCULATION
B31: Baseline Annual | C31: =C27 + C28 + C29
B32: Annual Benefit (Steady State) | C32: =C31*C30
B35: Customer Retention — Digital Engagement & Churn Reduction
B36: Consumer Attrition Reduction
B37: Annual Churning Customers | C37: 20640 | D37: HIGH | E37: CLIENT DATA: attrition < 6% on 344,000 consumer accounts. Using 6% as ceiling: 344,000 × 0.06 = 20,640 customers leaving per year. The Nov 14 transcript noted AUM is increasing while account count is decreasing, confirming churn and failure to attract Gen Z/Millennials (00:44:36). | F37: CLIENT DATA + DERIVED
B38: Full Relationship Value | C38: 700 | D38: MEDIUM | E38: Full NIM-based relationship value: $8.27B consumer deposits × 3.0% NIM / 344K = $721; rounded to $700 conservative. The attrition lever captures the full relationship value lost (not just fee income), because a churning customer takes their deposits and relationship. Validate with CFO. | F38: DERIVED
B39: Backbase Impact | C39: =INDEX('Scenario Data'!$C$82:$E$82,1,'Cashflows'!$C$5) | D39: MEDIUM | E39: Gap-based: WSFS current attrition 6%. Best-in-class digital-first community banks: 2% attrition. Gap = (6%-2%)/6% = 66.7%. Capture rate = 0.30 (digital engagement reduces attrition through better UX, proactive notifications, self-service; however, many churn factors are non-digital — product pricing, branch access, life events). backbase_impact = 66.7% × 0.30 = 0.20. This retains ~4,128 additional customers/year at steady state. Churn lever has delayed onset — 0% Year 1 (platform must be deployed and adopted before behavioral change occurs). Backbase enabler: Digital Engage (personalized notifications, NBA), self-service retention, loyalty programs, proactive alerts for at-risk customers. | F39: GAP-BASED CALCULATION
B40: Baseline Annual | C40: =C37 * C38
B41: Annual Benefit (Steady State) | C41: =C40*C39
B44: SMB Digital Onboarding — Manual Process Efficiency
B45: SMB Onboarding Labor Cost Reduction
B46: Annual New Smb Accounts | C46: 700 | D46: LOW | E46: ESTIMATE — no direct client data on new SMB account volumes. Derived from WSFS SMB deposit base ($1.89B) ÷ avg SMB relationship $2.7M = ~700 SMB clients. Assuming 100% annual turnover/replacement (10% growth + attrition) = ~700 new accounts/year. Validate with Head of SMB Banking. Flag: LOW confidence — model is proportionally sensitive to this number. | F46: ESTIMATE
B47: Avg Onboarding Cost Per Account | C47: 1985 | D47: HIGH | E47: CLIENT DATA: RM 7.5-15h @ $75/hr + Ops 10-20h @ $40/hr + Compliance 4-8h @ $40/hr. Midpoints: RM $843.75 + Ops $600 + Compliance $240 = $1,683.75. Range: $1,485–$2,485. Using midpoint $1,985/account. These costs are confirmed as fully manual process — no digital workflow exists per discovery. | F47: CLIENT DATA
B48: Backbase Impact | C48: =INDEX('Scenario Data'!$C$84:$E$84,1,'Cashflows'!$C$5) | D48: MEDIUM | E48: Gap-based: WSFS onboarding is 100% manual (confirmed: RM-led, no digital workflow). Best-in-class SMB digital onboarding: 60% process automation achievable. Gap = 100% manual. Capture rate = 0.30 (RM relationship element cannot be eliminated; compliance review remains human; platform automates data capture, document collection, ID verification). backbase_impact = 1.0 × 0.30 = 0.30. This saves ~$596/account in labor (30% of $1,985). Backbase enabler: SMB Digital Onboarding — digital application flow, pre-populated KYC via Alloy, document upload, automated compliance checks, RM dashboard for case management. Addresses transcript pain points: RM time burden, manual compliance steps. | F48: GAP-BASED CALCULATION
B49: Baseline Annual | C49: =C46 * C47
B50: Annual Benefit (Steady State) | C50: =C49*C48
B53: Cross-sell & Product Deepening — Revenue Uplift
B54: Products-per-Customer Uplift via Digital Engagement
B55: Addressable Customers | C55: 344000 | D55: MEDIUM | E55: Full consumer base: 344,000 accounts. All digitally engaged customers are addressable for cross-sell via NBA (Next Best Action) features and proactive digital prompts. NOTE: Only ~65% (220,000) are currently digitally active — model applies to full base as target state. | F55: DERIVED
B56: Products Gap Per Customer | C56: 0.9 | D56: MEDIUM | E56: CLIENT DATA: 2.3 avg products/customer. BENCHMARK (industry best-in-class for community banks with strong digital engagement): 3.2 products/customer. Gap = 3.2 - 2.3 = 0.9 products/customer. NOTE: Full closure of gap is not realistic in a 5-year model — the backbase_impact captures the realistic portion Backbase can drive. | F56: CLIENT DATA + BENCHMARK
B57: Avg Product Revenue Per Year | C57: 152 | D57: MEDIUM | E57: Derived: $350 net revenue per customer / 2.3 products = $152/product/year net. This represents marginal net revenue per incremental product added (checking, savings, CD, credit card, mortgage, LOC). Conservative — some products yield more (mortgages), some less (savings accounts). | F57: DERIVED
B58: Backbase Impact | C58: =INDEX('Scenario Data'!$C$81:$E$81,1,'Cashflows'!$C$5) | D58: LOW | E58: Gap-based: Current 2.3 vs best-in-class 3.2 = gap of 0.9 products = 28.1% of the 3.2 target. Capture rate = 0.28 (digital cross-sell is a nudge, not a guarantee; customer willingness, product fit, credit underwriting all constrain uptake; 5-year horizon). backbase_impact = 28.1% × 0.28 ≈ 0.08. Steady-state: 344,000 × 0.9 × 0.08 = 24,768 incremental products → $3.77M incremental revenue at $152/product/yr. Low confidence: cross-sell impact highly dependent on NBA engine configuration, product portfolio competitiveness, and digital adoption rate. Product penetration curve has 0% Year 1 (requires platform maturity + adoption). Backbase enabler: Digital Engage (NBA cross-sell prompts), personalized product recommendations, digital product onboarding within the app — addressing the lack of digital cross-sell capability identified in transcript (no personalization, no proactive engagement features on current platform). | F58: GAP-BASED CALCULATION
B59: Baseline Annual | C59: =C55 * C56 * C57
B60: Annual Benefit (Steady State) | C60: =C59*C58
B64: ACTIVE BACKBASE IMPACTS (auto-selected from scenario)
B65: Abandonment Recovery | C65: =INDEX('Scenario Data'!$C$80:$E$80,1,'Cashflows'!$C$5)
B66: Cross Sell Deepening | C66: =INDEX('Scenario Data'!$C$81:$E$81,1,'Cashflows'!$C$5)
B67: Retention Improvement | C67: =INDEX('Scenario Data'!$C$82:$E$82,1,'Cashflows'!$C$5)
B68: Servicing Deflection | C68: =INDEX('Scenario Data'!$C$83:$E$83,1,'Cashflows'!$C$5)
B69: Smb Onboarding Efficiency | C69: =INDEX('Scenario Data'!$C$84:$E$84,1,'Cashflows'!$C$5)
B72: INVESTMENT
B73: License
B74: Year 1 | C74: 1000000
B75: Year 2 | C75: 1000000
B76: Year 3 | C76: 1000000
B77: Year 4 | C77: 1000000
B78: Year 5 | C78: 1000000
B80: Implementation
B81: Year 1 | C81: 4000000
B82: Year 2 | C82: 1500000
B83: Year 3 | C83: 500000
B84: Year 4 | C84: 0
B85: Year 5 | C85: 0
B88: ACTIVE CURVES (auto-selected from scenario)
B89: These cells use INDEX formulas — they update when you change the scenario on the Cashflows sheet.
B90: Acquisition — Implementation
B91: Year 1 | C91: =INDEX('Scenario Data'!$C$9:$E$9,1,'Cashflows'!$C$5)
B92: Year 2 | C92: =INDEX('Scenario Data'!$C$10:$E$10,1,'Cashflows'!$C$5)
B93: Year 3 | C93: =INDEX('Scenario Data'!$C$11:$E$11,1,'Cashflows'!$C$5)
B94: Year 4 | C94: =INDEX('Scenario Data'!$C$12:$E$12,1,'Cashflows'!$C$5)
B95: Year 5 | C95: =INDEX('Scenario Data'!$C$13:$E$13,1,'Cashflows'!$C$5)
B96: Acquisition — Effectiveness
B97: Year 1 | C97: =INDEX('Scenario Data'!$C$45:$E$45,1,'Cashflows'!$C$5)
B98: Year 2 | C98: =INDEX('Scenario Data'!$C$46:$E$46,1,'Cashflows'!$C$5)
B99: Year 3 | C99: =INDEX('Scenario Data'!$C$47:$E$47,1,'Cashflows'!$C$5)
B100: Year 4 | C100: =INDEX('Scenario Data'!$C$48:$E$48,1,'Cashflows'!$C$5)
B101: Year 5 | C101: =INDEX('Scenario Data'!$C$49:$E$49,1,'Cashflows'!$C$5)
B103: Product Penetration — Implementation
B104: Year 1 | C104: =INDEX('Scenario Data'!$C$16:$E$16,1,'Cashflows'!$C$5)
B105: Year 2 | C105: =INDEX('Scenario Data'!$C$17:$E$17,1,'Cashflows'!$C$5)
B106: Year 3 | C106: =INDEX('Scenario Data'!$C$18:$E$18,1,'Cashflows'!$C$5)
B107: Year 4 | C107: =INDEX('Scenario Data'!$C$19:$E$19,1,'Cashflows'!$C$5)
B108: Year 5 | C108: =INDEX('Scenario Data'!$C$20:$E$20,1,'Cashflows'!$C$5)
B109: Product Penetration — Effectiveness
B110: Year 1 | C110: =INDEX('Scenario Data'!$C$52:$E$52,1,'Cashflows'!$C$5)
B111: Year 2 | C111: =INDEX('Scenario Data'!$C$53:$E$53,1,'Cashflows'!$C$5)
B112: Year 3 | C112: =INDEX('Scenario Data'!$C$54:$E$54,1,'Cashflows'!$C$5)
B113: Year 4 | C113: =INDEX('Scenario Data'!$C$55:$E$55,1,'Cashflows'!$C$5)
B114: Year 5 | C114: =INDEX('Scenario Data'!$C$56:$E$56,1,'Cashflows'!$C$5)
B116: Retention — Implementation
B117: Year 1 | C117: =INDEX('Scenario Data'!$C$23:$E$23,1,'Cashflows'!$C$5)
B118: Year 2 | C118: =INDEX('Scenario Data'!$C$24:$E$24,1,'Cashflows'!$C$5)
B119: Year 3 | C119: =INDEX('Scenario Data'!$C$25:$E$25,1,'Cashflows'!$C$5)
B120: Year 4 | C120: =INDEX('Scenario Data'!$C$26:$E$26,1,'Cashflows'!$C$5)
B121: Year 5 | C121: =INDEX('Scenario Data'!$C$27:$E$27,1,'Cashflows'!$C$5)
B122: Retention — Effectiveness
B123: Year 1 | C123: =INDEX('Scenario Data'!$C$59:$E$59,1,'Cashflows'!$C$5)
...

Sheet Scenario Data
B2: Scenario Definitions
B3: Edit values here to customize scenarios. All lever sheets reference this table.
B5: Parameter | C5: Conservative | D5: Moderate | E5: Aggressive
B7: IMPLEMENTATION CURVES
B8: Acquisition
B9: Year 1 | C9: 0.1 | D9: 0.15 | E9: 0.2
B10: Year 2 | C10: 0.4 | D10: 0.5 | E10: 0.6
B11: Year 3 | C11: 0.7 | D11: 0.8 | E11: 0.9
B12: Year 4 | C12: 0.9 | D12: 0.95 | E12: 1
B13: Year 5 | C13: 1 | D13: 1 | E13: 1
B15: Product Penetration
B16: Year 1 | C16: 0 | D16: 0 | E16: 0
B17: Year 2 | C17: 0.3 | D17: 0.4 | E17: 0.5
B18: Year 3 | C18: 0.65 | D18: 0.75 | E18: 0.85
B19: Year 4 | C19: 0.85 | D19: 0.95 | E19: 1
B20: Year 5 | C20: 1 | D20: 1 | E20: 1
B22: Retention
B23: Year 1 | C23: 0 | D23: 0 | E23: 0
B24: Year 2 | C24: 0.3 | D24: 0.4 | E24: 0.5
B25: Year 3 | C25: 0.65 | D25: 0.75 | E25: 0.85
B26: Year 4 | C26: 0.85 | D26: 0.9 | E26: 1
B27: Year 5 | C27: 1 | D27: 1 | E27: 1
B29: Servicing
B30: Year 1 | C30: 0.15 | D30: 0.2 | E30: 0.25
B31: Year 2 | C31: 0.5 | D31: 0.6 | E31: 0.7
B32: Year 3 | C32: 0.8 | D32: 0.9 | E32: 1
B33: Year 4 | C33: 0.95 | D33: 1 | E33: 1
B34: Year 5 | C34: 1 | D34: 1 | E34: 1
B36: Smb Onboarding
B37: Year 1 | C37: 0.1 | D37: 0.15 | E37: 0.2
B38: Year 2 | C38: 0.45 | D38: 0.55 | E38: 0.65
B39: Year 3 | C39: 0.75 | D39: 0.85 | E39: 0.95
B40: Year 4 | C40: 0.95 | D40: 1 | E40: 1
B41: Year 5 | C41: 1 | D41: 1 | E41: 1
B43: EFFECTIVENESS CURVES
B44: Acquisition
B45: Year 1 | C45: 0.15 | D45: 0.2 | E45: 0.25
B46: Year 2 | C46: 0.4 | D46: 0.5 | E46: 0.55
B47: Year 3 | C47: 0.65 | D47: 0.75 | E47: 0.8
B48: Year 4 | C48: 0.85 | D48: 0.9 | E48: 0.95
B49: Year 5 | C49: 1 | D49: 1 | E49: 1
B51: Product Penetration
B52: Year 1 | C52: 0 | D52: 0 | E52: 0
B53: Year 2 | C53: 0.25 | D53: 0.3 | E53: 0.4
B54: Year 3 | C54: 0.55 | D54: 0.6 | E54: 0.7
B55: Year 4 | C55: 0.8 | D55: 0.85 | E55: 0.92
B56: Year 5 | C56: 1 | D56: 1 | E56: 1
B58: Retention
B59: Year 1 | C59: 0 | D59: 0 | E59: 0
B60: Year 2 | C60: 0.25 | D60: 0.35 | E60: 0.45
B61: Year 3 | C61: 0.55 | D61: 0.65 | E61: 0.75
B62: Year 4 | C62: 0.8 | D62: 0.85 | E62: 0.9
B63: Year 5 | C63: 1 | D63: 1 | E63: 1
B65: Servicing
B66: Year 1 | C66: 0.2 | D66: 0.25 | E66: 0.3
B67: Year 2 | C67: 0.45 | D67: 0.55 | E67: 0.65
B68: Year 3 | C68: 0.7 | D68: 0.8 | E68: 0.85
B69: Year 4 | C69: 0.9 | D69: 0.95 | E69: 1
B70: Year 5 | C70: 1 | D70: 1 | E70: 1
B72: Smb Onboarding
B73: Year 1 | C73: 0.15 | D73: 0.2 | E73: 0.25
B74: Year 2 | C74: 0.45 | D74: 0.5 | E74: 0.6
B75: Year 3 | C75: 0.7 | D75: 0.75 | E75: 0.85
B76: Year 4 | C76: 0.88 | D76: 0.9 | E76: 0.95
B77: Year 5 | C77: 1 | D77: 1 | E77: 1
B79: BACKBASE IMPACTS
B80: Abandonment Recovery | C80: 0.08 | D80: 0.15 | E80: 0.22
B81: Cross Sell Deepening | C81: 0.05 | D81: 0.08 | E81: 0.12
B82: Retention Improvement | C82: 0.1 | D82: 0.2 | E82: 0.3
B83: Servicing Deflection | C83: 0.12 | D83: 0.25 | E83: 0.38
B84: Smb Onboarding Efficiency | C84: 0.18 | D84: 0.3 | E84: 0.45

Sheet Bank Profile
B1: Bank Profile
B3: BANK IDENTITY
B4: Bank Name | C4: WSFS Bank (Wilmington Savings Fund Society)
B5: Country | C5: United States
B6: Currency | C6: USD
B7: Stock Ticker | C7: WSFS (NASDAQ)
B8: Report Year | C8: 2024
B9: Data Sources | C9: Public filings + Client-provided questionnaire (Nov 2025) + Discovery transcript (Nov 14, 2025)
B11: Market Context Status | C11: NOT_RUN
B13: KEY FINANCIAL METRICS
B14: Metric | C14: Value | D14: Confidence | E14: Source
B15: Total Deposits | C15: 17226000000 | D15: HIGH | E15: Public filing
B16: Consumer Deposits | C16: 8270000000 | D16: HIGH | E16: Public filing — 48% of total
B17: SMB Deposits | C17: 1890000000 | D17: HIGH | E17: Public filing — 11% of total
B18: Consumer Accounts (estimated) | C18: 344000 | D18: MEDIUM | E18: Derived — $8.27B / $24K avg deposit (industry benchmark)
B19: Digitally Active Consumers | C19: 220000 | D19: HIGH | E19: CLIENT DATA — ~65% of 344K
B20: Monthly App Starts (Consumer Onboarding) | C20: 1600 | D20: HIGH | E20: CLIENT DATA
B21: Monthly Apps Funded | C21: 140 | D21: HIGH | E21: CLIENT DATA
B22: App Abandonment Rate | C22: 91% | D22: HIGH | E22: CLIENT DATA — Tom Holdren cited explicitly in Nov 14 demo (00:45:36)
B23: Annual Revenue per Consumer | C23: 350 | D23: HIGH | E23: CLIENT DATA
B24: Annual Consumer Attrition Rate | C24: < 6% | D24: HIGH | E24: CLIENT DATA
B25: Avg Products per Customer | C25: 2.3 | D25: HIGH | E25: CLIENT DATA
B26: Monthly Business Servicing Requests | C26: 4,000–5,000 | D26: HIGH | E26: CLIENT DATA
B27: Business Onboarding Cost per Account | C27: $1,485–$2,485 | D27: HIGH | E27: Derived — RM 7.5-15h@$75 + Ops 10-20h@$40 + Compliance 4-8h@$40
B28: Annual Marketing Spend | C28: 8712000 | D28: HIGH | E28: Public filing — $2.178M/quarter
B29: CEB Platform Deprecation Date | C29: September 2026 | D29: HIGH | E29: CLIENT DATA — confirmed in transcript (00:24:08)
B31: DERIVED METRICS
B32: Metric | C32: Value | D32: Confidence | E32: Derivation
B33: Full Relationship Value per Consumer (NIM-based) | C33: 700 | D33: MEDIUM | E33: $8.27B consumer deposits × 3.0% NIM / 344K accounts ≈ $721; rounded down to $700 as conservative anchor for retention/acquisition levers
B34: Annual Churning Consumers (6% attrition cap) | C34: 20640 | D34: HIGH | E34: 344,000 × 0.06 = 20,640
B35: Annual Apps Lost to Abandonment | C35: 17520 | D35: HIGH | E35: 1,460 abandoned/month × 12 = 17,520/year
B36: Annual SMB Servicing Requests | C36: 54000 | D36: HIGH | E36: 4,500/month (midpoint) × 12 = 54,000/year
B38: DATA GAPS
B39: Data Needed | C39: Priority | D39: Impact | E39: Where to Obtain
B40: Exact consumer call center volume (calls/year) | C40: HIGH | D40: Servicing deflection lever sizing — model uses 360,000/yr estimate from 220K digitally active × 35% call propensity × 3 calls/yr; validate with COO/Ops | E40: COO or Head of Operations
B41: Annual new SMB account openings | C41: HIGH | D41: SMB onboarding lever baseline — model uses 700 accounts/yr as estimate; actual figure changes lever value proportionally | E41: Head of SMB Banking
B42: Call center average handle time and FTE cost | C42: MEDIUM | D42: Used $10/call blended fully-loaded; validate for accuracy | E42: Operations / Finance
B43: Products per customer segmentation | C43: MEDIUM | D43: Cross-sell lever assumes uniform 2.3 products/customer; segmented data would refine addressable population | E43: Chief Data Officer
B44: Annual Report financial data (C/I ratio, NII, ROE) | C44: HIGH | D44: Required for reasonableness checks and executive benchmark comparisons | E44: Public filings — WSFS NASDAQ: WSFS

Sheet Assumptions
B1: Assumptions Register
B3: All assumptions documented with sources and validation owners
B5: ID | C5: Assumption | D5: Value | E5: Conf. | F5: Source | G5: Owner | H5: Sensitivity
B6: A-001 | C6: Monthly app abandonment rate | D6: 91% (1,460 of 1,600 apps per month don't fund) | E6: HIGH | F6: CLIENT DATA — Tom Holdren explicitly cited in Nov 14, 2025 demo transcript (00:45:36) | G6: Head of Digital Banking | H6: HIGH — this is the anchor metric for Lever 1; a 10% change in abandonment rate shifts L1 baseline by ~$1.2M
B7: A-002 | C7: Annual revenue per consumer | D7: $350/customer/year (net fee/service income); $700 used for retention/acquisition levers (full NIM-based relationship value) | E7: MEDIUM | F7: $350 = CLIENT DATA. $700 = DERIVED (NIM calculation). Validate higher figure with CFO. | G7: CFO / Finance | H7: HIGH — if true relationship value is closer to $350, steady-state benefit drops by ~40%
B8: A-003 | C8: Consumer attrition rate | D8: 6% (CLIENT DATA states <6%; model uses 6% as ceiling) | E8: HIGH | F8: CLIENT DATA | G8: Head of Retail Banking | H8: MEDIUM — if actual attrition is 4% rather than 6%, Lever 3 baseline drops 33%
B9: A-004 | C9: Annual consumer accounts | D9: 344,000 (derived: $8.27B consumer deposits / $24K avg deposit) | E9: MEDIUM | F9: DERIVED — average deposit is an industry benchmark; actual count not provided | G9: Head of Retail Banking / CIO | H9: HIGH — affects all per-customer calculations across all 5 levers
B10: A-005 | C10: Annual new SMB account openings | D10: 700 accounts/year | E10: LOW | F10: ESTIMATE — no client data provided. Derived from SMB deposit base / average relationship size. | G10: Head of SMB Banking | H10: HIGH — L4 baseline is directly proportional to this number; validate as priority
B11: A-006 | C11: Consumer call center volume | D11: 360,000 calls/year (~$10/call fully loaded) | E11: LOW | F11: ESTIMATE — Bailey DeLellis confirmed call-center-driven support model (00:22:00); volume derived from digital adoption rate and industry ratios | G11: COO / Head of Operations | H11: MEDIUM — L2 baseline is $3.6M for call center component; ±50% range gives $1.8M–$5.4M
B12: A-007 | C12: Business onboarding cost | D12: $1,985/account (midpoint of $1,485–$2,485 CLIENT DATA range) | E12: HIGH | F12: CLIENT DATA | G12: Head of SMB Operations | H12: LOW — range is known; midpoint is defensible
B13: A-008 | C13: CEB deprecation creates implementation urgency | D13: September 2026 deadline — confirms budget and executive approval trajectory | E13: HIGH | F13: CLIENT DATA — confirmed in transcript (00:24:08) | G13: CTO | H13: LOW — timeline context only; does not affect financial model
B14: A-009 | C14: Best-in-class digital onboarding funded rate | D14: 60% funded rate (DBS, Marcus, Ally Digital) | E14: MEDIUM | F14: INDUSTRY BENCHMARK — digital-native and leading community bank benchmarks | G14: Backbase Value Consulting | H14: MEDIUM — if best-in-class is 40% instead of 60%, capture rate changes but impact on L1 is modest (<10%)
B15: A-010 | C15: Products per customer best-in-class | D15: 3.2 products/customer | E15: MEDIUM | F15: INDUSTRY BENCHMARK — BAI Banking Outlook, Cornerstone Advisors community bank digital study | G15: Backbase Value Consulting | H15: LOW — L5 cross-sell is flagged LOW confidence overall; this assumption only affects the gap sizing, not the final captured benefit materially

Sheet Data Gaps
B1: Data Gaps — Required for Validation
B3: These data points are CRITICAL for validating the ROI model.
B5: ID | C5: Data Needed | D5: Priority | E5: Source | F5: Impact on Model
B6: DG-001 | C6: Exact annual new SMB account volume | D6: HIGH | E6: Head of SMB Banking — CRM / core system | F6: L4 (SMB Onboarding) baseline is $1.66M — a 50% error in account volume causes a $248K/year error in steady-state benefit
B7: DG-002 | C7: Annual consumer call center call volume | D7: HIGH | E7: COO / Operations — call center reporting system | F7: L2 (Servicing Deflection) baseline includes $3.6M call center component based on estimate; actual volume validates or shifts this significantly
B8: DG-003 | C8: Annual branch visit count for deflectable tasks | D8: MEDIUM | E8: Branch Operations — transaction logs | F8: L2 branch component ($1.55M) is estimated; actual visit volumes for simple tasks (payments, account changes) refine the baseline
B9: DG-004 | C9: True fully-loaded revenue per consumer relationship (NIM-based) | D9: HIGH | E9: CFO — management accounts or segment P&L | F9: Model uses $700 for retention/acquisition levers; if CFO confirms closer to $350, 5-year benefits decrease by approximately $6M
B10: DG-005 | C10: Current products per customer (segmented by digital adoption) | D10: MEDIUM | E10: Chief Data Officer — customer analytics | F10: L5 (Cross-sell) assumes uniform 2.3 products; digitally active customers likely have different ratios; segmentation refines addressable market
B11: DG-006 | C11: Consumer attrition segmentation by digital engagement status | D11: MEDIUM | E11: Head of Retail Analytics | F11: If digitally active customers already attrite at <3% vs non-digital at >9%, the L3 lever should be scoped to at-risk non-digital segment only
B12: DG-007 | C12: Marketing cost per acquired consumer (CAC) | D12: LOW | E12: CMO / Finance — marketing attribution data | F12: Would add a cost-efficiency dimension to L1 (abandonment recovery is more cost-effective than paid acquisition); strengthens ROI case
