Workbook
Name ScenarioIndex: 'Cashflows'!$C$5
Name DiscountRate: 'Model Inputs'!$C11
Name License_Y1: 'Model Inputs'!$C109
Name Impl_Y1: 'Model Inputs'!$C116
Name License_Y2: 'Model Inputs'!$C110
Name Impl_Y2: 'Model Inputs'!$C117
Name License_Y3: 'Model Inputs'!$C111
Name Impl_Y3: 'Model Inputs'!$C118
Name License_Y4: 'Model Inputs'!$C112
Name Impl_Y4: 'Model Inputs'!$C119
Name License_Y5: 'Model Inputs'!$C113
Name Impl_Y5: 'Model Inputs'!$C120

Sheet Cover Page
B5: Return on Investment Calculator
B7: Value Consulting - Business Case
B10: Client Name: | C10: BECU
B12: Date: | C12: 2026-02-26
B14: Currency: | C14: USD
B16: Analysis Period: | C16: 5 Years
B18: Selected Scenario: | C18: Moderate
B20: Discount Rate: | C20: 10.0%
B24: DATA SOURCE LEGEND
B26: Green | C26: From transcript/client data
B27: Yellow | C27: Estimate - requires validation
B28: Blue | C28: Backbase benchmark
B29: Red border | C29: Low confidence - critical validation

Sheet Instructions
B2: ROI Model Instructions
B5: THIS IS A LIVE MODEL — all calculations use Excel formulas.
B6: Changing any input on 'Model Inputs' will automatically recalculate all sheets.
B8: SCENARIO SWITCHING
B9: • Go to 'Model Inputs' sheet, cell C5
B10: • Select: 1 = Conservative, 2 = Moderate, 3 = Aggressive
B11: • All curves, impacts, and downstream calculations will update instantly
B13: EDITING INPUTS
B14: • Blue-shaded cells on 'Model Inputs' are editable — change volumes, rates, costs
B15: • Yellow cells are estimates that should be validated with client data
B16: • Green cells are from transcript — highest confidence
B18: SHEET ARCHITECTURE
... B28: • LOW - Estimate based on typical patterns - REQUIRES VALIDATION

Sheet Table of Contents
B3: Table of Contents
B5: Input Layer | C5: Model Inputs — editable parameters
C6: Scenario Data — Conservative / Moderate / Aggressive
B7: Calculation | C7: Lever: L1 — Digital Membership Origination
B8: Calculation | C8: Lever: L2 — Digital Loan Origination
B9: Calculation | C9: Lever: L3 — Member Retention
B10: Calculation | C10: Lever: L4 — Cross-sell & Product Penetration
B11: Calculation | C11: Lever: L5 — Contact Center Cost Avoidance
B12: Calculation | C12: Lever: L6 — Branch Cost Avoidance
B13: Calculation | C13: Lever: L7 — Employee Enablement
B14: Calculation | C14: Lever: L8 — IT Platform Consolidation
C15: Cashflows — 5-year projection
B16: Output Layer | C16: Results Dashboard — NPV, IRR, Payback, ROI
B17: Reference | C17: Assumptions Register
C18: Data Gaps for Validation

Sheet Cashflows
B1: 5 Year Cashflows & ROI
B3: All values are live formulas. Change the scenario below — Journey Analysis and Cashflows update automatically.
B4: SCENARIO SELECTOR
B5: Active Scenario (1=Conservative, 2=Moderate, 3=Aggressive) | C5: 2
B6: =IF(C5=1,"Conservative — slower adoption, cautious assumptions",IF(C5=2,"Moderate — base case, phased rollout","Aggressive — fast adoption, full benefit"))
C8: Year 1 | D8: Year 2 | E8: Year 3 | F8: Year 4 | G8: Year 5 | H8: Total
B9: CASH INFLOWS (Benefits)
B10: L1 — Digital Membership Origination | C10: ='Journey Analysis'!C17*'Model Inputs'!C126*'Model Inputs'!C132 | D10: ='Journey Analysis'!C17*'Model Inputs'!C127*'Model Inputs'!C133 | E10: ='Journey Analysis'!C17*'Model Inputs'!C128*'Model Inputs'!C134 | F10: ='Journey Analysis'!C17*'Model Inputs'!C129*'Model Inputs'!C135 | G10: ='Journey Analysis'!C17*'Model Inputs'!C130*'Model Inputs'!C136 | H10: =SUM(C10:G10)
B11: L2 — Digital Loan Origination | C11: ='Journey Analysis'!C32*'Model Inputs'!C126*'Model Inputs'!C132 | D11: ='Journey Analysis'!C32*'Model Inputs'!C127*'Model Inputs'!C133 | E11: ='Journey Analysis'!C32*'Model Inputs'!C128*'Model Inputs'!C134 | F11: ='Journey Analysis'!C32*'Model Inputs'!C129*'Model Inputs'!C135 | G11: ='Journey Analysis'!C32*'Model Inputs'!C130*'Model Inputs'!C136 | H11: =SUM(C11:G11)
B12: L3 — Member Retention | C12: ='Journey Analysis'!C47*'Model Inputs'!C126*'Model Inputs'!C132 | D12: ='Journey Analysis'!C47*'Model Inputs'!C127*'Model Inputs'!C133 | E12: ='Journey Analysis'!C47*'Model Inputs'!C128*'Model Inputs'!C134 | F12: ='Journey Analysis'!C47*'Model Inputs'!C129*'Model Inputs'!C135 | G12: ='Journey Analysis'!C47*'Model Inputs'!C130*'Model Inputs'!C136 | H12: =SUM(C12:G12)
B13: L4 — Cross-sell & Product Penetration | C13: ='Journey Analysis'!C61*'Model Inputs'!C126*'Model Inputs'!C132 | D13: ='Journey Analysis'!C61*'Model Inputs'!C127*'Model Inputs'!C133 | E13: ='Journey Analysis'!C61*'Model Inputs'!C128*'Model Inputs'!C134 | F13: ='Journey Analysis'!C61*'Model Inputs'!C129*'Model Inputs'!C135 | G13: ='Journey Analysis'!C61*'Model Inputs'!C130*'Model Inputs'!C136 | H13: =SUM(C13:G13)
B14: L5 — Contact Center Cost Avoidance | C14: ='Journey Analysis'!C76*'Model Inputs'!C126*'Model Inputs'!C132 | D14: ='Journey Analysis'!C76*'Model Inputs'!C127*'Model Inputs'!C133 | E14: ='Journey Analysis'!C76*'Model Inputs'!C128*'Model Inputs'!C134 | F14: ='Journey Analysis'!C76*'Model Inputs'!C129*'Model Inputs'!C135 | G14: ='Journey Analysis'!C76*'Model Inputs'!C130*'Model Inputs'!C136 | H14: =SUM(C14:G14)
B15: L6 — Branch Cost Avoidance | C15: ='Journey Analysis'!C91*'Model Inputs'!C126*'Model Inputs'!C132 | D15: ='Journey Analysis'!C91*'Model Inputs'!C127*'Model Inputs'!C133 | E15: ='Journey Analysis'!C91*'Model Inputs'!C128*'Model Inputs'!C134 | F15: ='Journey Analysis'!C91*'Model Inputs'!C129*'Model Inputs'!C135 | G15: ='Journey Analysis'!C91*'Model Inputs'!C130*'Model Inputs'!C136 | H15: =SUM(C15:G15)
B16: L7 — Employee Enablement | C16: ='Journey Analysis'!C107*'Model Inputs'!C126*'Model Inputs'!C132 | D16: ='Journey Analysis'!C107*'Model Inputs'!C127*'Model Inputs'!C133 | E16: ='Journey Analysis'!C107*'Model Inputs'!C128*'Model Inputs'!C134 | F16: ='Journey Analysis'!C107*'Model Inputs'!C129*'Model Inputs'!C135 | G16: ='Journey Analysis'!C107*'Model Inputs'!C130*'Model Inputs'!C136 | H16: =SUM(C16:G16)
B17: L8 — IT Platform Consolidation | C17: ='Journey Analysis'!C121*'Model Inputs'!C126*'Model Inputs'!C132 | D17: ='Journey Analysis'!C121*'Model Inputs'!C127*'Model Inputs'!C133 | E17: ='Journey Analysis'!C121*'Model Inputs'!C128*'Model Inputs'!C134 | F17: ='Journey Analysis'!C121*'Model Inputs'!C129*'Model Inputs'!C135 | G17: ='Journey Analysis'!C121*'Model Inputs'!C130*'Model Inputs'!C136 | H17: =SUM(C17:G17)
B19: Total Cash Inflow | C19: =SUM(C10:C17) | D19: =SUM(D10:D17) | E19: =SUM(E10:E17) | F19: =SUM(F10:F17) | G19: =SUM(G10:G17) | H19: =SUM(H10:H17)
B22: CASH OUTFLOWS (Investment)
B23: License | C23: ='Model Inputs'!C109 | D23: ='Model Inputs'!C110 | E23: ='Model Inputs'!C111 | F23: ='Model Inputs'!C112 | G23: ='Model Inputs'!C113 | H23: =SUM(C23:G23)
B24: Implementation | C24: ='Model Inputs'!C116 | D24: ='Model Inputs'!C117 | E24: ='Model Inputs'!C118 | F24: ='Model Inputs'!C119 | G24: ='Model Inputs'!C120 | H24: =SUM(C24:G24)
B25: Total Cash Outflow | C25: =C23+C24 | D25: =D23+D24 | E25: =E23+E24 | F25: =F23+F24 | G25: =G23+G24 | H25: =H23+H24
B28: NET CASHFLOW | C28: =C19-C25 | D28: =D19-D25 | E28: =E19-E25 | F28: =F19-F25 | G28: =G19-G25 | H28: =SUM(C28:G28)
B29: Cumulative Cashflow | C29: =C28 | D29: =C29+D28 | E29: =D29+E28 | F29: =E29+F28 | G29: =F29+G28
B33: FINANCIAL METRICS
B34: Discount Rate (WACC) | C34: ='Model Inputs'!C11
B35: Total 5-Year Benefits | C35: =H19
B36: Total 5-Year Investment | C36: =H25
B37: Net Benefit | C37: =C35-C36
B38: ROI % | C38: =IFERROR((C35-C36)/C36,0)
B39: Net Present Value (NPV) | C39: =NPV(C34,C28:G28)
B40: Internal Rate of Return (IRR) | C40: =IFERROR(IRR(C28:G28),"N/A")
B41: Payback Period (Years) | C41: =IF(C29>=0,1-((C29-C28)/C28),IF(D29>=0,2-((D29-D28)/D28),IF(E29>=0,3-((E29-E28)/E28),IF(F29>=0,4-((F29-F28)/F28),IF(G29>=0,5-((G29-G28)/G28),"N/A")))))
B45: BENEFITS BY LEVER (Annual Steady State)
B47: Lever Group | C47: Lifecycle Stage | D47: Annual Benefit
B48: L1 — Digital Membership Origination | C48: acquire | D48: ='Journey Analysis'!C17
B49: L2 — Digital Loan Origination | C49: acquire | D49: ='Journey Analysis'!C32
B50: L3 — Member Retention | C50: retain | D50: ='Journey Analysis'!C47
B51: L4 — Cross-sell & Product Penetration | C51: expand | D51: ='Journey Analysis'!C61
B52: L5 — Contact Center Cost Avoidance | C52: retain | D52: ='Journey Analysis'!C76
B53: L6 — Branch Cost Avoidance | C53: retain | D53: ='Journey Analysis'!C91
B54: L7 — Employee Enablement | C54: retain | D54: ='Journey Analysis'!C107
B55: L8 — IT Platform Consolidation | C55: other | D55: ='Journey Analysis'!C121
B56: TOTAL | D56: =SUM(D48:D55)

Sheet Journey Analysis
B1: Journey Analysis — Benefit Calculation Chain
B2: Active Scenario: | C2: =IF('Cashflows'!$C$5=1,"Conservative",IF('Cashflows'!$C$5=2,"Moderate","Aggressive")) | D2: (Change on Cashflows sheet)
B3: Each lever: input factors → Baseline (formula) → × Backbase Impact → Annual Benefit. Change scenario on Cashflows to update scenario-linked impacts.
B5: L1 — Digital Membership Origination
B6: Revenue Generation
B7: Digital Membership Conversion Uplift | D7: Revenue
B8: Factor | C8: Value | D8: Unit
B9: App Starts Annual | C9: ='Model Inputs'!C18 | D9: applications/year
B10: Abandonment Rate | C10: ='Model Inputs'!C19 | D10: percentage
B11: Avg Revenue Per Member | C11: ='Model Inputs'!C20 | D11: USD/member/year
B12: Baseline | C12: =C9 * C10 * C11 | D12: USD/year
B13: Backbase Impact | C13: ='Model Inputs'!C21 | D13: % of baseline captured by Backbase
B14: Annual Benefit | C14: =C12*C13 | D14: USD/year (scenario-adjusted)
B17: Total: L1 — Digital Membership Origination | C17: =C14
B20: L2 — Digital Loan Origination
B21: Revenue Generation
B22: Digital Loan Conversion Uplift | D22: Revenue
B23: Factor | C23: Value | D23: Unit
B24: Loan Starts Annual | C24: ='Model Inputs'!C28 | D24: applications/year
B25: Abandonment Rate | C25: ='Model Inputs'!C29 | D25: percentage
B26: Avg Loan Revenue | C26: ='Model Inputs'!C30 | D26: USD/loan/year
B27: Baseline | C27: =C24 * C25 * C26 | D27: USD/year
B28: Backbase Impact | C28: ='Model Inputs'!C31 | D28: % of baseline captured by Backbase
B29: Annual Benefit | C29: =C27*C28 | D29: USD/year (scenario-adjusted)
B32: Total: L2 — Digital Loan Origination | C32: =C29
B35: L3 — Member Retention
B36: Revenue Generation
B37: Churn Reduction via Digital Engagement | D37: Revenue
B38: Factor | C38: Value | D38: Unit
B39: Total Members | C39: ='Model Inputs'!C38 | D39: members
B40: Churn Rate | C40: ='Model Inputs'!C39 | D40: percentage
B41: Avg Revenue Per Member | C41: ='Model Inputs'!C40 | D41: USD/member/year
B42: Baseline | C42: =C39 * C40 * C41 | D42: USD/year
B43: Backbase Impact | C43: ='Model Inputs'!C41 | D43: % of baseline captured by Backbase
B44: Annual Benefit | C44: =C42*C43 | D44: USD/year (scenario-adjusted)
B47: Total: L3 — Member Retention | C47: =C44
B50: L4 — Cross-sell & Product Penetration
B51: Revenue Generation
B52: Product Penetration Uplift | D52: Revenue
B53: Factor | C53: Value | D53: Unit
B54: Total Revenue Annual | C54: ='Model Inputs'!C48 | D54: USD/year
B55: Penetration Uplift Pct | C55: ='Model Inputs'!C49 | D55: percentage
B56: Baseline | C56: =C54 * C55 | D56: USD/year
B57: Backbase Impact | C57: ='Model Inputs'!C50 | D57: % of baseline captured by Backbase
B58: Annual Benefit | C58: =C56*C57 | D58: USD/year (scenario-adjusted)
B61: Total: L4 — Cross-sell & Product Penetration | C61: =C58
B64: L5 — Contact Center Cost Avoidance
B65: Cost Reduction
B66: Digital Self-Service Call Deflection | D66: Cost
B67: Factor | C67: Value | D67: Unit
B68: Deflectable Calls Annual | C68: ='Model Inputs'!C57 | D68: calls/year
B69: Aht Hours | C69: ='Model Inputs'!C58 | D69: hours
B70: Loaded Hourly Rate | C70: ='Model Inputs'!C59 | D70: USD/hour
B71: Baseline | C71: =C68 * C69 * C70 | D71: USD/year
B72: Backbase Impact | C72: ='Model Inputs'!C60 | D72: % of baseline captured by Backbase
B73: Annual Benefit | C73: =C71*C72 | D73: USD/year (scenario-adjusted)
B76: Total: L5 — Contact Center Cost Avoidance | C76: =C73
B79: L6 — Branch Cost Avoidance
B80: Cost Reduction
B81: Digital Migration of Branch Servicing | D81: Cost
B82: Factor | C82: Value | D82: Unit
B83: Deflectable Visits Annual | C83: ='Model Inputs'!C67 | D83: visits/year
B84: Handle Time Hours | C84: ='Model Inputs'!C68 | D84: hours
B85: Loaded Hourly Rate | C85: ='Model Inputs'!C69 | D85: USD/hour
B86: Baseline | C86: =C83 * C84 * C85 | D86: USD/year
B87: Backbase Impact | C87: ='Model Inputs'!C70 | D87: % of baseline captured by Backbase
B88: Annual Benefit | C88: =C86*C87 | D88: USD/year (scenario-adjusted)
B91: Total: L6 — Branch Cost Avoidance | C91: =C88
B94: L7 — Employee Enablement
B95: Cost Reduction
B96: Employee Productivity via Unified Workbench | D96: Cost
B97: Factor | C97: Value | D97: Unit
B98: Branch Fte | C98: ='Model Inputs'!C77 | D98: FTE
B99: Loaded Hourly Rate | C99: ='Model Inputs'!C78 | D99: USD/hour
B100: Annual Hours | C100: ='Model Inputs'!C79 | D100: hours/year
B101: Productivity Gain Pct | C101: ='Model Inputs'!C80 | D101: percentage
B102: Baseline | C102: =C98 * C99 * C100 * C101 | D102: USD/year
B103: Backbase Impact | C103: ='Model Inputs'!C81 | D103: % of baseline captured by Backbase
B104: Annual Benefit | C104: =C102*C103 | D104: USD/year (scenario-adjusted)
B107: Total: L7 — Employee Enablement | C107: =C104
B110: L8 — IT Platform Consolidation
B111: Cost Reduction
B112: Legacy Platform Decommission | D112: Cost
B113: Factor | C113: Value | D113: Unit
B114: Platforms Replaced | C114: ='Model Inputs'!C88 | D114: platforms
B115: Avg Annual Platform Cost | C115: ='Model Inputs'!C89 | D115: USD/year/platform
B116: Baseline | C116: =C114 * C115 | D116: USD/year
B117: Backbase Impact | C117: ='Model Inputs'!C90 | D117: % of baseline captured by Backbase
B118: Annual Benefit | C118: =C116*C117 | D118: USD/year (scenario-adjusted)
B121: Total: L8 — IT Platform Consolidation | C121: =C118
B124: GRAND TOTAL — ALL LEVERS
C125: Annual Benefit
B126: Total Annual Benefit (Scenario-Adjusted, Steady State) | C126: =C17+C32+C47+C61+C76+C91+C107+C121

Sheet Model Inputs
B2: Model Inputs
B3: Blue cells are editable. Change values and the model recalculates.
B5: Active Scenario | C5: =IF('Cashflows'!$C$5=1,"Conservative",IF('Cashflows'!$C$5=2,"Moderate","Aggressive")) | D5: (Change scenario on Cashflows sheet)
B7: BASIC INFORMATION
B8: Input | C8: Value | D8: Conf. | E8: Assumption/Comment | F8: Source
B10: FINANCIAL PARAMETERS
B11: Discount Rate (WACC) | C11: 0.1
B12: Analysis Period (Years) | C12: 5
B13: YoY Growth Rate | C13: 0.04
B15: LEVER GROUP INPUTS
B16: L1 — Digital Membership Origination
B17: Digital Membership Conversion Uplift
B18: App Starts Annual | C18: 197738 | D18: HIGH | E18: Digital account opening starts in 2025 | F18: CLIENT DATA (Jeff — Digital originations 2025)
B19: Abandonment Rate | C19: 0.261 | D19: HIGH | E19: 26.1% of digital membership applications are abandoned | F19: CLIENT DATA (Jeff — 2025 data)
B20: Avg Revenue Per Member | C20: 874 | D20: HIGH | E20: Average revenue per member derived from Q4 2025 financials | F20: DERIVED (NII + Non-Interest Income / 1.5M members)
B21: Backbase Impact | C21: 0.3 | D21: MEDIUM | E21: Backbase Digital Onboarding recovers 30% of abandoned applications through streamlined KYC, pre-population, and mobile-first UX | F21: BENCHMARK
B22: Baseline Annual | C22: =C18 * C19 * C20
B23: Annual Benefit (Steady State) | C23: =C22*C21
B26: L2 — Digital Loan Origination
B27: Digital Loan Conversion Uplift
B28: Loan Starts Annual | C28: 104813 | D28: HIGH | E28: Digital loan application starts in 2025 | F28: CLIENT DATA (Jeff — 2025 data)
B29: Abandonment Rate | C29: 0.302 | D29: HIGH | E29: 30.2% of digital loan applications are abandoned | F29: CLIENT DATA (Jeff — 2025 data)
B30: Avg Loan Revenue | C30: 500 | D30: LOW | E30: Average first-year revenue per loan (interest margin). Loan portfolio $20.3B / ~400K active loans × NIM ~3% ÷ weighted avg life | F30: ESTIMATE
B31: Backbase Impact | C31: 0.25 | D31: MEDIUM | E31: Backbase Lending Origination recovers 25% of abandoned loan applications through pre-qualification, document upload, and real-time decisioning | F31: BENCHMARK
B32: Baseline Annual | C32: =C28 * C29 * C30
B33: Annual Benefit (Steady State) | C33: =C32*C31
B36: L3 — Member Retention
B37: Churn Reduction via Digital Engagement
B38: Total Members | C38: 1500000 | D38: HIGH | E38: Total retail members | F38: CLIENT DATA (BECU 2024 Annual Report)
B39: Churn Rate | C39: 0.045 | D39: MEDIUM | E39: 4.5% annual member attrition rate | F39: CLIENT DATA
B40: Avg Revenue Per Member | C40: 874 | D40: HIGH | E40: From Q4 2025 financials | F40: DERIVED
B41: Backbase Impact | C41: 0.15 | D41: LOW | E41: Backbase reduces churn by 15% through improved digital engagement, financial wellness tools, and proactive retention campaigns. Churn has structural causes (relocation, life events) so digital can only address a portion. | F41: BENCHMARK
B42: Baseline Annual | C42: =C38 * C39 * C40
B43: Annual Benefit (Steady State) | C43: =C42*C41
B46: L4 — Cross-sell & Product Penetration
B47: Product Penetration Uplift
B48: Total Revenue Annual | C48: 1310700000 | D48: HIGH | E48: Total annual revenue (NII + non-interest income) | F48: CLIENT DATA (Q4 2025 Statement)
B49: Penetration Uplift Pct | C49: 0.02 | D49: LOW | E49: 2% revenue uplift from improved cross-sell. Conservative: only 30% CC penetration, 9% auto loan, 1% investment — significant room for digital product bundling | F49: BENCHMARK
B50: Backbase Impact | C50: 0.2 | D50: LOW | E50: Backbase Digital Engage NBA engine and onboarding cross-sell captures 20% of addressable product penetration opportunity | F50: BENCHMARK
B51: Baseline Annual | C51: =C48 * C49
B52: Annual Benefit (Steady State) | C52: =C51*C50
B55: L5 — Contact Center Cost Avoidance
B56: Digital Self-Service Call Deflection
B57: Deflectable Calls Annual | C57: 1126128 | D57: MEDIUM | E57: 39.2% of 2.87M annual calls are deflectable (Deposit Servicing 22,592 + Banking Access 21,068 + Balance Inquiries 12,282 + Transfers 6,482 = 62,424/mo × 12 + Debit Servicing 11,441 × 12 = ~887K + Online Banking 10,555 × 12 = ~127K → ~1.13M) | F57: DERIVED
B58: Aht Hours | C58: 0.1206 | D58: HIGH | E58: Overall AHT 434 seconds = 0.1206 hours | F58: CLIENT DATA
B59: Loaded Hourly Rate | C59: 46.15 | D59: HIGH | E59: Fully loaded blended hourly rate for contact center agents | F59: CLIENT DATA
B60: Backbase Impact | C60: 0.35 | D60: MEDIUM | E60: Backbase self-service deflects 35% of deflectable calls through digital servicing, account maintenance, and FAQ self-service. Chatbot currently at 56.5% containment on 58.6K sessions — Backbase Engage extends this to transactional self-service. | F60: BENCHMARK
B61: Baseline Annual | C61: =C57 * C58 * C59
B62: Annual Benefit (Steady State) | C62: =C61*C60
B65: L6 — Branch Cost Avoidance
B66: Digital Migration of Branch Servicing
B67: Deflectable Visits Annual | C67: 750000 | D67: MEDIUM | E67: 50% of 1.5M annual branch visits are deflectable (account inquiries 101K/mo × 12 = 1.21M, minus complex ones). Account inquiries are largest branch visit category. | F67: DERIVED
B68: Handle Time Hours | C68: 0.2567 | D68: HIGH | E68: 15:25 average service time = 0.2567 hours | F68: CLIENT DATA
B69: Loaded Hourly Rate | C69: 46.15 | D69: MEDIUM | E69: Using same loaded rate as contact center; branch FTE may differ | F69: ESTIMATE
B70: Backbase Impact | C70: 0.22 | D70: MEDIUM | E70: Backbase digital servicing migrates 22% of deflectable branch visits to self-service. Conservative — many branch visits are relationship-driven (12% new account, 8% loans). | F70: BENCHMARK
B71: Baseline Annual | C71: =C67 * C68 * C69
B72: Annual Benefit (Steady State) | C72: =C71*C70
B75: L7 — Employee Enablement
B76: Employee Productivity via Unified Workbench
B77: Branch Fte | C77: 632.7 | D77: HIGH | E77: Branch employees as of year end 2025 | F77: CLIENT DATA (Retail Workforce Team)
B78: Loaded Hourly Rate | C78: 46.15 | D78: MEDIUM | E78: Blended loaded hourly rate | F78: ESTIMATE
B79: Annual Hours | C79: 2080 | D79: HIGH | E79: Standard 40hr/week × 52 weeks | F79: STANDARD
B80: Productivity Gain Pct | C80: 0.2 | D80: LOW | E80: 20% productivity gain from eliminating 30-50 app context switches (pain point: 30-50 applications per transaction), providing unified Member 360 view (currently unavailable), and reducing 12-week new hire training time | F80: BENCHMARK
B81: Backbase Impact | C81: 0.15 | D81: LOW | E81: Backbase Employee Workbench captures 15% of productivity gain. Unified interface replaces multi-app workflow but behavioral change and adoption limit early impact. | F81: BENCHMARK
B82: Baseline Annual | C82: =C77 * C78 * C79 * C80
B83: Annual Benefit (Steady State) | C83: =C82*C81
B86: L8 — IT Platform Consolidation
B87: Legacy Platform Decommission
B88: Platforms Replaced | C88: 3 | D88: HIGH | E88: Corillian (Replace), MX Mobile (Replace), Mulesoft ESB (Retire → Azure APIM) | F88: CLIENT DATA (IT-App Rationalization)
B89: Avg Annual Platform Cost | C89: 1000000 | D89: LOW | E89: Average annual cost per platform (license + maintenance + integration support). No actual license costs provided in questionnaire — CRITICAL DATA GAP. | F89: ESTIMATE
B90: Backbase Impact | C90: 0.45 | D90: MEDIUM | E90: Backbase replaces Corillian and MX directly (high capture), Mulesoft ESB partially replaced by Backbase integration layer. 45% reflects that some costs persist during parallel-run period. | F90: BENCHMARK
B91: Baseline Annual | C91: =C88 * C89
B92: Annual Benefit (Steady State) | C92: =C91*C90
B96: ACTIVE BACKBASE IMPACTS (auto-selected from scenario)
B97: Branch Deflection | C97: =INDEX('Scenario Data'!$C$24:$E$24,1,'Cashflows'!$C$5)
B98: Call Deflection | C98: =INDEX('Scenario Data'!$C$25:$E$25,1,'Cashflows'!$C$5)
B99: Churn Reduction | C99: =INDEX('Scenario Data'!$C$26:$E$26,1,'Cashflows'!$C$5)
B100: Cross Sell Uplift | C100: =INDEX('Scenario Data'!$C$27:$E$27,1,'Cashflows'!$C$5)
B101: Employee Productivity | C101: =INDEX('Scenario Data'!$C$28:$E$28,1,'Cashflows'!$C$5)
B102: It Consolidation | C102: =INDEX('Scenario Data'!$C$29:$E$29,1,'Cashflows'!$C$5)
B103: Loan Conversion | C103: =INDEX('Scenario Data'!$C$30:$E$30,1,'Cashflows'!$C$5)
B104: Membership Conversion | C104: =INDEX('Scenario Data'!$C$31:$E$31,1,'Cashflows'!$C$5)
B107: INVESTMENT
B108: License
B109: Year 1 | C109: 1000000
B110: Year 2 | C110: 1000000
B111: Year 3 | C111: 1000000
B112: Year 4 | C112: 1000000
B113: Year 5 | C113: 1000000
B115: Implementation
B116: Year 1 | C116: 500000
B117: Year 2 | C117: 500000
B118: Year 3 | C118: 500000
B119: Year 4 | C119: 500000
B120: Year 5 | C120: 500000
B123: ACTIVE CURVES (auto-selected from scenario)
B124: These cells use INDEX formulas — they update when you change the scenario on the Cashflows sheet.
B125: Default — Implementation
B126: Year 1 | C126: =INDEX('Scenario Data'!$C$9:$E$9,1,'Cashflows'!$C$5)
B127: Year 2 | C127: =INDEX('Scenario Data'!$C$10:$E$10,1,'Cashflows'!$C$5)
...

Sheet Scenario Data
B2: Scenario Definitions
B3: Edit values here to customize scenarios. All lever sheets reference this table.
B5: Parameter | C5: Conservative | D5: Moderate | E5: Aggressive
B7: IMPLEMENTATION CURVES
B8: Default
B9: Year 1 | C9: 0.1 | D9: 0.2 | E9: 0.3
B10: Year 2 | C10: 0.35 | D10: 0.55 | E10: 0.7
B11: Year 3 | C11: 0.6 | D11: 0.8 | E11: 0.9
B12: Year 4 | C12: 0.8 | D12: 0.95 | E12: 1
B13: Year 5 | C13: 0.9 | D13: 1 | E13: 1
B15: EFFECTIVENESS CURVES
B16: Default
B17: Year 1 | C17: 0.15 | D17: 0.25 | E17: 0.35
B18: Year 2 | C18: 0.35 | D18: 0.5 | E18: 0.6
B19: Year 3 | C19: 0.55 | D19: 0.75 | E19: 0.85
B20: Year 4 | C20: 0.7 | D20: 0.9 | E20: 0.95
B21: Year 5 | C21: 0.85 | D21: 1 | E21: 1
B23: BACKBASE IMPACTS
B24: Branch Deflection | C24: 0.12 | D24: 0.22 | E24: 0.35
B25: Call Deflection | C25: 0.2 | D25: 0.35 | E25: 0.5
B26: Churn Reduction | C26: 0.08 | D26: 0.15 | E26: 0.2
B27: Cross Sell Uplift | C27: 0.1 | D27: 0.2 | E27: 0.3
B28: Employee Productivity | C28: 0.08 | D28: 0.15 | E28: 0.25
B29: It Consolidation | C29: 0.25 | D29: 0.45 | E29: 0.55
B30: Loan Conversion | C30: 0.12 | D30: 0.25 | E30: 0.35
B31: Membership Conversion | C31: 0.15 | D31: 0.3 | E31: 0.45

Sheet Bank Profile
B1: Bank Profile
B3: BANK IDENTITY
B4: Bank Name | C4: BECU
B5: Country
B6: Currency | C6: USD
B7: Stock Ticker | C7: N/A
B8: Report Year
B9: Data Sources
B11: Market Context Status | C11: NOT_RUN
B13: KEY FINANCIAL METRICS
B14: Metric | C14: Value | D14: Confidence | E14: Source

Sheet Assumptions
B1: Assumptions Register
B3: All assumptions documented with sources and validation owners
B5: ID | C5: Assumption | D5: Value | E5: Conf. | F5: Source | G5: Owner | H5: Sensitivity
B6: A1 | C6: Total members remain at ~1.5M for baseline year | D6: 1,500,000 | E6: HIGH | F6: BECU 2024 Annual Report
B7: A2 | C7: Average revenue per member = $874 | D7: $874 | E7: HIGH | F7: Derived: ($1,094.5M NII + $216.3M non-interest) / 1.5M members
B8: A3 | C8: Member churn rate = 4.5% | D8: 4.5% | E8: MEDIUM | F8: CLIENT DATA
B9: A4 | C9: Digital onboarding abandonment rate = 26.1% | D9: 26.1% | E9: HIGH | F9: CLIENT DATA (Jeff — 2025)
B10: A5 | C10: Loan application abandonment rate = 30.2% | D10: 30.2% | E10: HIGH | F10: CLIENT DATA (Jeff — 2025)
B11: A6 | C11: Contact center AHT = 434 seconds | D11: 434 sec | E11: HIGH | F11: CLIENT DATA — Member Services 2025
B12: A7 | C12: Loaded hourly rate = $46.15/hr | D12: $46.15 | E12: HIGH | F12: CLIENT DATA
B13: A8 | C13: Investment estimate = $20M | D13: $20M | E13: LOW | F13: ESTIMATE — no Backbase pricing
B14: A9 | C14: Average loan revenue = $500/loan/year | D14: $500 | E14: LOW | F14: ESTIMATE
B15: A10 | C15: IT platform cost = $1M/platform/year | D15: $1M | E15: LOW | F15: ESTIMATE
B16: A11 | C16: Discount rate = 10% | D16: 10% | E16: HIGH | F16: Standard WACC for credit unions
B17: A12 | C17: 4% YoY member growth rate | D17: 4% | E17: HIGH | F17: BECU 2024 Annual Report

Sheet Data Gaps
B1: Data Gaps — Required for Validation
B3: These data points are CRITICAL for validating the ROI model.
B5: ID | C5: Data Needed | D5: Priority | E5: Source | F5: Impact on Model
B6: DG-001 | D6: CRITICAL | F6: Determines break-even and ROI
B7: DG-002 | D7: HIGH | F7: L8 IT Consolidation lever accuracy
B8: DG-003 | D8: MEDIUM | F8: Potential additional cost avoidance lever
B9: DG-004 | D9: MEDIUM | F9: L4 cross-sell baseline accuracy
B10: DG-005 | D10: HIGH | F10: L2 loan origination lever accuracy
B11: DG-006 | D11: MEDIUM | F11: Could add activation lever
