Workbook
Name xrate: #REF!

Sheet Cover Page
C13: Return on Investment Calculator
C16: Client Name: | D16: Seabank
C18: Date: | D18: 45809
C21: Value Consulting - Business Case

Sheet Instructions
B1: Return on Investment Instructions
C3: Overview: | D3: This tool will be used to derive the Return on investment (ROI) for purchasing and implementing Backbase as a solution for the bank. Backbase value consulting team will use this ROI calculation tool to develop a business case for a given engagement.
C4: Purpose: | D4: ROI is a performance measure used to evaluate the efficiency and profitability of an investment through directly measuring the amount of return on a particular investment. In other words ROI shows how well an investment has performed, relative to the cost of it. We have developed this model to standardize the approach for calculating ROI and reducing efforts due to the interlinked functionalities between sheets, therefore, users will spend less time building the necessary analysis, rather inputs would be inserted in given cells and the sheet will automatically calculate the final ROI.
C5: Who should use this tool | D5: This tool is expected to be filled and used by value consulting team members
C6: Cell Instructions and Legends | D6: The ROI tool is designed to help end users calculate the return on investment for implementing backbase as a solution. This model aims save time and effort while calculating the final ROI for a potential opportunity. The way to use the this model is explained below: The sheet structure is of two main categories "Inputs" and "Analysis". In the inputs sections, it is expected to be manually filled in order to populate the analysis. Hence, the Analysis sections is automatically populated. Inputs are often gathered during or after a workshop session, however, some inputs follow an assumption based approach. In the "Inputs" section, there will be three legends introduced in order to differentiate between types of inputs as follows: A- "Required information" this field is information given by the customer during or after conducting the workshop session. B- "Calculated Information" this field is automatically generated through a specific formula. D- "Assumption" this field will be assumed by the user based on best practice experience.
C7: Sheet Instructions | D7: Input Sheet | E7: First section in "input" sheet will cover information about the customer such as name, revenue and industry. Second section in "input" sheet covers Backbase loading and effectiveness on customer value drivers, loyalty, retention, and customer servicing. The inputs in this section are based on educated assumptions that should be backed by a sane market study and previous engagements. Third section in "input" sheet covers inputs and assumptions pertaining to potential cost reduction due to digital implementation (reduction in physical channel visits) and revenue generation (through customer conversion, loyalty, and retention). For this section to be filled, workshops have to be conducted with the client in order to derive the needed information.
D8: Cost Reduction and Revenue Generation Sheet | E8: In this section, a detailed analysis of all inputs from the previous section "Input" sheet will be displayed. This sheet will provide a breakdown view of the following details: - Value drivers behind cost reduction in customer acquisition, loan origination, and customer servicing - Value drivers behind revenue generation in customer acquisition and loan origination. Note: this sheet will be automatically generated.
D9: Servicing-Subsection Sheet | E9: This sheet will provide a breakdown view of customer servicing details. According to customer inputs and best practices, the type of services will be displayed in a list under 3 journeys: - Branch - Call Center - Back-office Note: this sheet will be automatically generated.
D10: Cash Flows Sheet | E10: In the "Cash Flows" section a final calculation of cash flows "cash inflows and cash outflows" followed by Payback period, Net present Value, Return on Investment, and Internal Rate of Return will presented. Note: this sheet will automatically generate the aforementioned outputs based on all the inputs from "input" sheet.

Sheet Table of Contents
B3: Table of Contents
B5: Section 1 | C5: Results Dashboard
C6: Return on Investment
C7: Net Present Value
C8: Payback Period
B9: Section 2 | C9: Value Driver Inputs
C10: Customer Onboarding
C11: Loan Origination
C12: Loyalty and Retention
C13: Servicing Inputs
B14: Section 3 | C14: Value Driver Analysis
C15: Customer Onboarding
C16: Loan Origination
C17: Loyalty and Retention
B18: Section 4 | C18: Servicing Analysis
C19: Branch
C20: Call Center
C21: Back Office
C22: Impact on Customer Onboarding
B23: Section 5 | C23: IT Cost Savings - Estimation & Analysis
C24: Impact on Loan Origination
C25: Impact on Loyalty and Retention
C26: Impact on Customer Servicing
B27: Section 6 | C27: Cash Flows
C28: Projection Inflows
C29: Projection Outflows
C30: Return on Investment
C31: Net Present Value
C32: Payback Period

Sheet Results Dashboard
B2: Financial Metrics 5 Year Projections
E5: Revenues | R5: Costs
B6: Return on Investment (ROI)
B7: ='Cashflows - Analysis'!N14 -> 29274570
B12: Net Present Value (NPV)
B13: ='Cashflows - Analysis'!N13 -> 4054730.8
B17: Internal Rate of Return (IRR)
B18: ='Cashflows - Analysis'!N21 -> 0.45666217
B24: Payback Period in Years
B25: ='Cashflows - Analysis'!N20 -> 1.7279603

Sheet Customer Phases - Inputs and As
B2: Backbase VC - Business Case
B3: Customer Phases - Inputs and Assumptions
C5: Required info
C6: Calculation
C7: Assumptions / Backbase benchmarks | F7: CCurr
B11: Basic Information
B12: Initial Data
B13: Customer Name | C13: Seabank | E13: Ave. revenue / customer | F13: 39.87 | H13: Product Penetration | I13: 2.53
B14: Industry | C14: Banking | E14: Average FTE rate/ hour | F14: =(I14/F16)/(250*8) -> 8.0103948 | H14: Total Staff Costs | I14: ='Annual report data'!J23 -> 84349457
B15: Revenue 2024 | C15: ='Annual report data'!E11 -> 11078105 | E15: Total customers | F15: 3656262
B16: currency conversion rate (VND to USD) | C16: =1/'Annual report data'!E7 -> 3.99106e-05 | E16: Total FTE | F16: 5265
B19: Backbase Loading and Effectiveness on Customer/Loan Acquisition | I19: Backbase Loading and Effectiveness on Customer Servicing
C20: Year 1 | D20: Year 2 | E20: Year 3 | F20: Year 4 | G20: Year 5 | J20: Year 1 | K20: Year 2 | L20: Year 3 | M20: Year 4 | N20: Year 5
B21: Backbase Implementation | C21: 0.3 | D21: 0.7 | E21: 0.8 | F21: 1 | G21: 1 | I21: Backbase Implementation | J21: 0.3 | K21: 0.7 | L21: 0.8 | M21: 1 | N21: 1
B22: Backbase Effectiveness (Adoption Rate) | C22: 0.15 | D22: 0.35 | E22: 0.6 | F22: 0.85 | G22: 1 | I22: Backbase Effectiveness (Adoption Rate) | J22: 0.15 | K22: 0.35 | L22: 0.6 | M22: 0.85 | N22: 1
B23: Year on Year Growth | C23: 0.15 | D23: 0.15 | E23: 0.15 | F23: 0.15 | G23: 0.15 | I23: Year on Year Growth | J23: 0.08 | K23: 0.08 | L23: 0.08 | M23: 0.08 | N23: 0.08
B25: Backbase Loading and Effectiveness on Customer Churn | I25: Backbase Loading and Effectiveness on Product Penetration
C26: Year 1 | D26: Year 2 | E26: Year 3 | F26: Year 4 | G26: Year 5 | J26: Year 1 | K26: Year 2 | L26: Year 3 | M26: Year 4 | N26: Year 5
B27: Backbase Implementation | C27: 0.3 | D27: 0.7 | E27: 0.8 | F27: 1 | G27: 1 | I27: Backbase Implementation | J27: 0.3 | K27: 0.7 | L27: 0.8 | M27: 1 | N27: 1
B28: Backbase Effectiveness (Adoption Rate) | C28: 0.15 | D28: 0.35 | E28: 0.6 | F28: 0.85 | G28: 1 | I28: Backbase Effectiveness (Adoption Rate) | J28: 0.15 | K28: 0.35 | L28: 0.6 | M28: 0.85 | N28: 1
B29: Year on Year Growth | C29: 0.1 | D29: 0.1 | E29: 0.1 | F29: 0.1 | G29: 0.1 | I29: Year on Year Growth | J29: 0.08 | K29: 0.08 | L29: 0.08 | M29: 0.08 | N29: 0.08
W30: total CCs | X30: 273000
B33: Customer Onboarding (CASA) | E33: USL Loan Acquisition | H33: Loyalty & Retention | K33: CLO | N33: Servicing Journey Names: Retail and SME
B35: Increase Customer Conversion in website | E35: Increase Customer Conversion in website | H35: Improve Customer Churn | K35: Activation / Dormancy Reduction | N35: Branch | Q35: Call Center | S35: Back-Office | U35: Impact
B36: Customers that start onboarding | C36: =153108+361339 -> 514447 | D36: From Sebank: Android: 153,108 IOS: 361,339 | E36: Intent to Purchase Lending Product (personal loans) | F36: =F74*3 -> 24129 | G36: Assumption: 3x total new customers | H36: Total number of current active customers | I36: =F15*12% -> 438751.44 | J36: Seabank data | K36: Total Number of New Customers | L36: =C73 -> 609377 | N36: Service | O36: Volume | P36: Time Spent in HR | Q36: Volume | R36: Time Spent in HR | S36: Volume | T36: Time Spent in HR | U36: Backbase Impact | V36: Notes | W36: Assumption: Volumes in branch taken for comparable VN bank; capped at 70% accounting for difference in # of branches and customer base | Y36: Assumption: 5x of actual customers ordered CC online
B37: Current Customer Leakage (%) - includes Activation leakage | C37: =1-((65699+52075)/C36) -> 0.7710668 | D37: Data from Seabank: Q4/2024: 52,075 user 2025: 65,699 user | E37: Current Customer Leakage (%) | F37: =1-(F74/F36) -> 0.66666667 | H37: Customer Churn | I37: 0.02 | J37: Seabank data | K37: Current Activation Rate | L37: =18% -> 0.18 | M37: From SeABank | N37: Accounts & Balance | O37: =150241*70% -> 105168.7 | P37: 0.08 | Q37: =1560*12 -> 18720 | R37: ='Extra Tables Parking lot'!F15 -> 0.083333333 | S37: ='Extra Tables Parking lot'!G15 -> 0 | T37: ='Extra Tables Parking lot'!H15 -> 0 | U37: 0.35 | V37: Volumes in branch assumed for lack of accurate data from Seabank | W37: =O37/$O$55 -> 0.1306192 | X37: =Q37/$Q$55 -> 0.22306959
B38: Average Income per Customer | C38: =F13 -> 39.87 | D38: From seabank | E38: Average Income per Customer | F38: =F13 -> 39.87 | H38: Average Income per Customer | I38: =F13 -> 39.87 | K38: Number of inactive customers | L38: =L36*(1-L37) -> 499689.14 | N38: Account Statement | O38: =107315*70% -> 75120.5 | P38: 0.17 | R38: ='Extra Tables Parking lot'!F16 -> 0.16666667 | S38: ='Extra Tables Parking lot'!G16 | T38: ='Extra Tables Parking lot'!H16 | U38: 0.4 | V38: Volumes in branch assumed for lack of accurate data from Seabank | W38: =O38/$O$55 -> 0.093299427 | X38: =Q38/$Q$55 -> 0
B39: Backbase Impact | C39: =10%*75% -> 0.075 | D39: Assumption: Integrated digital onboarding solution (with A/C funding will remove friction in the onboarding process across branch/digital channels) | E39: Backbase Impact | F39: =20%*75% -> 0.15 | H39: Backbase Impact | I39: =10%*75% -> 0.075 | K39: Backbase Impact | L39: 0.15 | N39: Transaction Dispute | O39: =76839*70% -> 53787.3 | P39: 0.33 | Q39: =400*12 -> 4800 | R39: ='Extra Tables Parking lot'!F17 -> 0.25 | T39: ='Extra Tables Parking lot'!H17 -> 0.75 | U39: 0.4 | V39: Volumes in branch assumed for lack of accurate data from Seabank | W39: =O39/$O$55 -> 0.066803659 | X39: =Q39/$Q$55 -> 0.057197331
N40: Transfers | O40: =148653*(12/5) -> 356767.2 | P40: =10/60 -> 0.16666667 | Q40: =940*12 -> 11280 | R40: ='Extra Tables Parking lot'!F18 -> 0.083333333 | S40: ='Extra Tables Parking lot'!G18 -> 0 | T40: ='Extra Tables Parking lot'!H18 -> 0 | U40: 0.1 | V40: Data from seabank | W40: =O40/$O$55 -> 0.44310375
B41: Increase Customer Conversion in Direct (Branch) Sales - Branch onboarding | E41: Increase Customer Conversion in Direct (Branch) Sales. Branch Lending Origination | H41: Increase Product Penetration | K41: Product Cross / Upsell | N41: internal transfers | Q41: ='Extra Tables Parking lot'!E19 -> 0 | R41: ='Extra Tables Parking lot'!F19 -> 0.16666667 | S41: ='Extra Tables Parking lot'!G19 -> 0 | T41: ='Extra Tables Parking lot'!H19 -> 0.083333333 | U41: 0.1 | W41: =O41/$O$55 -> 0 | X41: =Q41/$Q$55 -> 0
B42: No of Visits/Year | C42: =(193177/80%) -> 241471.25 | D42: Of 193K accounts opened in branch, there is 20% leakage i.e., 5-10% customers who failed to open because they did not like the process and 5-10% that inquired but were not interested in a product | E42: No of Visits/Year | F42: =(F73-F74)*2 -> 103600 | G42: Assumption: 2x new loans | H42: Total number of current customers | I42: =F15 -> 3656262 | K42: Total Customer Base | L42: =F15 -> 3656262 | N42: Debit Card Ordering | O42: =3162*(12/5) -> 7588.8 | P42: =15/60 -> 0.25 | Q42: =90*12 -> 1080 | R42: ='Extra Tables Parking lot'!F20 -> 0.16666667 | T42: ='Extra Tables Parking lot'!H20 -> 0.5 | U42: 0.35 | V42: Data from seabank | W42: =O42/$O$55 -> 0.0094252659 | X42: =Q42/$Q$55 -> 0.012869399
B43: Current Customer Leakage (%) - Activation leakage | C43: 0.2 | D43: Assumption | E43: Current Customer Leakage (%) | F43: =(F73-F74)/F42 -> 0.5 | H43: Digital Inactive Customers | I43: =F15-I36 -> 3217510.6 | K43: of which, already purchase 2nd product | L43: =18% -> 0.18 | M43: Assumption, 18% of active base would already buy the second product | N43: Card block | O43: =1638*70% -> 1146.6 | P43: 0.17 | Q43: =440*12 -> 5280 | R43: ='Extra Tables Parking lot'!F21 -> 0.083333333 | S43: ='Extra Tables Parking lot'!G21 -> 0 | T43: ='Extra Tables Parking lot'!H21 -> 0 | U43: 0.2 | V43: Volumes in branch assumed for lack of accurate data from Seabank | W43: =O43/$O$55 -> 0.0014240736 | X43: =Q43/$Q$55 -> 0.062917064 | Y43: Customers who were rejected or dropped out of the process
B44: Average Income per Customer | C44: =F13 -> 39.87 | E44: Average Income per Customer | F44: =F38 -> 39.87 | H44: Average Income per Additional Product | I44: =($C$38*(9/10)+$F$38*(1/10))/2 -> 19.935 | J44: Assumption: for every 10 deposit products sold, 1 loan product is sold | K44: Income per additional product | L44: =I44 -> 19.935 | M44: Assumption: for every 10 deposit products sold, 1 loan product is sold | N44: Cards PIN reset | O44: =1092*70% -> 764.4 | P44: 0.17 | Q44: =120*12 -> 1440 | R44: ='Extra Tables Parking lot'!F22 -> 0.083333333 | S44: ='Extra Tables Parking lot'!G22 -> 0 | T44: ='Extra Tables Parking lot'!H22 -> 0 | U44: 0.2 | V44: Volumes in branch assumed for lack of accurate data from Seabank | W44: =O44/$O$55 -> 0.00094938242 | X44: =Q44/$Q$55 -> 0.017159199
B45: Backbase Impact | C45: =10%*75% -> 0.075 | D45: Assumption: Due to better CX , 5% customers activate | E45: Backbase Impact | F45: =10%*75% -> 0.075 | G45: Based on backbase impact in increasing origination at comparable banks; global average | H45: Backbase Impact | I45: =5%*75% -> 0.0375 | J45: Bundled products during onboarding | K45: Backbase Impact | L45: 0.05 | M45: Impact assumption: 0.3-0.5 additional product are sold per customer, given current penetration at 2.53 | N45: Card limit change | O45: =8736*70% -> 6115.2 | P45: 0.17 | Q45: =120*12 -> 1440 | R45: ='Extra Tables Parking lot'!F23 -> 0.16666667 | T45: ='Extra Tables Parking lot'!H23 -> 0.5 | U45: 0.35 | V45: Volumes in branch assumed for lack of accurate data from Seabank | W45: =O45/$O$55 -> 0.0075950593 | X45: =Q45/$Q$55 -> 0.017159199 | Y45: Assumption: integrated digital loan origination solution will help employee to service prospects more efficiently, and increase conversion.
N46: Credit card order request | Q46: ='Extra Tables Parking lot'!E24 -> 7000 | R46: ='Extra Tables Parking lot'!F24 -> 0.25 | T46: ='Extra Tables Parking lot'!H24 -> 0.5 | U46: 0.35 | V46: Data from seabank | W46: =O46/$O$55 -> 0 | X46: =Q46/$Q$55 -> 0.083412774
B47: Reduce Branch Visits | E47: Reduce Branch Visits | H47: FTE Hourly Rate $ | K47: Marketing Efficiency | N47: Deposit products enquiry | Q47: =150*12 -> 1800 | R47: ='Extra Tables Parking lot'!F25 -> 0.083333333 | S47: ='Extra Tables Parking lot'!G25 -> 0 | T47: ='Extra Tables Parking lot'!H25 -> 0 | U47: 0.35 | V47: Data from seabank | W47: =O47/$O$55 -> 0 | X47: =Q47/$Q$55 -> 0.021448999
B48: No of Visits/Calls/Tasks/Year | C48: =C42 -> 241471.25 | E48: No of Visits/Calls/Tasks/Year | F48: =F42 -> 103600 | G48: Assumption: ±1/3 loans was actually approved/disbursed; = branch walk-ins x3 of approved loans. | K48: Number of Marketing FTE | L48: 15 | M48: Assumption | N48: Bill payments | O48: =1248*(12/5) -> 2995.2 | P48: =10/60 -> 0.16666667 | Q48: =60*12 -> 720 | R48: ='Extra Tables Parking lot'!F26 -> 0.16666667 | S48: ='Extra Tables Parking lot'!G26 -> 0 | T48: ='Extra Tables Parking lot'!H26 -> 0 | U48: 0.1 | V48: Volumes in branch assumed for lack of accurate data from Seabank | W48: =O48/$O$55 -> 0.0037200291 | Y48: Assumption: ±1/3 loans was actually approved/disbursed; = branch walk-ins x3 of approved loans.
B49: Average Time Spent /Interaction (hours) | C49: =20/60 -> 0.33333333 | D49: Assuming 20 mins, 15 mins for account opening + time spent to consult & potential wait time | E49: Average Time Spent per Interaction (hours) | F49: =40/60 -> 0.66666667 | G49: Total average processing time per one personal loan disbursed. | H49: =F14 -> 8.0103948 | K49: Cost/FTE | L49: =I14/F16 -> 16020.79 | N49: International Transfers | O49: =462*(12/5) -> 1108.8 | P49: =30/60 -> 0.5 | Q49: =20*12 -> 240 | R49: ='Extra Tables Parking lot'!F27 -> 0.083333333 | T49: ='Extra Tables Parking lot'!H27 -> 0.25 | U49: 0.2 | V49: Volumes in branch assumed for lack of accurate data from Seabank | W49: =O49/$O$55 -> 0.0013771261 | X49: =Q49/$Q$55 -> 0.0028598665 | Y49: Total average processing time per one personal loan disbursed.
B50: Average FTE Costs per Hour (USD) | C50: =F14 -> 8.0103948 | D50: Calculated | E50: Average FTE Costs per Hour (USD) | F50: =F14 -> 8.0103948 | H50: Hour to Mins | I50: 60 | K50: Backbase Impact | L50: 0.35 | M50: Reduction in effort of manual campaign planning | N50: Customer Details Update / KYC details | O50: =86889*70% -> 60822.3 | P50: 0.17 | Q50: =140*12 -> 1680 | R50: ='Extra Tables Parking lot'!F28 -> 0.16666667 | S50: ='Extra Tables Parking lot'!G28 -> 0 | T50: ='Extra Tables Parking lot'!H28 -> 0 | U50: 0.35 | V50: Volumes in branch assumed for lack of accurate data from Seabank | W50: =O50/$O$55 -> 0.075541107 | X50: =Q50/$Q$55 -> 0.020019066
B51: Backbase Impact | C51: 0.3 | D51: 30% customers move to digital | E51: Backbase Impact | F51: 0.3 | G51: Assuming 30% move to digital | N51: Credit card info inquiry (& other CC servicing) | Q51: =1200*12 -> 14400 | R51: ='Extra Tables Parking lot'!F29 -> 0.16666667 | S51: ='Extra Tables Parking lot'!G29 -> 0 | T51: ='Extra Tables Parking lot'!H29 -> 0 | U51: 0.35 | V51: Data from seabank | W51: =O51/$O$55 -> 0 | X51: =Q51/$Q$55 -> 0.17159199 | Y51: Assuming 30% move to digital
N52: Loan Servicing | O52: =191100*70% -> 133770 | P52: 0.25 | Q52: =1170*12 -> 14040 | R52: ='Extra Tables Parking lot'!F30 -> 0.16666667 | T52: ='Extra Tables Parking lot'!H30 -> 0.25 | U52: 0.35 | V52: Volumes in branch assumed for lack of accurate data from Seabank | W52: =O52/$O$55 -> 0.16614192 | X52: =Q52/$Q$55 -> 0.16730219
B53: Reduce effort @ branch visits | E53: Reduce effort @ branch visits
B54: No of Visits/Year | C54: =C48 -> 241471.25 | E54: No of Visits/Calls/Tasks/Year | F54: =F73-F74 -> 51800
B55: Average Time Spent /Interaction (hours) | C55: =C49 -> 0.33333333 | E55: Average Time Spent per Interaction (hour) | F55: =40/60 -> 0.66666667 | N55: Total | O55: =SUM(O37:O53) -> 805155 | Q55: =sum(Q37:Q53) -> 83920 | S55: =sum(S37:S53) -> 0
B56: Average FTE Costs per Hour (USD) | C56: =C50 -> 8.0103948 | E56: Average FTE Costs per Hour (USD) | F56: =F14 -> 8.0103948
B57: Backbase Impact | C57: 0.2 | D57: Manual data entry effort | E57: Backbase Impact | F57: 0.2 | N57: Calls per customer | O57: =Q55/F15 -> 0.022952403
N58: Branch visits per customer | O58: =O55/F15 -> 0.22021261
B59: Reduce Call Center Calls for Deposit products - Cost Avoidance Lever | E59: Reduce Call Center Calls for Lending products - Cost Avoidance Lever | N59: Back office tasks per customer | O59: =S55/F15 -> 0
B60: No of Visits/Calls/Tasks/Year | C60: 0 | D60: NA | E60: No of Visits/Calls/Tasks/Year | G60: assuming 0.56 calls per application | W60: No of Visits/Calls/Tasks/Year | Y60: assuming 0.56 calls per application
B61: Average Time Spent per Interaction (hour) | C61: 0 | E61: Average Time Spent per Interaction (hour) | W61: Average Time Spent per Interaction (hour)
B62: Average FTE Costs per Hour (USD) | C62: =F14 -> 8.0103948 | E62: Average FTE Costs per Hour (USD) | W62: Average FTE Costs per Hour (USD)
B63: Backbase Impact | C63: 0 | D63: Prospects can differentiate and compare between the products easier during an integrated onboarding journey online, reducing number of inquiry calls | E63: Backbase Impact | F63: 0.45 | G63: Prospects can track and trace application online, thus reducing calls to customer care | W63: Backbase Impact | Y63: Prospects can track and trace application online, thus reducing calls to customer care
B65: Reduce Back Office Tasks for Deposit products - Cost Avoidance Lever | E65: Reduce Back Office Tasks for Lending products - Cost Avoidance Lever | W65: Reduce Back Office Tasks for CC products - Cost Avoidance Lever
B66: No of Visits/Calls/Tasks/Year | C66: 0 | E66: No of Visits/Calls/Tasks/Year | G66: Assuming prospect always submits an application & BO reviews every application. | W66: No of Visits/Calls/Tasks/Year | Y66: Assuming prospect always submits an application & BO reviews every application.
B67: Average Time Spent per Interaction (hour) | C67: 0 | E67: Average Time Spent per Interaction (hour) | F67: =30/60 -> 0.5 | G67: average processing time per application | W67: Average Time Spent per Interaction (hour) | Y67: average processing time per application
B68: Average FTE Costs per Hour (USD) | C68: =F14 -> 8.0103948 | E68: Average FTE Costs per Hour (USD) | F68: =F14 -> 8.0103948 | W68: Average FTE Costs per Hour (USD)
B69: Backbase Impact | C69: 0.2 | E69: Backbase Impact | F69: 0.5 | G69: STP will reduce manual processing effort | W69: Backbase Impact | Y69: STP will reduce manual processing effort
B72: Yearly Accounts Opened | E72: Yearly Loans Acquired | W72: Yearly CC Acquired
B73: No of accounts opened yearly | C73: =(F15*C76)/(1+F76) -> 609377 | D73: From SeABank - Growth in customers from 2023-24 was 20% | E73: No of loans acquired yearly | F73: 59843 | W73: No of CC acquired yearly
B74: Out of which digitally | C74: =C73*C75 -> 499689.14 | E74: Out of which digitally | F74: =5543+2500 -> 8043 | G74: From seabank: 5K overdraft + 2.5K CC | W74: Out of which digitally
B75: Proportion Digital | C75: 0.82 | D75: From SeABank - activation is 18% | E75: Proportion Digital | F75: =F74/F73 -> 0.13440168 | G75: Assumption: proportion of digital inquiries | W75: Proportion Digital
B76: Yearly growth in account opening | C76: 0.2 | D76: Data from seabank | E76: Yearly growth in loan acquisition | F76: 0.2 | G76: Comparable banks in VN is 30% loan growth, Conservative estimate 20% | W76: Yearly growth in CC acquisition | Y76: As per AR 2021, 30% CAGR for CASA & loans growth, for conservative estimates we have considered 17% for CC
B78: Anticipated Growth in Costs
B79: Yearly growth in costs | C79: ='Annual report data'!F23 -> 0.13835274 | D79: Increase in staff costs FY23-24
W82: Baseline Data - Lending products
W83: Website visits Jan-Mar 2023 | Y83: (similarweb)
W84: Annual - Derived | Y84: x4
W85: Intent to purchase lending product | Y85: high-lvl website traffic analysis
W86: Purchased product
W87: Leakage absolute
W88: Top/down funnel leakage (%)

Sheet Customer & Loan Acquisition - A
B2: Backbase VC-Business Case
B3: Customer and Loan Acquisition Analysis
C7: Required info
C8: Calculated Info
C9: Assumptions
B14: Customer Acquisition - Onboarding Value Drivers | C14: Total | D14: Impact | E14: Data Detail | H14: Total | I14: Year 1 | J14: Year 2 | K14: Year 3 | L14: Year 4 | M14: Year 5
B15: Sum of Customer Onboarding Value Drivers | C15: =sum(C16:C44) -> 24634790 | G15: Customer Onboarding (Cost Reduction + Revenue Improvement) | H15: =sUm(I15:M15) -> 1752132.6 | I15: =I19+I23 -> 29475.938 | J15: =J19+J23 -> 161712.99 | K15: =K19+K23 -> 327174.43 | L15: =L19+L23 -> 571638.87 | M15: =M19+M23 -> 662130.38
B16: Total Revenue Generation - Customer Acquisition | C16: =C23+C32 -> 1330563.3 | G16: Increase Revenue | H16: =sum(I16:M16) -> 714068.98 | I16: =I19 -> 14968.837 | J16: =J19 -> 34372.886 | K16: =K19 -> 124075.03 | L16: =L19 -> 249258.86 | M16: =M19 -> 291393.37
B17: Increase Customer Conversion in website | C17: =C23 -> 1186151.4 | D17: Revenue Generation and Cost Reduction | G17: Average Income per New Customer | H17: =AVERAGE(I17:M17) -> 21.9285 | I17: =$C$155/4 -> 9.9675 | J17: =$C$155/3 -> 13.29 | K17: =$C$155/2 -> 19.935 | L17: =$C$155/1.5 -> 26.58 | M17: =$C$155/1 -> 39.87
B18: Website Visits - Intention to Purchase Product | C18: ='Customer Phases - Inputs and As'!C36 -> 514447 | G18: New Customers Acquired | H18: =SUM(I18:M18) -> 26998.388 | I18: =($C$25+$C$34)*'Customer Phases - Inputs and As'!C21*'Customer Phases - Inputs and As'!C22 -> 1501.7645 | J18: =(($C$25+$C$34)/2*'Customer Phases - Inputs and As'!D21*'Customer Phases - Inputs and As'!D22)-I18 -> 2586.3721 | K18: =(($C$25+$C$34)/2*'Customer Phases - Inputs and As'!E21*'Customer Phases - Inputs and As'!E22*1.1)-J18 -> 6223.9794 | L18: =(($C$25+$C$34)/2*'Customer Phases - Inputs and As'!F21*'Customer Phases - Inputs and As'!F22*1.1)-K18 -> 9377.6848 | M18: =(($C$25+$C$34)/2*'Customer Phases - Inputs and As'!G21*'Customer Phases - Inputs and As'!G22)-L18 -> 7308.5871
B19: Current Customer Leakage (%) | C19: ='Customer Phases - Inputs and As'!C37 -> 0.7710668 | E19: Current absolute leakage rate due to non-activation & non-completion of application | G19: Income form New Customers Acquired | H19: =SUM(I19:M19) -> 714068.98 | I19: =I17*I18 -> 14968.837 | J19: =J17*J18 -> 34372.886 | K19: =K17*K18 -> 124075.03 | L19: =L17*L18 -> 249258.86 | M19: =M17*M18 -> 291393.37
B20: Average Income/Customer | C20: ='Customer Phases - Inputs and As'!C38 -> 39.87 | G20: Reduce Costs | H20: =sum(I20:M20) -> 1038063.6 | I20: =I23 -> 14507.1 | J20: =J23 -> 127340.1 | K20: =K23 -> 203099.4 | L20: =L23 -> 322380.01 | M20: =M23 -> 370737.01
B21: Baseline | C21: =C20*C18*C19 -> 15815353 | E21: Customers Leakage Value (visits x leakage x revenue/product) | G21: Number of Physical Interactions and Tasks | H21: =SUM(I21:M21) -> 3256182.5 | I21: =C37+C53+C61+C45 -> 482942.5 | J21: =I21*(1+'Customer Phases - Inputs and As'!D23) -> 555383.88 | K21: =J21*(1+'Customer Phases - Inputs and As'!E23) -> 638691.46 | L21: =K21*(1+'Customer Phases - Inputs and As'!F23) -> 734495.17 | M21: =L21*(1+'Customer Phases - Inputs and As'!G23) -> 844669.45
B22: Backbase Impact | C22: ='Customer Phases - Inputs and As'!C39 -> 0.075 | E22: Post implementation % customers can be converted from leaked out due to digital | G22: Number of Physical Interactions and Tasks Converted to Digital | H22: =SUM(I22:M22) -> 814045.61 | I22: =C43+C59+C67+C51 -> 120735.62 | J22: =I22*(1+'Customer Phases - Inputs and As'!D23) -> 138845.97 | K22: =J22*(1+'Customer Phases - Inputs and As'!E23) -> 159672.86 | L22: =K22*(1+'Customer Phases - Inputs and As'!F23) -> 183623.79 | M22: =L22*(1+'Customer Phases - Inputs and As'!G23) -> 211167.36
B23: Potential Annual benefits | C23: =C21*C22 -> 1186151.4 | E23: Net more income that can be generated due to higher digital conversions | G23: Cost Saved | H23: =SUM(I23:M23) -> 1038063.6 | I23: =C35*'Customer Phases - Inputs and As'!C21*'Customer Phases - Inputs and As'!C22 -> 14507.1 | J23: =C35*'Customer Phases - Inputs and As'!D21*'Customer Phases - Inputs and As'!D22+C35*('Customer Phases - Inputs and As'!D23) -> 127340.1 | K23: =C35*'Customer Phases - Inputs and As'!E21*'Customer Phases - Inputs and As'!E22+C35*'Customer Phases - Inputs and As'!E23 -> 203099.4 | L23: =C35*'Customer Phases - Inputs and As'!F21*'Customer Phases - Inputs and As'!F22+C35*'Customer Phases - Inputs and As'!F23 -> 322380.01 | M23: =L23*'Customer Phases - Inputs and As'!G21*'Customer Phases - Inputs and As'!G22+L23*'Customer Phases - Inputs and As'!G23 -> 370737.01
B24: Current Customer Leakage # | C24: =C18*C19 -> 396673 | E24: Total No of Customer who could have been converted | G24: USL Origination (Cost Reduction + Revenue Improvement) | H24: =sUm(I24:M24) -> 1351893.8 | I24: =I28+I32 -> 12783.367 | J24: =J28+J32 -> 112021.23 | K24: =K28+K32 -> 211735.33 | L24: =L28+L32 -> 392046.65 | M24: =M28+M32 -> 623307.26
B25: Net More Customers Acquired | C25: =C24*C22 -> 29750.475 | E25: No of customer who could be converted after applying Backbase impact | G25: Increase Revenue | H25: =sum(I25:M25) -> 639306.21 | I25: =I28 -> 2824.8443 | J25: =J28 -> 24607.533 | K25: =K28 -> 72316.015 | L25: =L28 -> 170746.15 | M25: =M28 -> 368811.67
B26: Increase Customer Conversion in Branch sales | C26: =C32 -> 144411.88 | D26: Revenue Generation | G26: Average Income per New Customer | H26: =SUM(I26:M26) -> 109.6425 | I26: =$C$74/4 -> 9.9675 | J26: =$C$74/3 -> 13.29 | K26: =$C$74/2 -> 19.935 | L26: =$C$74/1.5 -> 26.58 | M26: =$C$74/1 -> 39.87
B27: No of Visits/Year | C27: ='Customer Phases - Inputs and As'!C42 -> 241471.25 | E27: Customer visiting branch; | G27: New Loans Acquisitions | H27: =SUM(I27:M27) -> 21436.792 | I27: =(($C$79+$C$88)*'Customer Phases - Inputs and As'!C21*'Customer Phases - Inputs and As'!C22) -> 283.4055 | J27: =(($C$79+$C$88)*'Customer Phases - Inputs and As'!D21*'Customer Phases - Inputs and As'!D22)*(1+'Customer Phases - Inputs and As'!F76) -> 1851.5826 | K27: =(($C$79+$C$88)*'Customer Phases - Inputs and As'!E21*'Customer Phases - Inputs and As'!E22)*((1+'Customer Phases - Inputs and As'!F76)) -> 3627.5904 | L27: =(($C$79+$C$88)*'Customer Phases - Inputs and As'!F21*'Customer Phases - Inputs and As'!F22)*((1+'Customer Phases - Inputs and As'!F76)) -> 6423.858 | M27: =((L27*'Customer Phases - Inputs and As'!G21*'Customer Phases - Inputs and As'!G22)*((1+'Customer Phases - Inputs and As'!F76)^2)) -> 9250.3555
B28: Current Customer Leakage (%) | C28: ='Customer Phases - Inputs and As'!C43 -> 0.2 | E28: Current absolute leakage rate including activation leakage | G28: Income form New Loans Acquisitions | H28: =SUM(I28:M28) -> 639306.21 | I28: =I27*I26 -> 2824.8443 | J28: =J27*J26 -> 24607.533 | K28: =K27*K26 -> 72316.015 | L28: =L27*L26 -> 170746.15 | M28: =M27*M26 -> 368811.67
B29: Average Income/Customer | C29: ='Customer Phases - Inputs and As'!C44 -> 39.87 | G29: Reduce Costs | H29: =sum(I29:M29) -> 712587.63 | I29: =I32 -> 9958.5228 | J29: =J32 -> 87413.7 | K29: =K32 -> 139419.32 | L29: =L32 -> 221300.51 | M29: =M32 -> 254495.58
B30: Baseline | C30: =C29*C27*C28 -> 1925491.7 | E30: Customers Leakage Value | G30: Number of Physical Interactions and Tasks | H30: =SUM(I30:M30) -> 1047766 | I30: =C91+C99+C107+C115 -> 155400 | J30: =I30*(1+'Customer Phases - Inputs and As'!D23) -> 178710 | K30: =J30*(1+'Customer Phases - Inputs and As'!E23) -> 205516.5 | L30: =K30*(1+'Customer Phases - Inputs and As'!F23) -> 236343.98 | M30: =L30*(1+'Customer Phases - Inputs and As'!G23) -> 271795.57
B31: Backbase Impact | C31: ='Customer Phases - Inputs and As'!C45 -> 0.075 | E31: Assumption: Integrated digital onboarding solution will remove friction in the onboarding process across branch/digital channels | G31: Number of Physical Interactions and Tasks Converted to Digital | H31: =SUM(I31:M31) -> 279404.28 | I31: =C97+C105+C113+C121 -> 41440 | J31: =I31*(1+'Customer Phases - Inputs and As'!D23) -> 47656 | K31: =J31*(1+'Customer Phases - Inputs and As'!E23) -> 54804.4 | L31: =K31*(1+'Customer Phases - Inputs and As'!F23) -> 63025.06 | M31: =L31*(1+'Customer Phases - Inputs and As'!G23) -> 72478.819
B32: Potential Annual benefits | C32: =C30*C31 -> 144411.88 | E32: Net more income that can be generated due to higher conversions | G32: Cost Saved | H32: =SUM(I32:M32) -> 712587.63 | I32: =C89*'Customer Phases - Inputs and As'!C21*'Customer Phases - Inputs and As'!C22 -> 9958.5228 | J32: =$C$89*'Customer Phases - Inputs and As'!D21*'Customer Phases - Inputs and As'!D22+$C$89*'Customer Phases - Inputs and As'!D23 -> 87413.7 | K32: =C89*'Customer Phases - Inputs and As'!E21*'Customer Phases - Inputs and As'!E22+C89*'Customer Phases - Inputs and As'!E23 -> 139419.32 | L32: =C89*'Customer Phases - Inputs and As'!F21*'Customer Phases - Inputs and As'!F22+C89*'Customer Phases - Inputs and As'!F23 -> 221300.51 | M32: =L32*'Customer Phases - Inputs and As'!G21*'Customer Phases - Inputs and As'!G22+L32*'Customer Phases - Inputs and As'!G23 -> 254495.58
B33: Current Customer Leakage # | C33: =C27*C28 -> 48294.25 | E33: No of Customer who could have been converted | G33: CLO (Cost Reduction + Revenue Improvement) | H33: =sUm(I33:M33) -> 7952116.8 | I33: =(I37+I41)*0 -> 0 | J33: =J37+J41 -> 765378.88 | K33: =K37+K41 -> 1487416.4 | L33: =L37+L41 -> 2619573.4 | M33: =M37+M41 -> 3079748.2
B34: Net More Customers Acquired | C34: =C33*C31 -> 3622.0687 | E34: No of customer who could be converted after applying Backbase impact | G34: Increase Revenue | H34: =sum(I34:M34) -> 7695106.6 | I34: =I37*0 -> 0 | J34: =J37 -> 732155.77 | K34: =K37 -> 1434427.6 | L34: =L37 -> 2540132.3 | M34: =M37 -> 2988390.9
B35: Total Cost Benefit - Customer Acquisition | C35: =C42+C58+C66+C50 -> 322380.01 | G35: Average Income per Customer (Additional) | H35: =SUM(I35:M35) -> 106.32 | I35: =$C$128/4 -> 9.9675 | J35: =$C$128/4 -> 9.9675 | K35: =$C$128/2 -> 19.935 | L35: =$C$128/1.5 -> 26.58 | M35: =$C$128 -> 39.87
B36: Reduce Branch Visits | C36: =C42 -> 193428 | D36: Cost Reduction | G36: Reactivate Dorman Customers | H36: =SUM(I36:M36) -> 7829584.2 | I36: =(($C$131)*'Customer Phases - Inputs and As'!C21*'Customer Phases - Inputs and As'!C22) -> 134477.59 | J36: =(($C$131)*'Customer Phases - Inputs and As'!D21*'Customer Phases - Inputs and As'!D22)*((1+'Customer Phases - Inputs and As'!X76)) -> 732155.77 | K36: =(($C$131)*'Customer Phases - Inputs and As'!E21*'Customer Phases - Inputs and As'!E22)*((1+'Customer Phases - Inputs and As'!X76)^2) -> 1434427.6 | L36: =(($C$131)*'Customer Phases - Inputs and As'!F21*'Customer Phases - Inputs and As'!F22)*((1+'Customer Phases - Inputs and As'!X76)^3) -> 2540132.3 | M36: =(($C$131)*'Customer Phases - Inputs and As'!G21*'Customer Phases - Inputs and As'!G22)*((1+'Customer Phases - Inputs and As'!X76)^3) -> 2988390.9
B37: No of Visits/Calls/Tasks/Year | C37: ='Customer Phases - Inputs and As'!C48 -> 241471.25 | E37: Volume of physical interactions or back office tasks created | G37: Product cross sell and upsell | H37: =SUM(I37:M37) -> 7829584.2 | I37: =(($C$140)*'Customer Phases - Inputs and As'!C21*'Customer Phases - Inputs and As'!C22) -> 134477.59 | J37: =(($C$140)*'Customer Phases - Inputs and As'!D21*'Customer Phases - Inputs and As'!D22)*((1+'Customer Phases - Inputs and As'!X76)) -> 732155.77 | K37: =(($C$140)*'Customer Phases - Inputs and As'!E21*'Customer Phases - Inputs and As'!E22)*((1+'Customer Phases - Inputs and As'!X76)^2) -> 1434427.6 | L37: =(($C$140)*'Customer Phases - Inputs and As'!F21*'Customer Phases - Inputs and As'!F22)*((1+'Customer Phases - Inputs and As'!X76)^3) -> 2540132.3 | M37: =(($C$140)*'Customer Phases - Inputs and As'!G21*'Customer Phases - Inputs and As'!G22)*((1+'Customer Phases - Inputs and As'!X76)^3) -> 2988390.9
B38: Average Time Spent /Interaction (hours) | C38: ='Customer Phases - Inputs and As'!C49 -> 0.33333333 | E38: Time spent on 1 visit, call or task | G38: Reduce Costs | H38: =sum(I38:M38) -> 257010.21 | I38: =I41*0 -> 0 | J38: =J41 -> 33223.112 | K38: =K41 -> 52988.762 | L38: =L41 -> 79441.088 | M38: =M41 -> 91357.251
B39: Average FTE Costs/Hour (USD) | C39: ='Customer Phases - Inputs and As'!C50 -> 8.0103948 | E39: assumed employee cost per hour | G39: Improve marketing team's operational efficiency | H39: =SUM(I39:M39) -> 567095.92 | I39: =C144 -> 84109.145 | J39: =I39*(1+'Customer Phases - Inputs and As'!D23) -> 96725.517 | K39: =J39*(1+'Customer Phases - Inputs and As'!E23) -> 111234.34 | L39: =K39*(1+'Customer Phases - Inputs and As'!F23) -> 127919.5 | M39: =L39*(1+'Customer Phases - Inputs and As'!G23) -> 147107.42
B40: Baseline | C40: =C39*C38*C37 -> 644760.01 | E40: Total monetary value spent on interactions
B41: Backbase Impact | C41: ='Customer Phases - Inputs and As'!C51 -> 0.3 | E41: Post Implementation due to digital adoption traffic will move to digital channels | G41: Cost Saved | H41: =SUM(I41:M41) -> 260795.12 | I41: =C143*'Customer Phases - Inputs and As'!C21*'Customer Phases - Inputs and As'!C22 -> 3784.9115 | J41: =$C$143*'Customer Phases - Inputs and As'!D21*'Customer Phases - Inputs and As'!D22+$C$143*'Customer Phases - Inputs and As'!D23 -> 33223.112 | K41: =C143*'Customer Phases - Inputs and As'!E21*'Customer Phases - Inputs and As'!E22+C143*'Customer Phases - Inputs and As'!E23 -> 52988.762 | L41: =C143*'Customer Phases - Inputs and As'!F21*'Customer Phases - Inputs and As'!F22+K41*'Customer Phases - Inputs and As'!F23 -> 79441.088 | M41: =L41*'Customer Phases - Inputs and As'!G21*'Customer Phases - Inputs and As'!G22+L41*'Customer Phases - Inputs and As'!G23 -> 91357.251
B42: Potential Annual benefits | C42: =C40*C41 -> 193428 | E42: Net costs that can be saved | G42: Customer Loyalty and Retention | H42: =sUm(I42:M42) -> 6375921.5 | I42: =I43+I44 -> 109418.84 | J42: =J43+J44 -> 596367.66 | K42: =K43+K44 -> 1168393.8 | L42: =L43+L44 -> 2069030.7 | M42: =M43+M44 -> 2432710.5
B43: Net Decrease in Traffic/Year | C43: =C41*C37 -> 72441.375 | E43: No of interactions moved to digital | G43: Improve Customer Churn | H43: =SUM(I43:M43) -> 74061.073 | I43: =($C$152)*'Customer Phases - Inputs and As'!C27*'Customer Phases - Inputs and As'!C28 -> 1180.7788 | J43: =($C$152)*'Customer Phases - Inputs and As'!D27*'Customer Phases - Inputs and As'!D28*(1+'Customer Phases - Inputs and As'!C29) -> 7071.5533 | K43: =($C$152)*'Customer Phases - Inputs and As'!E27*'Customer Phases - Inputs and As'!E28*(1+'Customer Phases - Inputs and As'!C29) -> 13854.472 | L43: =($C$152)*'Customer Phases - Inputs and As'!F28*(1+'Customer Phases - Inputs and As'!C29) -> 24533.96 | M43: =($C$152/1)*'Customer Phases - Inputs and As'!E29*(1+'Customer Phases - Inputs and As'!C29)+L43 -> 27420.309
B44: Reduce Back Office Tasks | C44: =C50 -> 0 | D44: Cost Reduction | G44: Increase Product Penetration | H44: =SUM(I44:M44) -> 6301860.4 | I44: =$C$159*'Customer Phases - Inputs and As'!J27*'Customer Phases - Inputs and As'!J28 -> 108238.06 | J44: =$C$159*'Customer Phases - Inputs and As'!K28*'Customer Phases - Inputs and As'!K27 -> 589296.11 | K44: =$C$159*'Customer Phases - Inputs and As'!L28*'Customer Phases - Inputs and As'!L27 -> 1154539.3 | L44: =$C$159*'Customer Phases - Inputs and As'!M28*'Customer Phases - Inputs and As'!M27 -> 2044496.7 | M44: =$C$159*'Customer Phases - Inputs and As'!N28*'Customer Phases - Inputs and As'!N27 -> 2405290.2
B45: No of Visits/Calls/Tasks/Year | C45: ='Customer Phases - Inputs and As'!C66 -> 0 | E45: Volume of physical interactions or back office tasks created | G45: Customer Servicing | H45: =sUm(I45:M45) -> 842505.67 | I45: =I46+I47 -> 12854.408 | J45: =J46+J47 -> 69537.207 | K45: =K46+K47 -> 137113.69 | L45: =L46+L47 -> 242795.54 | M45: =M46+M47 -> 380204.83
B46: Average Time Spent /Interaction (hour) | C46: ='Customer Phases - Inputs and As'!C67 -> 0 | E46: Time spent on 1 visit, call or task | G46: Cost Avoidance | H46: =SUM(I46:M46) -> 842505.67 | I46: ='Servicing - Analysis'!C92 -> 12854.408 | J46: ='Servicing - Analysis'!D92 -> 69537.207 | K46: ='Servicing - Analysis'!F92 -> 137113.69 | L46: ='Servicing - Analysis'!G92 -> 242795.54 | M46: ='Servicing - Analysis'!H92 -> 380204.83
B47: Average FTE Costs/Hour (USD) | C47: ='Customer Phases - Inputs and As'!C68 -> 8.0103948 | E47: Based on average monthly salary
B48: Baseline | C48: =C47*C46*C45 -> 0 | E48: Total monetary value spent on interactions
B49: Backbase Impact | C49: ='Customer Phases - Inputs and As'!C69 -> 0.2 | E49: Post Implementation due to digital adoption traffic will move to digital channels | G49: [Table not relevant for this analysis)
B50: Potential Annual benefits | C50: =C48*C49 -> 0 | E50: Net costs that can be saved | G50: Revenue Benefits With and Without Backbase | H50: Total | I50: Year 1 | J50: Year 2 | K50: Year 3 | L50: Year 4 | M50: Year 5 | N50: With BB
B51: Net Decrease in Traffic/Year | C51: =C49*C45 -> 0 | E51: No of interactions moved to digital | G51: Number of Customers Acquired | N51: =I58 -> 60126.406
B52: Reduce effort @ branch visits | C52: =C58 -> 128952 | D52: Cost Reduction | G52: Without Backbase | H52: =sum(I52:M52) -> 3718486.7 | I52: ='Customer Phases - Inputs and As'!C74 -> 499689.14 | J52: =I52*(1+'Customer Phases - Inputs and As'!$C$76) -> 599626.97 | K52: =J52*(1+'Customer Phases - Inputs and As'!$C$76) -> 719552.36 | L52: =K52*(1+'Customer Phases - Inputs and As'!$C$76) -> 863462.83 | M52: =L52*(1+'Customer Phases - Inputs and As'!$C$76) -> 1036155.4
B53: No of Visits/Calls/Tasks/Year | C53: ='Customer Phases - Inputs and As'!C54 -> 241471.25 | E53: Volume of physical interactions or back office tasks created | G53: With Backbase | H53: =sum(I53:M53) -> 3745485.1 | I53: =I52+I18 -> 501190.9 | J53: =J52+J18 -> 602213.34 | K53: =K52+K18 -> 725776.34 | L53: =L52+L18 -> 872840.52 | M53: =M52+M18 -> 1043464
B54: Average Time Spent /Interaction (hour) | C54: ='Customer Phases - Inputs and As'!C55 -> 0.33333333 | E54: Time spent on 1 visit, call or task | G54: Revenue generated without Backbase | H54: =sum(I54:M54) -> 91556328 | I54: =I52*I17 -> 4980651.5 | J54: =J52*J17 -> 7969042.4 | K54: =K52*K17 -> 14344276 | L54: =L52*L17 -> 22950842 | M54: =M52*M17 -> 41311516
B55: Average FTE Costs/Hour (USD) | C55: ='Customer Phases - Inputs and As'!C56 -> 8.0103948 | E55: Based on average monthly salary | G55: Revenue generated with Backbase | H55: =sum(I55:M55) -> 92270397 | I55: =I53*I17 -> 4995620.3 | J55: =J53*J17 -> 8003415.3 | K55: =K53*K17 -> 14468351 | L55: =L53*L17 -> 23200101 | M55: =M53*M17 -> 41602909
B56: Baseline | C56: =C55*C54*C53 -> 644760.01 | E56: Total amount of value spent on interactions | G56: Loans Acquired
B57: Backbase Impact | C57: ='Customer Phases - Inputs and As'!C57 -> 0.2 | E57: Post Implementation due to digital adoption traffic will move to digital channels | G57: Without Backbase | H57: =sum(I57:M57) -> 445327.67 | I57: ='Customer Phases - Inputs and As'!F73 -> 59843 | J57: =I57*(1+'Customer Phases - Inputs and As'!$C$76) -> 71811.6 | K57: =J57*(1+'Customer Phases - Inputs and As'!$C$76) -> 86173.92 | L57: =K57*(1+'Customer Phases - Inputs and As'!$C$76) -> 103408.7 | M57: =L57*(1+'Customer Phases - Inputs and As'!$C$76) -> 124090.44
B58: Potential Annual benefits | C58: =C56*C57 -> 128952 | E58: Net costs that can be saved | G58: With Backbase | H58: =sum(I58:M58) -> 466764.46 | I58: =I57+I27 -> 60126.406 | J58: =J57+J27 -> 73663.183 | K58: =K57+K27 -> 89801.51 | L58: =L57+L27 -> 109832.56 | M58: =M57+M27 -> 133340.8
B59: Net Decrease in eBranch calls | C59: =C57*C53 -> 48294.25 | E59: No of interactions moved to digital | G59: Revenue generated without Backbase | H59: =sum(I59:M59) -> 10964828 | I59: =I57*I26 -> 596485.1 | J59: =J57*J26 -> 954376.16 | K59: =K57*K26 -> 1717877.1 | L59: =L57*L26 -> 2748603.4 | M59: =M57*M26 -> 4947486
B60: Reduce Call Center Calls | C60: =C66 -> 0 | D60: Cost Reduction | G60: Revenue generated with Backbase | H60: =sum(I60:M60) -> 11604134 | I60: =I58*I26 -> 599309.95 | J60: =J58*J26 -> 978983.7 | K60: =K58*K26 -> 1790193.1 | L60: =L58*L26 -> 2919349.5 | M60: =M58*M26 -> 5316297.7
B61: No of Visits/Calls/Tasks/Year | C61: ='Customer Phases - Inputs and As'!C60 -> 0 | E61: Volume of physical interactions or back office tasks created | G61: CC Acquired
B62: Average Time Spent /Interaction (hour) | C62: ='Customer Phases - Inputs and As'!C61 -> 0 | E62: Time spent on 1 visit, call or task | G62: Without Backbase | H62: =sum(I62:M62) -> 0 | I62: ='Customer Phases - Inputs and As'!X73 | J62: =I62*(1+'Customer Phases - Inputs and As'!$X$76) -> 0 | K62: =J62*(1+'Customer Phases - Inputs and As'!$X$76) -> 0 | L62: =K62*(1+'Customer Phases - Inputs and As'!$X$76) -> 0 | M62: =L62*(1+'Customer Phases - Inputs and As'!$X$76) -> 0
B63: Average FTE Costs/Hour (USD) | C63: ='Customer Phases - Inputs and As'!C62 -> 8.0103948 | E63: Based on data provided average monthly salary | G63: With Backbase | H63: =sum(I63:M63) -> 7829584.2 | I63: =I62+I36 -> 134477.59 | J63: =J62+J36 -> 732155.77 | K63: =K62+K36 -> 1434427.6 | L63: =L62+L36 -> 2540132.3 | M63: =M62+M36 -> 2988390.9
B64: Baseline | C64: =C63*C62*C61 -> 0 | G64: Revenue generated without Backbase | H64: =sum(I64:M64) -> 0 | I64: =I62*I35 -> 0 | J64: =J62*J35 -> 0 | K64: =K62*K35 -> 0 | L64: =L62*L35 -> 0 | M64: =M62*M35 -> 0
B65: Backbase Impact | C65: ='Customer Phases - Inputs and As'!C63 -> 0 | E65: Post Implementation due to digital adoption traffic will move to digital channels | G65: Revenue generated with Backbase | H65: =sum(I65:M65) -> 2.2389734e+08 | I65: =I63*I35 -> 1340405.4 | J65: =J63*J35 -> 7297762.6 | K65: =K63*K35 -> 28595315 | L65: =L63*L35 -> 67516716 | M65: =M63*M35 -> 1.1914715e+08
B66: Potential Annual benefits | C66: =C64*C65 -> 0 | E66: Net costs that can be saved | G66: Cost Reduction Benefits With and Without Backbase
B67: Net Decrease in Call volume/Year | C67: =C65*C61 -> 0 | E67: No of interactions moved to digital | G67: Reduce Costs for Account Opening
B68: Loans Acquisition | C68: Total | D68: Impact | E68: Data Detail | G68: Without Backbase | H68: =sum(I68:M68) -> 8496067.1 | I68: =C48+C64+C56+C40 -> 1289520 | J68: =I68*(1+'Customer Phases - Inputs and As'!$C$79) -> 1467928.7 | K68: =J68*(1+'Customer Phases - Inputs and As'!$C$79) -> 1671020.6 | L68: =K68*(1+'Customer Phases - Inputs and As'!$C$79) -> 1902210.9 | M68: =L68*(1+'Customer Phases - Inputs and As'!$C$79) -> 2165387
B69: Sum of Loan Origination Value Drivers | C69: =+SUM(C71,C80,C90,C98,C106,C114) -> 472397.78 | G69: With Backbase | H69: =sum(I69:M69) -> 6123171 | I69: =I68-I23 -> 1275012.9 | J69: =J68-J23 -> 1340588.6 | K69: =$J$68-K23 -> 1264829.3 | L69: =$J$68-L23 -> 1145548.6 | M69: =$J$68-M23 -> 1097191.6
B70: Total Revenue Generation - Loan Acquisition | C70: =C77+C86 -> 251097.27 | G70: Reduce Costs for Loan Acquisition
B71: Increase Customer Conversion - preapproved | C71: =C77 -> 96202.323 | D71: Revenue Generation | G71: Without Backbase | H71: =sum(I71:M71) -> 5467685.4 | I71: =C94+C102+C110+C118 -> 829876.9 | J71: =I71*(1+'Customer Phases - Inputs and As'!$C$79) -> 944692.64 | K71: =J71*(1+'Customer Phases - Inputs and As'!$C$79) -> 1075393.5 | L71: =K71*(1+'Customer Phases - Inputs and As'!$C$79) -> 1224177.1 | M71: =L71*(1+'Customer Phases - Inputs and As'!$C$79) -> 1393545.3
B72: No of Visits/Year | C72: ='Customer Phases - Inputs and As'!F36 -> 24129 | G72: With Backbase | H72: =sum(I72:M72) -> 3781244.1 | I72: =I71-I32 -> 819918.38 | J72: =$I$71-J32 -> 742463.2 | K72: =$J$71-K32 -> 805273.32 | L72: =$J$71-L32 -> 723392.13 | M72: =$J$71-M32 -> 690197.06
B73: Current Customer Leakage (%) | C73: ='Customer Phases - Inputs and As'!F37 -> 0.66666667 | E73: Customer do not proceed from product page
B74: Average Loan Income/Customer | C74: ='Customer Phases - Inputs and As'!F38 -> 39.87 | E74: Average income from 1 customer
B75: Baseline | C75: =C74*C72*C73 -> 641348.82 | E75: Total Customer Leakage Value
B76: Backbase Impact | C76: ='Customer Phases - Inputs and As'!F39 -> 0.15 | E76: Interested customer/prospects would proceed with online loan origination if given possibility to | G76: Reduce Costs to Serve for banking operations
B77: Potential Annual benefits - Backbase | C77: =C75*C76 -> 96202.323 | E77: Net more income that can be generated due to higher digital conversions | G77: Without Backbase | H77: =sum(I77:M77) -> 6267173.5 | I77: ='Servicing - Analysis'!$I$88 -> 1068280.2 | J77: =I77*(1+'Customer Phases - Inputs and As'!K$23) -> 1153742.6 | K77: =J77*(1+'Customer Phases - Inputs and As'!L$23) -> 1246042 | L77: =K77*(1+'Customer Phases - Inputs and As'!M$23) -> 1345725.4 | M77: =L77*(1+'Customer Phases - Inputs and As'!N$23) -> 1453383.4
B78: Current Customer Leakage # | C78: =C72*C73 -> 16086 | E78: No of Customer who could have been converted | G78: With Backbase | H78: =sum(I78:M78) -> 5424667.9 | I78: =I$77-'Servicing - Analysis'!C$92 -> 1055425.8 | J78: =J$77-'Servicing - Analysis'!D$92 -> 1084205.4 | K78: =K$77-'Servicing - Analysis'!F$92 -> 1108928.3 | L78: =L$77-'Servicing - Analysis'!G$92 -> 1102929.8 | M78: =M$77-'Servicing - Analysis'!H$92 -> 1073178.6
B79: Net More Loans Sold | C79: =C78*C76 -> 2412.9 | E79: No of customer who could be converted after applying Backbase impact | G79: Cost Avoidance - Totals, for Deck
B80: Increase Customer Conversion in branch sales | C80: =C86 -> 154894.95 | D80: Revenue Generation | G80: Without Backbase | H80: =sum(I80:M80) -> 20230926 | I80: =I$68+I$71+I$77 -> 3187677.1 | J80: =J$68+J$71+J$77 -> 3566363.9 | K80: =K$68+K$71+K$77 -> 3992456.1 | L80: =L$68+L$71+L$77 -> 4472113.3 | M80: =M$68+M$71+M$77 -> 5012315.7
B81: No of Visits/Year | C81: ='Customer Phases - Inputs and As'!F42 -> 103600 | E81: Intending to open a loan | G81: With Backbase | H81: =sum(I81:M81) -> 15329083 | I81: =I$69+I$72+I$78 -> 3150357.1 | J81: =J$69+J$72+J$78 -> 3167257.1 | K81: =K$69+K$72+K$78 -> 3179030.9 | L81: =L$69+L$72+L$78 -> 2971870.6 | M81: =M$69+M$72+M$78 -> 2860567.3
B82: Current Customer Leakage (%) | C82: ='Customer Phases - Inputs and As'!F43 -> 0.5 | G82: check | H82: =H77-H78 -> 842505.67 | N82: =I60 -> 599309.95
B83: Average Income/Customer | C83: ='Customer Phases - Inputs and As'!F44 -> 39.87 | E83: Average income from 1 customer | H83: ='Servicing - Analysis'!I92 -> 842505.67 | N83: =J60 -> 978983.7
B84: Baseline | C84: =C83*C81*C82 -> 2065266 | E84: Customers Leakage Value | G84: Revenue Generation - Fee Income - Uplift Transactions on Digital | H84: Total | I84: Year 1 | J84: Year 2 | K84: Year 3 | L84: Year 4 | M84: Year 5 | N84: =K60 -> 1790193.1
B85: Backbase Impact | C85: ='Customer Phases - Inputs and As'!F45 -> 0.075 | E85: Assumption: integrated digital loan origination solution will help employee to service prospects more efficiently, and increase conversion. | G85: Additional Transactions with Backbase - New Customers | H85: =sum(I85:M85) -> 0 | I85: ='Customer Phases - Inputs and As'!$F$105*I$18*'Customer Phases - Inputs and As'!J$21*'Customer Phases - Inputs and As'!J$22 -> 0 | J85: ='Customer Phases - Inputs and As'!$F$105*J$18*'Customer Phases - Inputs and As'!K$21*'Customer Phases - Inputs and As'!K$22 -> 0 | K85: ='Customer Phases - Inputs and As'!$F$105*K$18*'Customer Phases - Inputs and As'!L$21*'Customer Phases - Inputs and As'!L$22 -> 0 | L85: ='Customer Phases - Inputs and As'!$F$105*L$18*'Customer Phases - Inputs and As'!M$21*'Customer Phases - Inputs and As'!M$22 -> 0 | M85: ='Customer Phases - Inputs and As'!$F$105*M$18*'Customer Phases - Inputs and As'!N$21*'Customer Phases - Inputs and As'!N$22 -> 0 | N85: =L60 -> 2919349.5
B86: Potential Annual benefits | C86: =C84*C85 -> 154894.95 | E86: Net more income that can be generated due to higher digital conversions | G86: Additional Transactions with Backbase - Existing Customers | H86: =sum(I86:M86) -> 0 | I86: ='Customer Phases - Inputs and As'!$F$104*'Customer Phases - Inputs and As'!J$21*'Customer Phases - Inputs and As'!J$22*'Customer Phases - Inputs and As'!$J$23 -> 0 | J86: ='Customer Phases - Inputs and As'!$F$104*'Customer Phases - Inputs and As'!K$21*'Customer Phases - Inputs and As'!K$22*'Customer Phases - Inputs and As'!$J$23 -> 0 | K86: ='Customer Phases - Inputs and As'!$F$104*'Customer Phases - Inputs and As'!L$21*'Customer Phases - Inputs and As'!L$22*'Customer Phases - Inputs and As'!$J$23 -> 0 | L86: ='Customer Phases - Inputs and As'!$F$104*'Customer Phases - Inputs and As'!M$21*'Customer Phases - Inputs and As'!M$22*'Customer Phases - Inputs and As'!$J$23 -> 0 | M86: ='Customer Phases - Inputs and As'!$F$104*'Customer Phases - Inputs and As'!N$21*'Customer Phases - Inputs and As'!N$22*'Customer Phases - Inputs and As'!$J$23*1.1 -> 0 | N86: =M60 -> 5316297.7
B87: Current Customer Leakage # | C87: =C81*C82 -> 51800 | E87: No of Customer who could have been converted | G87: Additional Transactions with Backbase - TOTAL | H87: =sum(I87:M87) -> 0 | I87: =I85+I86 -> 0 | J87: =J85+J86 -> 0 | K87: =K85+K86 -> 0 | L87: =L85+L86 -> 0 | M87: =M85+M86 -> 0 | N87: With BB
B88: Net More Loans Sold | C88: =C87*C85 -> 3885 | E88: No of customer who could be converted after applying Backbase impact | G88: Value in USD | H88: =sum(I88:M88) -> 0 | I88: =I87*'Customer Phases - Inputs and As'!$E$102 -> 0 | J88: =J87*'Customer Phases - Inputs and As'!$E$102 -> 0 | K88: =K87*'Customer Phases - Inputs and As'!$E$102 -> 0 | L88: =L87*'Customer Phases - Inputs and As'!$E$102 -> 0 | M88: =M87*'Customer Phases - Inputs and As'!$E$102 -> 0 | N88: =I72 -> 819918.38
B89: Total Cost Benefit - Loan Acquisition | C89: =C96+C104+C112+C120 -> 221300.51 | N89: =J72 -> 742463.2
B90: Reduce Branch Visits | C90: =C96 -> 165975.38 | D90: Cost Reduction | N90: =K72 -> 805273.32
B91: No of Visits/Calls/Tasks/Year | C91: ='Customer Phases - Inputs and As'!F48 -> 103600 | E91: Volume of physical interactions or back office tasks created | N91: =L72 -> 723392.13
B92: Average Time Spent /Interaction (hours) | C92: ='Customer Phases - Inputs and As'!F49 -> 0.66666667 | E92: Time spent on1 visit, call or task | N92: =M72 -> 690197.06
B93: Average FTE Costs/Hour (USD) | C93: ='Customer Phases - Inputs and As'!F50 -> 8.0103948 | E93: Based on average monthly salary
B94: Baseline | C94: =C93*C92*C91 -> 553251.27 | E94: Total monetary value spent on interactions | I94: Year 4 | J94: =L54 -> 22950842 | K94: =L55 -> 23200101 | L94: Year 4 | M94: =L59 -> 2748603.4
B95: Backbase Impact | C95: ='Customer Phases - Inputs and As'!F51 -> 0.3 | E95: Post Implementation due to digital adoption traffic will move to digital channels | I95: Year 5 | J95: =M54 -> 41311516 | K95: =M55 -> 41602909 | L95: Year 5 | M95: =M59 -> 4947486
B96: Potential Annual benefits | C96: =C94*C95 -> 165975.38 | E96: Net costs that can be saved | J96: Without BB | K96: With BB | M96: Without BB
B97: Net Decrease in Traffic/Year | C97: =C95*C91 -> 31080 | E97: No of interactions moved to digital | I97: Year 1 | J97: =I68 -> 1289520 | K97: =I69 -> 1275012.9 | L97: Year 1 | M97: =I71 -> 829876.9
B98: Reduce effort @ branch visits | C98: =C104 -> 55325.127 | D98: Cost Reduction | I98: Year 2 | J98: =J68 -> 1467928.7 | K98: =J69 -> 1340588.6 | L98: Year 2 | M98: =J71 -> 944692.64
B99: No of Visits/Calls/Tasks/Year | C99: ='Customer Phases - Inputs and As'!F54 -> 51800 | E99: total disbursed loans via Branch. | I99: Year 3 | J99: =K68 -> 1671020.6 | K99: =K69 -> 1264829.3 | L99: Year 3 | M99: =K71 -> 1075393.5
B100: Average Time Spent /Interaction (hour) | C100: ='Customer Phases - Inputs and As'!F55 -> 0.66666667 | E100: Time spent on1 visit, call or task | I100: Year 4 | J100: =L68 -> 1902210.9 | K100: =L69 -> 1145548.6 | L100: Year 4 | M100: =L71 -> 1224177.1
B101: Average FTE Costs/Hour (USD) | C101: ='Customer Phases - Inputs and As'!F56 -> 8.0103948 | E101: Based on average monthly salary | I101: Year 5 | J101: =M68 -> 2165387 | K101: =M69 -> 1097191.6 | L101: Year 5 | M101: =M71 -> 1393545.3
B102: Baseline | C102: =C101*C100*C99 -> 276625.63 | E102: Total amount of value spent on interactions
B103: Backbase Impact | C103: ='Customer Phases - Inputs and As'!F57 -> 0.2 | E103: traffic will move to integrated digital channels after implementation
B104: Potential Annual benefits | C104: =C102*C103 -> 55325.127 | E104: Net costs that can be saved
B105: Net Decrease in Traffic/Year | C105: =C103*C99 -> 10360 | E105: No of interactions moved to digital
B106: Reduce Call Center Calls | C106: =C112 -> 0 | D106: Cost Reduction
B107: No of Visits/Calls/Tasks/Year | C107: ='Customer Phases - Inputs and As'!F60 | E107: Volume of physical interactions or back office tasks created
B108: Average Time Spent /Interaction (hour) | C108: ='Customer Phases - Inputs and As'!F61 | E108: Time spent on1 visit, call or task
...

Sheet Servicing - Analysis
B2: Backbase VC-Business Case
B3: Servicing Analysis
C7: Required info
C8: Calculated Info
C9: Assumptions
B14: Servicing Journey Names | C14: Yearly Volume | D14: Time Spent/Visit (HR) | F14: Baseline (Annual Cost) | G14: Backbase Impact | H14: After Impact
B15: Total | C15: =sum(C17:C33,C35:C51,C53:C69) -> 877075 | F15: =F16+F34+F52 -> 1259014.1 | H15: =H16+H34+H52 -> 331529.51
B16: Branch | C16: =sum(C17:C33) -> 805155 | F16: =sum(F17:F33) -> 1173463 | H16: =sum(H17:H33) -> 301802.93
B17: Accounts & Balance | C17: ='Customer Phases - Inputs and As'!O37 -> 105168.7 | D17: ='Customer Phases - Inputs and As'!P37 -> 0.08 | F17: =C17*D17*'Customer Phases - Inputs and As'!$H$49 -> 67395.425 | G17: ='Customer Phases - Inputs and As'!U37 -> 0.35 | H17: =F17*G17 -> 23588.399
B18: Account Statement | C18: ='Customer Phases - Inputs and As'!O38 -> 75120.5 | D18: ='Customer Phases - Inputs and As'!P38 -> 0.17 | F18: =C18*D18*'Customer Phases - Inputs and As'!$H$49 -> 102296.63 | G18: ='Customer Phases - Inputs and As'!U38 -> 0.4 | H18: =F18*G18 -> 40918.651
B19: Transaction Dispute | C19: ='Customer Phases - Inputs and As'!O39 -> 53787.3 | D19: ='Customer Phases - Inputs and As'!P39 -> 0.33 | F19: =C19*D19*'Customer Phases - Inputs and As'!$H$49 -> 142182.98 | G19: ='Customer Phases - Inputs and As'!U39 -> 0.4 | H19: =F19*G19 -> 56873.191
B20: Internal Transfers | C20: ='Customer Phases - Inputs and As'!O40 -> 356767.2 | D20: ='Customer Phases - Inputs and As'!P40 -> 0.16666667 | F20: =C20*D20*'Customer Phases - Inputs and As'!$H$49 -> 476307.69 | G20: ='Customer Phases - Inputs and As'!U40 -> 0.1 | H20: =F20*G20 -> 47630.769
B21: Inter Bank Transfers | C21: ='Customer Phases - Inputs and As'!O41 | D21: ='Customer Phases - Inputs and As'!P41 | F21: =C21*D21*'Customer Phases - Inputs and As'!$H$49 -> 0 | G21: ='Customer Phases - Inputs and As'!U41 -> 0.1 | H21: =F21*G21 -> 0
B22: Debit Card Ordering | C22: ='Customer Phases - Inputs and As'!O42 -> 7588.8 | D22: ='Customer Phases - Inputs and As'!P42 -> 0.25 | F22: =C22*D22*'Customer Phases - Inputs and As'!$H$49 -> 15197.321 | G22: ='Customer Phases - Inputs and As'!U42 -> 0.35 | H22: =F22*G22 -> 5319.0624
B23: Card block | C23: ='Customer Phases - Inputs and As'!O43 -> 1146.6 | D23: ='Customer Phases - Inputs and As'!P43 -> 0.17 | F23: =C23*D23*'Customer Phases - Inputs and As'!$H$49 -> 1561.4022 | G23: ='Customer Phases - Inputs and As'!U43 -> 0.2 | H23: =F23*G23 -> 312.28043
B24: Cards PIN reset | C24: ='Customer Phases - Inputs and As'!O44 -> 764.4 | D24: ='Customer Phases - Inputs and As'!P44 -> 0.17 | F24: =C24*D24*'Customer Phases - Inputs and As'!$H$49 -> 1040.9348 | G24: ='Customer Phases - Inputs and As'!U44 -> 0.2 | H24: =F24*G24 -> 208.18696
B25: Card limit change | C25: ='Customer Phases - Inputs and As'!O45 -> 6115.2 | D25: ='Customer Phases - Inputs and As'!P45 -> 0.17 | F25: =C25*D25*'Customer Phases - Inputs and As'!$H$49 -> 8327.4783 | G25: ='Customer Phases - Inputs and As'!U45 -> 0.35 | H25: =F25*G25 -> 2914.6174
B26: Credit card order request | C26: ='Customer Phases - Inputs and As'!O46 | D26: ='Customer Phases - Inputs and As'!P46 | F26: =C26*D26*'Customer Phases - Inputs and As'!$H$49 -> 0 | G26: ='Customer Phases - Inputs and As'!U46 -> 0.35 | H26: =F26*G26 -> 0
B27: Deposit products enquiry | C27: ='Customer Phases - Inputs and As'!O47 | D27: ='Customer Phases - Inputs and As'!P47 | F27: =C27*D27*'Customer Phases - Inputs and As'!$H$49 -> 0 | G27: ='Customer Phases - Inputs and As'!U47 -> 0.35 | H27: =F27*G27 -> 0
B28: Bill payments | C28: ='Customer Phases - Inputs and As'!O48 -> 2995.2 | D28: ='Customer Phases - Inputs and As'!P48 -> 0.16666667 | F28: =C28*D28*'Customer Phases - Inputs and As'!$H$49 -> 3998.7891 | G28: ='Customer Phases - Inputs and As'!U48 -> 0.1 | H28: =F28*G28 -> 399.87891
... B32: Loan Servicing | C32: ='Customer Phases - Inputs and As'!O52 -> 133770 | D32: ='Customer Phases - Inputs and As'!P52 -> 0.25 | F32: =C32*D32*'Customer Phases - Inputs and As'!$H$49 -> 267887.63 | G32: ='Customer Phases - Inputs and As'!U52 -> 0.35 | H32: =F32*G32 -> 93760.67
C33: ='Customer Phases - Inputs and As'!O53 | D33: ='Customer Phases - Inputs and As'!P53 | F33: =C33*D33*'Customer Phases - Inputs and As'!$H$49 -> 0 | G33: ='Customer Phases - Inputs and As'!U53 | H33: =F33*G33 -> 0
B34: Call Center | C34: =sum(C35:C51) -> 71920 | F34: =sum(F35:F51) -> 85551.016 | H34: =sum(H35:H51) -> 29726.575
B35: Accounts & Balance | C35: ='Customer Phases - Inputs and As'!Q37 -> 18720 | D35: ='Customer Phases - Inputs and As'!R37 -> 0.083333333 | F35: =C35*D35*'Customer Phases - Inputs and As'!$H$49 -> 12496.216 | G35: ='Customer Phases - Inputs and As'!U37 -> 0.35 | H35: =F35*G35 -> 4373.6756
B36: Account Statement | C36: ='Customer Phases - Inputs and As'!Q38 | D36: ='Customer Phases - Inputs and As'!R38 -> 0.16666667 | F36: =C36*D36*'Customer Phases - Inputs and As'!$H$49 -> 0 | G36: ='Customer Phases - Inputs and As'!U38 -> 0.4 | H36: =F36*G36 -> 0
B37: Transaction Dispute | C37: ='Customer Phases - Inputs and As'!Q39 -> 4800 | D37: ='Customer Phases - Inputs and As'!R39 -> 0.25 | F37: =C37*D37*'Customer Phases - Inputs and As'!$H$49 -> 9612.4738 | G37: ='Customer Phases - Inputs and As'!U39 -> 0.4 | H37: =F37*G37 -> 3844.9895
B38: Internal Transfers | C38: 0 | D38: ='Customer Phases - Inputs and As'!R40 -> 0.083333333 | F38: =C38*D38*'Customer Phases - Inputs and As'!$H$49 -> 0 | G38: ='Customer Phases - Inputs and As'!U40 -> 0.1 | H38: =F38*G38 -> 0
B39: Inter Bank Transfers | C39: ='Customer Phases - Inputs and As'!Q41 -> 0 | D39: ='Customer Phases - Inputs and As'!R41 -> 0.16666667 | F39: =C39*D39*'Customer Phases - Inputs and As'!$H$49 -> 0 | G39: ='Customer Phases - Inputs and As'!U41 -> 0.1 | H39: =F39*G39 -> 0
B40: Debit Card Ordering | C40: ='Customer Phases - Inputs and As'!Q42 -> 1080 | D40: ='Customer Phases - Inputs and As'!R42 -> 0.16666667 | F40: =C40*D40*'Customer Phases - Inputs and As'!$H$49 -> 1441.8711 | G40: ='Customer Phases - Inputs and As'!U42 -> 0.35 | H40: =F40*G40 -> 504.65487
B41: Card block | C41: ='Customer Phases - Inputs and As'!Q43 -> 5280 | D41: ='Customer Phases - Inputs and As'!R43 -> 0.083333333 | F41: =C41*D41*'Customer Phases - Inputs and As'!$H$49 -> 3524.5737 | G41: ='Customer Phases - Inputs and As'!U43 -> 0.2 | H41: =F41*G41 -> 704.91474
B42: Cards PIN reset | C42: ='Customer Phases - Inputs and As'!Q44 -> 1440 | D42: ='Customer Phases - Inputs and As'!R44 -> 0.083333333 | F42: =C42*D42*'Customer Phases - Inputs and As'!$H$49 -> 961.24738 | G42: ='Customer Phases - Inputs and As'!U44 -> 0.2 | H42: =F42*G42 -> 192.24948
B43: Card limit change | C43: ='Customer Phases - Inputs and As'!Q45 -> 1440 | D43: ='Customer Phases - Inputs and As'!R45 -> 0.16666667 | F43: =C43*D43*'Customer Phases - Inputs and As'!$H$49 -> 1922.4948 | G43: ='Customer Phases - Inputs and As'!U45 -> 0.35 | H43: =F43*G43 -> 672.87316
B44: Credit card order request | C44: ='Customer Phases - Inputs and As'!Q46 -> 7000 | D44: ='Customer Phases - Inputs and As'!R46 -> 0.25 | F44: =C44*D44*'Customer Phases - Inputs and As'!$H$49 -> 14018.191 | G44: ='Customer Phases - Inputs and As'!U46 -> 0.35 | H44: =F44*G44 -> 4906.3668
B45: Deposit products enquiry | C45: ='Customer Phases - Inputs and As'!Q47 -> 1800 | D45: ='Customer Phases - Inputs and As'!R47 -> 0.083333333 | F45: =C45*D45*'Customer Phases - Inputs and As'!$H$49 -> 1201.5592 | G45: ='Customer Phases - Inputs and As'!U47 -> 0.35 | H45: =F45*G45 -> 420.54573
B46: Bill payments | C46: 0 | D46: ='Customer Phases - Inputs and As'!R48 -> 0.16666667 | F46: =C46*D46*'Customer Phases - Inputs and As'!$H$49 -> 0 | G46: ='Customer Phases - Inputs and As'!U48 -> 0.1 | H46: =F46*G46 -> 0
B47: International Transfers | C47: ='Customer Phases - Inputs and As'!Q49 -> 240 | D47: ='Customer Phases - Inputs and As'!R49 -> 0.083333333 | F47: =C47*D47*'Customer Phases - Inputs and As'!$H$49 -> 160.2079 | G47: ='Customer Phases - Inputs and As'!U49 -> 0.2 | H47: =F47*G47 -> 32.041579
B48: Customer Details Update / KYC details | C48: ='Customer Phases - Inputs and As'!Q50 -> 1680 | D48: ='Customer Phases - Inputs and As'!R50 -> 0.16666667 | F48: =C48*D48*'Customer Phases - Inputs and As'!$H$49 -> 2242.9105 | G48: ='Customer Phases - Inputs and As'!U50 -> 0.35 | H48: =F48*G48 -> 785.01869
B49: Credit card info inquiry (& other CC servicing) | C49: ='Customer Phases - Inputs and As'!Q51 -> 14400 | D49: ='Customer Phases - Inputs and As'!R51 -> 0.16666667 | F49: =C49*D49*'Customer Phases - Inputs and As'!$H$49 -> 19224.948 | G49: ='Customer Phases - Inputs and As'!U51 -> 0.35 | H49: =F49*G49 -> 6728.7316
B50: Loan Servicing | C50: ='Customer Phases - Inputs and As'!Q52 -> 14040 | D50: ='Customer Phases - Inputs and As'!R52 -> 0.16666667 | F50: =C50*D50*'Customer Phases - Inputs and As'!$H$49 -> 18744.324 | G50: ='Customer Phases - Inputs and As'!U52 -> 0.35 | H50: =F50*G50 -> 6560.5133
C51: ='Customer Phases - Inputs and As'!Q53 | D51: ='Customer Phases - Inputs and As'!R53 | F51: =C51*D51*'Customer Phases - Inputs and As'!$H$49 -> 0 | G51: ='Customer Phases - Inputs and As'!U53 | H51: =F51*G51 -> 0
B52: Back-Office | C52: =sum(C53:C69) -> 0 | F52: =sum(F53:F69) -> 0 | H52: =sum(H53:H69) -> 0
B53: Accounts & Balance | C53: ='Customer Phases - Inputs and As'!S37 -> 0 | D53: ='Customer Phases - Inputs and As'!T37 -> 0 | F53: =C53*D53*'Customer Phases - Inputs and As'!$H$49 -> 0 | G53: ='Customer Phases - Inputs and As'!U37 -> 0.35 | H53: =F53*G53 -> 0
B54: Account Statement | C54: 0 | D54: ='Customer Phases - Inputs and As'!T38 | F54: =C54*D54*'Customer Phases - Inputs and As'!$H$49 -> 0 | G54: ='Customer Phases - Inputs and As'!U38 -> 0.4 | H54: =F54*G54 -> 0
B55: Transaction Dispute | C55: ='Customer Phases - Inputs and As'!S39 | D55: ='Customer Phases - Inputs and As'!T39 -> 0.75 | F55: =C55*D55*'Customer Phases - Inputs and As'!$H$49 -> 0 | G55: ='Customer Phases - Inputs and As'!U39 -> 0.4 | H55: =F55*G55 -> 0
B56: Internal Transfers | C56: ='Customer Phases - Inputs and As'!S40 -> 0 | D56: ='Customer Phases - Inputs and As'!T40 -> 0 | F56: =C56*D56*'Customer Phases - Inputs and As'!$H$49 -> 0 | G56: ='Customer Phases - Inputs and As'!U40 -> 0.1 | H56: =F56*G56 -> 0
B57: Inter Bank Transfers | C57: ='Customer Phases - Inputs and As'!S41 -> 0 | D57: ='Customer Phases - Inputs and As'!T41 -> 0.083333333 | F57: =C57*D57*'Customer Phases - Inputs and As'!$H$49 -> 0 | G57: ='Customer Phases - Inputs and As'!U41 -> 0.1 | H57: =F57*G57 -> 0
B58: Debit Card Ordering | C58: ='Customer Phases - Inputs and As'!S42 | D58: ='Customer Phases - Inputs and As'!T42 -> 0.5 | F58: =C58*D58*'Customer Phases - Inputs and As'!$H$49 -> 0 | G58: ='Customer Phases - Inputs and As'!U42 -> 0.35 | H58: =F58*G58 -> 0
B59: Card block | C59: ='Customer Phases - Inputs and As'!S43 -> 0 | D59: ='Customer Phases - Inputs and As'!T43 -> 0 | F59: =C59*D59*'Customer Phases - Inputs and As'!$H$49 -> 0 | G59: ='Customer Phases - Inputs and As'!U43 -> 0.2 | H59: =F59*G59 -> 0
B60: Cards PIN reset | C60: ='Customer Phases - Inputs and As'!S44 -> 0 | D60: ='Customer Phases - Inputs and As'!T44 -> 0 | F60: =C60*D60*'Customer Phases - Inputs and As'!$H$49 -> 0 | G60: ='Customer Phases - Inputs and As'!U44 -> 0.2 | H60: =F60*G60 -> 0
B61: Card limit change | C61: ='Customer Phases - Inputs and As'!S45 | D61: ='Customer Phases - Inputs and As'!T45 -> 0.5 | F61: =C61*D61*'Customer Phases - Inputs and As'!$H$49 -> 0 | G61: ='Customer Phases - Inputs and As'!U45 -> 0.35 | H61: =F61*G61 -> 0
B62: Credit card order request | C62: ='Customer Phases - Inputs and As'!S46 | D62: ='Customer Phases - Inputs and As'!T46 -> 0.5 | F62: =C62*D62*'Customer Phases - Inputs and As'!$H$49 -> 0 | G62: ='Customer Phases - Inputs and As'!U46 -> 0.35 | H62: =F62*G62 -> 0
B63: Deposit products enquiry | C63: ='Customer Phases - Inputs and As'!S47 -> 0 | D63: ='Customer Phases - Inputs and As'!T47 -> 0 | F63: =C63*D63*'Customer Phases - Inputs and As'!$H$49 -> 0 | G63: ='Customer Phases - Inputs and As'!U47 -> 0.35 | H63: =F63*G63 -> 0
B64: Bill payments | C64: ='Customer Phases - Inputs and As'!S48 -> 0 | D64: ='Customer Phases - Inputs and As'!T48 -> 0 | F64: =C64*D64*'Customer Phases - Inputs and As'!$H$49 -> 0 | G64: ='Customer Phases - Inputs and As'!U48 -> 0.1 | H64: =F64*G64 -> 0
B65: International Transfers | C65: ='Customer Phases - Inputs and As'!S49 | D65: ='Customer Phases - Inputs and As'!T49 -> 0.25 | F65: =C65*D65*'Customer Phases - Inputs and As'!$H$49 -> 0 | G65: ='Customer Phases - Inputs and As'!U49 -> 0.2 | H65: =F65*G65 -> 0
B66: Customer Details Update / KYC details | C66: ='Customer Phases - Inputs and As'!S50 -> 0 | D66: ='Customer Phases - Inputs and As'!T50 -> 0 | F66: =C66*D66*'Customer Phases - Inputs and As'!$H$49 -> 0 | G66: ='Customer Phases - Inputs and As'!U50 -> 0.35 | H66: =F66*G66 -> 0
... B68: Loan Servicing | C68: ='Customer Phases - Inputs and As'!S52 | D68: ='Customer Phases - Inputs and As'!T52 -> 0.25 | F68: =C68*D68*'Customer Phases - Inputs and As'!$H$49 -> 0 | G68: ='Customer Phases - Inputs and As'!U52 -> 0.35 | H68: =F68*G68 -> 0
C69: ='Customer Phases - Inputs and As'!S53 | D69: ='Customer Phases - Inputs and As'!T53 | F69: =C69*D69*'Customer Phases - Inputs and As'!$H$49 -> 0 | G69: ='Customer Phases - Inputs and As'!U53 | H69: =F69*G69 -> 0
B71: Type of Service | C71: Total Yearly Volume | D71: Time Spent (Hrs) | E71: Backbase Impact | F71: Total Reduction in Interactions | G71: FTE Blended Rate | H71: Cost Avoidance (USD) | I71: Full Cost
B72: Accounts & Balance | C72: =C17+C35+C53 -> 123888.7 | D72: =(D17+D35+D53)/2 -> 0.081666667 | E72: =AVERAGE(G17,G35,G53) -> 0.35 | F72: =C72*G17 -> 43361.045 | G72: ='Customer Phases - Inputs and As'!$H$49 -> 8.0103948 | H72: =D72*F72*G72 -> 28366.026 | I72: =C72*D72*G72 -> 81045.788
B73: Account Statement | C73: =C18+C36+C54 -> 75120.5 | D73: =(D18+D36+D54)/3 -> 0.11222222 | E73: =AVERAGE(G18,G36,G54) -> 0.4 | F73: =C73*G18 -> 30048.2 | G73: ='Customer Phases - Inputs and As'!$H$49 -> 8.0103948 | H73: =D73*F73*G73 -> 27011.658 | I73: =C73*D73*G73 -> 67529.146
B74: Transaction Dispute | C74: 0 | D74: =(D19+D37+D55)/3 -> 0.44333333 | E74: =AVERAGE(G19,G37,G55) -> 0.4 | F74: =C74*G19 -> 0 | G74: ='Customer Phases - Inputs and As'!$H$49 -> 8.0103948 | H74: =D74*F74*G74 -> 0 | I74: =C74*D74*G74 -> 0
B75: Internal Transfers | C75: =C20+C38+C56 -> 356767.2 | D75: =(D20+D38+D56)/2 -> 0.125 | E75: =AVERAGE(G20,G38,G56) -> 0.1 | F75: =C75*G20 -> 35676.72 | G75: ='Customer Phases - Inputs and As'!$H$49 -> 8.0103948 | H75: =D75*F75*G75 -> 35723.077 | I75: =C75*D75*G75 -> 357230.77
B76: Inter Bank Transfers | C76: =C21+C39+C57 -> 0 | D76: =(D21+D39+D57)/3 -> 0.083333333 | E76: =AVERAGE(G21,G39,G57) -> 0.1 | F76: =C76*G21 -> 0 | G76: ='Customer Phases - Inputs and As'!$H$49 -> 8.0103948 | H76: =D76*F76*G76 -> 0 | I76: =C76*D76*G76 -> 0
B77: Debit Card Ordering | C77: =C22+C40+C58 -> 8668.8 | D77: =(D22+D40+D58)/3 -> 0.30555556 | E77: =AVERAGE(G22,G40,G58) -> 0.35 | F77: =C77*G22 -> 3034.08 | G77: ='Customer Phases - Inputs and As'!$H$49 -> 8.0103948 | H77: =D77*F77*G77 -> 7426.2768 | I77: =C77*D77*G77 -> 21217.934 | P77: =1079/5 -> 215.8
B78: Card block | C78: =C23+C41+C59 -> 6426.6 | D78: =(D23+D41+D59)/2 -> 0.12666667 | E78: =AVERAGE(G23,G41,G59) -> 0.2 | F78: =C78*G23 -> 1285.32 | G78: ='Customer Phases - Inputs and As'!$H$49 -> 8.0103948 | H78: =D78*F78*G78 -> 1304.1499 | I78: =C78*D78*G78 -> 6520.7497
B79: Cards PIN reset | C79: =C24+C42+C60 -> 2204.4 | D79: =(D24+D42+D60)/2 -> 0.12666667 | E79: =AVERAGE(G24,G42,G60) -> 0.2 | F79: =C79*G24 -> 440.88 | G79: ='Customer Phases - Inputs and As'!$H$49 -> 8.0103948 | H79: =D79*F79*G79 -> 447.3389 | I79: =C79*D79*G79 -> 2236.6945 | P79: =H86+Sum(H77:H81) -> 26309.655 | Q79: =P79/5 -> 5261.9309
B80: Card limit change | C80: =C25+C43+C61 -> 7555.2 | D80: =(D25+D43+D61)/2 -> 0.41833333 | E80: =AVERAGE(G25,G43,G61) -> 0.35 | F80: =C80*G25 -> 2644.32 | G80: ='Customer Phases - Inputs and As'!$H$49 -> 8.0103948 | H80: =D80*F80*G80 -> 8861.1564 | I80: =C80*D80*G80 -> 25317.59
B81: Credit card order request | C81: =C26+C44+C62 -> 7000 | D81: =(D26+D44+D62)/3 -> 0.25 | E81: =AVERAGE(G26,G44,G62) -> 0.35 | F81: =C81*G26 -> 2450 | G81: ='Customer Phases - Inputs and As'!$H$49 -> 8.0103948 | H81: =D81*F81*G81 -> 4906.3668 | I81: =C81*D81*G81 -> 14018.191
B82: Deposit products enquiry | C82: =C27+C45+C63 -> 1800 | D82: =(D27+D45+D63)/2 -> 0.041666667 | E82: =AVERAGE(G27,G45,G63) -> 0.35 | F82: =C82*G27 -> 630 | G82: ='Customer Phases - Inputs and As'!$H$49 -> 8.0103948 | H82: =D82*F82*G82 -> 210.27286 | I82: =C82*D82*G82 -> 600.77961
B83: Bill payments | C83: =C28+C46+C64 -> 2995.2 | D83: =(D28+D46+D64)/2 -> 0.16666667 | E83: =AVERAGE(G28,G46,G64) -> 0.1 | F83: =C83*G28 -> 299.52 | G83: ='Customer Phases - Inputs and As'!$H$49 -> 8.0103948 | H83: =D83*F83*G83 -> 399.87891 | I83: =C83*D83*G83 -> 3998.7891
B84: International Transfers | C84: 0 | D84: =(D29+D47+D65)/3 -> 0.27777778 | E84: =AVERAGE(G29,G47,G65) -> 0.2 | F84: =C84*G29 -> 0 | G84: ='Customer Phases - Inputs and As'!$H$49 -> 8.0103948 | H84: =D84*F84*G84 -> 0 | I84: =C84*D84*G84 -> 0
B85: Customer Details Update / KYC details | C85: =C30+C48+C66 -> 62502.3 | D85: =(D30+D48+D66)/2 -> 0.16833333 | E85: =AVERAGE(G30,G48,G66) -> 0.35 | F85: =C85*G30 -> 21875.805 | G85: ='Customer Phases - Inputs and As'!$H$49 -> 8.0103948 | H85: =D85*F85*G85 -> 29497.695 | I85: =C85*D85*G85 -> 84279.13
B86: Credit card info inquiry (& other CC servicing) | C86: =C31+C49+C67 -> 14400 | D86: =(D31+D49+D67)/2 -> 0.083333333 | E86: =AVERAGE(G31,G49,G67) -> 0.35 | F86: =C86*G31 -> 5040 | G86: ='Customer Phases - Inputs and As'!$H$49 -> 8.0103948 | H86: =D86*F86*G86 -> 3364.3658 | I86: =C86*D86*G86 -> 9612.4738
B87: Loan Servicing | C87: =C32+C50+C68 -> 147810 | D87: =(D32+D50+D68)/2 -> 0.33333333 | E87: =AVERAGE(G32,G50,G68) -> 0.35 | F87: =C87*G32 -> 51733.5 | G87: ='Customer Phases - Inputs and As'!$H$49 -> 8.0103948 | H87: =D87*F87*G87 -> 138135.25 | I87: =C87*D87*G87 -> 394672.15
B88: Total | C88: =sum(C72:C87) -> 817138.9 | E88: =AVERAGE(E72:E87) -> 0.28125 | F88: =sum(F72:F87) -> 198519.39 | H88: =sum(H72:H87) -> 285653.52 | I88: =sum(I72:I87) -> 1068280.2
C91: Year 1 | D91: Year 2 | F91: Year 3 | G91: Year 4 | H91: Year 5 | I91: Total Savings
B92: Cost Avoidance | C92: =$H$88*'Customer Phases - Inputs and As'!J$21*'Customer Phases - Inputs and As'!J$22 -> 12854.408 | D92: =$H$88*'Customer Phases - Inputs and As'!K$21*'Customer Phases - Inputs and As'!K$22-($H$88*'Customer Phases - Inputs and As'!K$21*'Customer Phases - Inputs and As'!K$22*'Customer Phases - Inputs and As'!K$23^2) -> 69537.207 | F92: =$H$88*'Customer Phases - Inputs and As'!L$21*'Customer Phases - Inputs and As'!L$22-($H$88*'Customer Phases - Inputs and As'!L$21*'Customer Phases - Inputs and As'!L$22*'Customer Phases - Inputs and As'!L$2330) -> 137113.69 | G92: =$H$88*'Customer Phases - Inputs and As'!M$21*'Customer Phases - Inputs and As'!M$22-($H$88*'Customer Phases - Inputs and As'!M$21*'Customer Phases - Inputs and As'!M$22*'Customer Phases - Inputs and As'!M$23^4) -> 242795.54 | H92: =$H$88*'Customer Phases - Inputs and As'!N$21*'Customer Phases - Inputs and As'!N$22*1.1^3 -> 380204.83 | I92: =SUM(C92:H92) -> 842505.67

Sheet Extra Tables  Parking lot
C1: Net Income per Product | F1: Upsell Income per Product | I1: total digitally inactive customers | J1: ='Customer Phases - Inputs and As'!I13-750000 -> -749997.47
C2: Retail | D2: SME* | F2: Retail | G2: SME | I2: - 24/7 interbank transfer: | J2: 55932945
B3: Deposit Products | C3: ='Customer Phases - Inputs and As'!$C$38 -> 39.87 | D3: ='Customer Phases - Inputs and As'!$F$38 -> 39.87 | E3: Income /Customer* | I3: - Regular interbank transfer: | J3: 2869952 | L3: Legend
B4: Lending Products | E4: Upsell Income /Customer* | I4: - Internal transfer: | J4: 10645277 | L4: Assumed figure / extrapolated
C5: Average Income Per Product | F5: Average Income Per Segment | J5: 69448174 | L5: Data from HPB
I6: - Billing: | J6: 3897914
I7: - QR payment: | J7: 713022
I8: - Topup: | J8: 2780212
J9: 7391148
B10: ORIGINAL SERVICING CALCULATION - Retail + SME | I10: total CCs | J10: 273000 | L10: CC orders per month | M10: =50000/6 -> 8333.3333
C11: Servicing Journey Names: Retail and SME
C13: Branch | E13: Call Center | G13: Back-Office | I13: Impact | K13: Digital
B14: Service | C14: Volume | D14: Time Spent in HR | E14: Volume | F14: Time Spent in HR | G14: Volume | H14: Time Spent in HR | I14: Backbase Impact | J14: Notes | K14: Volume | L14: Time Spent in HR
B15: Accounts & Balance | C15: =J1*0.07 -> -52499.823 | D15: 0.083333333 | E15: =J1*0.09 -> -67499.772 | F15: 0.083333333 | G15: 0 | H15: 0 | I15: 0.35
B16: Account Statement | C16: =J1*0.05 -> -37499.874 | D16: 0.16666667 | E16: =C16/4 -> -9374.9684 | F16: 0.16666667 | I16: 0.45 | J16: back-office not involved
B17: Transaction Dispute | C17: =(J5+J9)*0.001 -> 76839.322 | D17: 0.33333333 | E17: =C17*2 -> 153678.64 | F17: 0.25 | G17: =(C17+E17)/2.5 -> 92207.186 | H17: 0.75 | I17: 0.45 | J17: Assumed as 1.7% of total service requests (HBR article on disputes), every dispute creates back-office task
B18: Internal Transfers | C18: =K18*0.2 -> 2129055.4 | D18: 0.16666667 | E18: - | F18: 0.083333333 | G18: 0 | H18: 0 | I18: 0.1 | J18: assuming 80% digital transfers; | K18: =J4 -> 10645277
B19: Inter Bank Transfers | C19: =K19*0.2 -> 11760579 | D19: 0.16666667 | E19: 0 | F19: 0.16666667 | G19: 0 | H19: 0.083333333 | I19: 0.1 | K19: =J3+J2 -> 58802897
B20: Debit Card Ordering | C20: ='Customer Phases - Inputs and As'!C73*0.1 -> 60937.7 | D20: =20/60 -> 0.33333333 | E20: =C20*0.13 -> 7921.901 | F20: =10/60 -> 0.16666667 | G20: =C20 -> 60937.7 | H20: 0.5 | I20: 0.5 | J20: using benchmarks - assuming 10% of all NTBs request for debit card
B21: Card block | C21: =J10*0.006 -> 1638 | D21: 0.16666667 | E21: =J10*0.01 -> 2730 | F21: 0.083333333 | G21: 0 | H21: 0 | I21: 0.2 | J21: back-office not involved
B22: Cards PIN reset | C22: =J10*0.004 -> 1092 | D22: 0.16666667 | E22: =J10*0.005 -> 1365 | F22: 0.083333333 | G22: 0 | H22: 0 | I22: 0.2 | J22: back-office not involved
B23: Card limit change | C23: =J10*0.032 -> 8736 | D23: 0.16666667 | E23: =J10*0.02 -> 5460 | F23: =10/60 -> 0.16666667 | G23: =C23+E23 -> 14196 | H23: =30/60 -> 0.5 | I23: 0.35 | J23: back-office in review & appraisal
B24: Credit card order request | C24: =(M10*0.7*12) -> 70000 | D24: =20/60 -> 0.33333333 | E24: =C24*0.1 -> 7000 | F24: =15/60 -> 0.25 | G24: =M10*12 -> 100000 | H24: 0.5 | I24: 0.35 | J24: back-office involved in review appraisal, card ordering/mailing
B25: Deposit products enquiry | C25: =J1*0.05 -> -37499.874 | D25: 0.083333333 | E25: =C25*2 -> -74999.747 | F25: 0.083333333 | G25: 0 | H25: 0 | I25: 0.4 | J25: Assumption: x2 product information inquiries in CC vs branch
B26: Bill payments | C26: =K26*0.012 -> 46774.968 | D26: 0.16666667 | E26: - | F26: 0.16666667 | G26: 0 | H26: 0 | I26: 0.1 | K26: =J6 -> 3897914
B27: International Transfers | C27: 200 | D27: =15/60 -> 0.25 | E27: 160 | F27: 0.083333333 | G27: 300 | H27: 0.25 | I27: 0.2
B28: Customer Details Update / KYC details | C28: ='Customer Phases - Inputs and As'!I13*0.03 -> 0.0759 | D28: =10/60 -> 0.16666667 | E28: =C28*0.02 -> 0.001518 | F28: =10/60 -> 0.16666667 | G28: 0 | H28: 0 | I28: 0.35
B29: Credit card info inquiry (& other CC servicing) | C29: =J10*0.07 -> 19110 | D29: =10/60 -> 0.16666667 | E29: =J10*0.1 -> 27300 | F29: =10/60 -> 0.16666667 | G29: 0 | H29: 0 | I29: 0.4 | J29: Assumption: x2 product information inquiries in branch vs CC
B30: Loan Servicing | C30: =J10*0.7 -> 191100 | D30: =15/60 -> 0.25 | E30: =J10*0.3 -> 81900 | F30: =10/60 -> 0.16666667 | G30: =(E30+C30)/10 -> 27300 | H30: 0.25 | I30: 0.5 | J30: Assuming 10% of servicing requests require BO involvement (ex: request to change schedule)
B33: Total interactions | C33: =SUM(C12:C31) -> 14238563 | E33: 280000 | G33: =SUM(G12:G31) -> 294940.89
C41: 215752500000
D42: =215/16840 -> 0.012767221
D43: =215/6900 -> 0.03115942
C50: Year 1 | D50: Year 2 | E50: Year 3 | F50: Year 4 | G50: Year 5 | H50: Total
C51: Revenue Growth
B52: New Customer Onboarding | C52: ='Customer & Loan Acquisition - A'!I$19 -> 14968.837 | D52: ='Customer & Loan Acquisition - A'!J$19 -> 34372.886 | E52: ='Customer & Loan Acquisition - A'!K$19 -> 124075.03 | F52: ='Customer & Loan Acquisition - A'!L$19 -> 249258.86 | G52: ='Customer & Loan Acquisition - A'!M$19 -> 291393.37 | H52: =SUM(C52:G52) -> 714068.98
B53: Lending Origination (USL) | C53: ='Customer & Loan Acquisition - A'!I$28 -> 2824.8443 | D53: ='Customer & Loan Acquisition - A'!J$28 -> 24607.533 | E53: ='Customer & Loan Acquisition - A'!K$28 -> 72316.015 | F53: ='Customer & Loan Acquisition - A'!L$28 -> 170746.15 | G53: ='Customer & Loan Acquisition - A'!M$28 -> 368811.67 | H53: =SUM(C53:G53) -> 639306.21
B54: CC Origination | C54: ='Customer & Loan Acquisition - A'!I37 -> 134477.59 | D54: ='Customer & Loan Acquisition - A'!J37 -> 732155.77 | E54: ='Customer & Loan Acquisition - A'!K37 -> 1434427.6 | F54: ='Customer & Loan Acquisition - A'!L37 -> 2540132.3 | G54: ='Customer & Loan Acquisition - A'!M37 -> 2988390.9 | H54: =SUM(C54:G54) -> 7829584.2
B55: Customer Retention | C55: ='Customer & Loan Acquisition - A'!I$43 -> 1180.7788 | D55: ='Customer & Loan Acquisition - A'!J$43 -> 7071.5533 | E55: ='Customer & Loan Acquisition - A'!K$43 -> 13854.472 | F55: ='Customer & Loan Acquisition - A'!L$43 -> 24533.96 | G55: ='Customer & Loan Acquisition - A'!M$43 -> 27420.309 | H55: =SUM(C55:G55) -> 74061.073
B56: Product Upsell | C56: ='Customer & Loan Acquisition - A'!I$44 -> 108238.06 | D56: ='Customer & Loan Acquisition - A'!J$44 -> 589296.11 | E56: ='Customer & Loan Acquisition - A'!K$44 -> 1154539.3 | F56: ='Customer & Loan Acquisition - A'!L$44 -> 2044496.7 | G56: ='Customer & Loan Acquisition - A'!M$44 -> 2405290.2 | H56: =SUM(C56:G56) -> 6301860.4
C57: Cost Avoidance / Savings
B58: New Customer Onboarding cost | C58: ='Customer & Loan Acquisition - A'!I23 -> 14507.1 | D58: ='Customer & Loan Acquisition - A'!J23 -> 127340.1 | E58: ='Customer & Loan Acquisition - A'!K23 -> 203099.4 | F58: ='Customer & Loan Acquisition - A'!L23 -> 322380.01 | G58: ='Customer & Loan Acquisition - A'!M23 -> 370737.01 | H58: =SUM(C58:G58) -> 1038063.6
B59: Loan Origination Cost (USL) | C59: ='Customer & Loan Acquisition - A'!I32 -> 9958.5228 | D59: ='Customer & Loan Acquisition - A'!J32 -> 87413.7 | E59: ='Customer & Loan Acquisition - A'!K32 -> 139419.32 | F59: ='Customer & Loan Acquisition - A'!L32 -> 221300.51 | G59: ='Customer & Loan Acquisition - A'!M32 -> 254495.58 | H59: =SUM(C59:G59) -> 712587.63
B60: CC Origination Cost | C60: ='Customer & Loan Acquisition - A'!I41 -> 3784.9115 | D60: ='Customer & Loan Acquisition - A'!J41 -> 33223.112 | E60: ='Customer & Loan Acquisition - A'!K41 -> 52988.762 | F60: ='Customer & Loan Acquisition - A'!L41 -> 79441.088 | G60: ='Customer & Loan Acquisition - A'!M41 -> 91357.251 | H60: =SUM(C60:G60) -> 260795.12
B61: Daily banking Servicing Cost | C61: ='Customer & Loan Acquisition - A'!I46 -> 12854.408 | D61: ='Customer & Loan Acquisition - A'!J46 -> 69537.207 | E61: ='Customer & Loan Acquisition - A'!K46 -> 137113.69 | F61: ='Customer & Loan Acquisition - A'!L46 -> 242795.54 | G61: ='Customer & Loan Acquisition - A'!M46 -> 380204.83 | H61: =SUM(C61:G61) -> 842505.67
B62: Total Annual Benefits | C62: =SUM(C52:C61) -> 302795.05 | D62: =SUM(D52:D61) -> 1705018 | E62: =SUM(E52:E61) -> 3331833.6 | F62: =SUM(F52:F61) -> 5895085.1 | G62: =SUM(G52:G61) -> 7178101.2 | H62: =SUM(H52:H61) -> 18412833
B65: ROI (w/Cost)
C66: Year 1 | D66: Year 2 | E66: Year 3 | F66: Year 4 | G66: Year 5 | H66: Total
C67: Revenue Growth
A68: Backbase Benefits | B68: New Customer Onboarding | C68: ='Customer & Loan Acquisition - A'!I$19 -> 14968.837 | D68: ='Customer & Loan Acquisition - A'!J$19 -> 34372.886 | E68: ='Customer & Loan Acquisition - A'!K$19 -> 124075.03 | F68: ='Customer & Loan Acquisition - A'!L$19 -> 249258.86 | G68: ='Customer & Loan Acquisition - A'!M$19 -> 291393.37 | H68: =SUM(C68:G68) -> 714068.98
B69: Lending Origination | C69: ='Customer & Loan Acquisition - A'!I$28 -> 2824.8443 | D69: ='Customer & Loan Acquisition - A'!J$28 -> 24607.533 | E69: ='Customer & Loan Acquisition - A'!K$28 -> 72316.015 | F69: ='Customer & Loan Acquisition - A'!L$28 -> 170746.15 | G69: ='Customer & Loan Acquisition - A'!M$28 -> 368811.67 | H69: =SUM(C69:G69) -> 639306.21 | J69: =H69/'Customer Phases - Inputs and As'!F38 -> 16034.768 | K69: loans
B70: Customer Retention | C70: ='Customer & Loan Acquisition - A'!I$43 -> 1180.7788 | D70: ='Customer & Loan Acquisition - A'!J$43 -> 7071.5533 | E70: ='Customer & Loan Acquisition - A'!K$43 -> 13854.472 | F70: ='Customer & Loan Acquisition - A'!L$43 -> 24533.96 | G70: ='Customer & Loan Acquisition - A'!M$43 -> 27420.309 | H70: =SUM(C70:G70) -> 74061.073
B71: Increase Engagement | C71: ='Cashflows - Analysis'!C$18 -> 0 | D71: ='Cashflows - Analysis'!D$18 -> 732155.77 | E71: ='Cashflows - Analysis'!E$18 -> 1434427.6 | F71: ='Cashflows - Analysis'!F$18 -> 2540132.3 | G71: ='Cashflows - Analysis'!G$18 -> 2988390.9 | H71: =SUM(C71:G71) -> 7695106.6
B72: Product Upsell | C72: ='Customer & Loan Acquisition - A'!I$44 -> 108238.06 | D72: ='Customer & Loan Acquisition - A'!J$44 -> 589296.11 | E72: ='Customer & Loan Acquisition - A'!K$44 -> 1154539.3 | F72: ='Customer & Loan Acquisition - A'!L$44 -> 2044496.7 | G72: ='Customer & Loan Acquisition - A'!M$44 -> 2405290.2 | H72: =SUM(C72:G72) -> 6301860.4
C73: Cost Avoidance / Savings
B74: Account opening cost | C74: ='Customer & Loan Acquisition - A'!I$23 -> 14507.1 | D74: ='Customer & Loan Acquisition - A'!J$23 -> 127340.1 | E74: ='Customer & Loan Acquisition - A'!K$23 -> 203099.4 | F74: ='Customer & Loan Acquisition - A'!L$23 -> 322380.01 | G74: ='Customer & Loan Acquisition - A'!M$23 -> 370737.01 | H74: =SUM(C74:G74) -> 1038063.6
B75: Loan Origination Cost | C75: ='Customer & Loan Acquisition - A'!I$32 -> 9958.5228 | D75: ='Customer & Loan Acquisition - A'!J$32 -> 87413.7 | E75: ='Customer & Loan Acquisition - A'!K$32 -> 139419.32 | F75: ='Customer & Loan Acquisition - A'!L$32 -> 221300.51 | G75: ='Customer & Loan Acquisition - A'!M$32 -> 254495.58 | H75: =SUM(C75:G75) -> 712587.63
B76: Servicing Cost | C76: ='Customer & Loan Acquisition - A'!I$46 -> 12854.408 | D76: ='Customer & Loan Acquisition - A'!J$46 -> 69537.207 | E76: ='Customer & Loan Acquisition - A'!K$46 -> 137113.69 | F76: ='Customer & Loan Acquisition - A'!L$46 -> 242795.54 | G76: ='Customer & Loan Acquisition - A'!M$46 -> 380204.83 | H76: =SUM(C76:G76) -> 842505.67
B77: Total Annual Benefits | C77: =SUM(C68:C76) -> 164532.55 | D77: =SUM(D68:D76) -> 1671794.9 | E77: =SUM(E68:E76) -> 3278844.9 | F77: =SUM(F68:F76) -> 5815644 | G77: =SUM(G68:G76) -> 7086743.9 | H77: =SUM(H68:H76) -> 18017560
C78: Costs: Licenses and Implementation
A79: Costs | B79: License Cost | C79: ='Cost Components'!C$8 -> 381000 | D79: ='Cost Components'!D$8 -> 707000 | E79: ='Cost Components'!E$8 -> 1117000 | F79: ='Cost Components'!F$8 -> 1114000 | G79: ='Cost Components'!G$8 -> 1152000 | H79: ='Cost Components'!J25
B80: Implementation Cost | C80: ='Cost Components'!C$9 -> 2508000 | D80: ='Cost Components'!D$9 -> 649000 | E80: ='Cost Components'!E$9 -> 275000 | F80: ='Cost Components'!F$9 -> 275000 | G80: ='Cost Components'!G$9 -> 275000 | H80: =SUM(C80:G80) -> 3982000
B81: Total Annual Cost | C81: =SUM(C79:C80) -> 2889000 | D81: =SUM(D79:D80) -> 1356000 | E81: =SUM(E79:E80) -> 1392000 | F81: =SUM(F79:F80) -> 1389000 | G81: =SUM(G79:G80) -> 1427000 | H81: =SUM(C81:G81) -> 8453000
C82: Net Annual Cash Flows
A83: Return on Investment | B83: Annual Return | C83: =C77-C81 -> -2724467.4 | D83: =D77-D81 -> 315794.86 | E83: =E77-E81 -> 1886844.9 | F83: =F77-F81 -> 4426644 | G83: =G77-G81 -> 5659743.9 | H83: =SUM(C83:G83) -> 9564560.2
B84: Net Present Value of Cash flows (@ 10%) | C84: =C83 -> -2724467.4 | D84: =D$83/(1+'Cashflows - Analysis'!$J$14)^1 -> 287086.24 | E84: =E$83/(1+'Cashflows - Analysis'!$J$14)^2 -> 1559375.9 | F84: =F$83/(1+'Cashflows - Analysis'!$J$14)^3 -> 3325803.2 | G84: =G$83/(1+'Cashflows - Analysis'!$J$14)^4 -> 3865681.2 | H84: =SUM(C84:G84) -> 6313479.1
B86: Payback period (years) | C86: =4+(B91/B92) -> 3.6413081
B87: ROI | C87: =(H77-H81)/H81 -> 1.1314989
B91: =sum(C84:E84) -> -878005.28
B92: =F84+B91 -> 2447797.9

Sheet IT Cost Savings - Inputs and An
B2: Backbase VC-Business Case
B3: IT Cost Saving Analysis
C7: Required info
C8: Calculated Info
C9: Assumptions
C14: System Name | D14: Total | E14: 1 | F14: 2 | G14: 3 | H14: 4 | I14: 5 | J14: 6 | K14: 7 | L14: 8 | M14: 9 | N14: 10 | O14: 11 | P14: 12 | Q14: 13 | R14: 14 | S14: 15
C15: Customer licenses Costs | D15: =sum(E15:S15) -> 7000000 | E15: 1000000 | F15: 1500000 | G15: 1500000 | H15: 1500000 | I15: 1500000
C16: Implementation costs | D16: =sum(E16:S16) -> 4000000 | E16: 2000000 | F16: 500000 | G16: 500000 | H16: 500000 | I16: 500000
C21: Year | E21: Year 1 | F21: Year 2 | G21: Year 3 | H21: Year 4 | I21: Year 5
C22: Total Costs Saved (BB Effectiveness Applied) | D22: =SUM(E22:I22) -> 41800000 | E22: =sum(E23:E24)*('Customer Phases - Inputs and As'!C21) -> 3300000 | F22: =sum(F23:F24)*('Customer Phases - Inputs and As'!D21) -> 7700000 | G22: =sum(G23:G24)*('Customer Phases - Inputs and As'!E21) -> 8800000 | H22: =sum(H23:H24)*('Customer Phases - Inputs and As'!F21) -> 11000000 | I22: =sum(I23:I24)*('Customer Phases - Inputs and As'!G21) -> 11000000
C23: Customer licenses | D23: =sum(E23:I23) -> 35000000 | E23: =D15 -> 7000000 | F23: =E23 -> 7000000 | G23: =F23 -> 7000000 | H23: =G23 -> 7000000 | I23: =H23 -> 7000000
C24: Implementation costs | D24: =sum(E24:I24) -> 20000000 | E24: =D16 -> 4000000 | F24: =E24 -> 4000000 | G24: =F24 -> 4000000 | H24: =G24 -> 4000000 | I24: =H24 -> 4000000

Sheet Cashflows - Analysis
B2: Backbase VC-Business Case
B3: Cashflows
C7: Required info
C8: Calculated Info
C9: Assumptions
C13: Year 1 | D13: Year 2 | E13: Year 3 | F13: Year 4 | G13: Year 5 | H13: Total | J13: Discount Rate | M13: NPV | N13: {=NPV(J14,C30:G30)} -> 4054730.8
B14: Total Yearly Cash Inflow | C14: =C20+C15 -> 164532.55 | D14: =D20+D15 -> 1705018 | E14: =E20+E15 -> 3331833.6 | F14: =F20+F15 -> 5895085.1 | G14: =G20+G15 -> 7178101.2 | H14: =sum(C14:G14) -> 18274570 | J14: 0.1 | M14: ROI | N14: =H14+H25 -> 29274570 | O14: =(H14+H25)/H25 -> 2.6613246
B15: Revenue Generation | C15: =sum(C16:C19) -> 127212.52 | D15: =sum(D16:D19) -> 1387503.9 | E15: =sum(E16:E19) -> 2799212.5 | F15: =sum(F16:F19) -> 5029167.9 | G15: =sum(G16:G19) -> 6081306.5 | H15: =sum(C15:G15) -> 15424403 | J15: =H15/5 -> 3084880.7
B16: Customer Onboarding Revenue Generation | C16: ='Customer & Loan Acquisition - A'!I16 -> 14968.837 | D16: ='Customer & Loan Acquisition - A'!J16 -> 34372.886 | E16: ='Customer & Loan Acquisition - A'!K16 -> 124075.03 | F16: ='Customer & Loan Acquisition - A'!L16 -> 249258.86 | G16: ='Customer & Loan Acquisition - A'!M16 -> 291393.37 | H16: =sum(C16:G16) -> 714068.98 | J16: =H16/5 -> 142813.8
B17: Loan Origination Revenue Generation | C17: ='Customer & Loan Acquisition - A'!I25 -> 2824.8443 | D17: ='Customer & Loan Acquisition - A'!J25 -> 24607.533 | E17: ='Customer & Loan Acquisition - A'!K25 -> 72316.015 | F17: ='Customer & Loan Acquisition - A'!L25 -> 170746.15 | G17: ='Customer & Loan Acquisition - A'!M25 -> 368811.67 | H17: =sum(C17:G17) -> 639306.21 | J17: =H17/5 -> 127861.24
B18: CLO Revenue Generation | C18: ='Customer & Loan Acquisition - A'!I34 -> 0 | D18: ='Customer & Loan Acquisition - A'!J34 -> 732155.77 | E18: ='Customer & Loan Acquisition - A'!K34 -> 1434427.6 | F18: ='Customer & Loan Acquisition - A'!L34 -> 2540132.3 | G18: ='Customer & Loan Acquisition - A'!M34 -> 2988390.9 | H18: =sum(C18:G18) -> 7695106.6 | J18: =H18/5 -> 1539021.3
B19: Customer Loyalty and Retention | C19: ='Customer & Loan Acquisition - A'!I42 -> 109418.84 | D19: ='Customer & Loan Acquisition - A'!J42 -> 596367.66 | E19: ='Customer & Loan Acquisition - A'!K42 -> 1168393.8 | F19: ='Customer & Loan Acquisition - A'!L42 -> 2069030.7 | G19: ='Customer & Loan Acquisition - A'!M42 -> 2432710.5 | H19: =sum(C19:G19) -> 6375921.5 | J19: =H19/5 -> 1275184.3
B20: Cost Reduction | C20: =SUM(C21:C24) -> 37320.031 | D20: =SUM(D21:D24) -> 317514.12 | E20: =SUM(E21:E24) -> 532621.17 | F20: =SUM(F21:F24) -> 865917.15 | G20: =SUM(G21:G24) -> 1096794.7 | H20: =SUM(C20:G20) -> 2850167.1 | J20: =H20/5 -> 570033.43 | M20: Payback Period | N20: =if(C32>0,1+-C30/C30,if(D32>0,1+-C30/D30,if(E32>0,1+-C30/E30,if(F32>0,1+-C30/F30,if(G32>0,1+-C30/G30))))) -> 1.7279603
B21: Customer Onboarding Cost Reduction | C21: ='Customer & Loan Acquisition - A'!I20 -> 14507.1 | D21: ='Customer & Loan Acquisition - A'!J20 -> 127340.1 | E21: ='Customer & Loan Acquisition - A'!K20 -> 203099.4 | F21: ='Customer & Loan Acquisition - A'!L20 -> 322380.01 | G21: ='Customer & Loan Acquisition - A'!M20 -> 370737.01 | H21: =sum(C21:G21) -> 1038063.6 | J21: =H21/5 -> 207612.72 | M21: IRR | N21: =IRR(C30:G30) -> 0.45666217
B22: Loan Origination Cost Reduction | C22: ='Customer & Loan Acquisition - A'!I29 -> 9958.5228 | D22: ='Customer & Loan Acquisition - A'!J29 -> 87413.7 | E22: ='Customer & Loan Acquisition - A'!K29 -> 139419.32 | F22: ='Customer & Loan Acquisition - A'!L29 -> 221300.51 | G22: ='Customer & Loan Acquisition - A'!M29 -> 254495.58 | H22: =sum(C22:G22) -> 712587.63 | J22: =H22/5 -> 142517.53
B23: CLO Cost Reduction | C23: ='Customer & Loan Acquisition - A'!I38 -> 0 | D23: ='Customer & Loan Acquisition - A'!J38 -> 33223.112 | E23: ='Customer & Loan Acquisition - A'!K38 -> 52988.762 | F23: ='Customer & Loan Acquisition - A'!L38 -> 79441.088 | G23: ='Customer & Loan Acquisition - A'!M38 -> 91357.251 | H23: =sum(C23:G23) -> 257010.21 | J23: =H23/5 -> 51402.043
B24: Customer Servicing | C24: ='Customer & Loan Acquisition - A'!I46 -> 12854.408 | D24: ='Customer & Loan Acquisition - A'!J46 -> 69537.207 | E24: ='Customer & Loan Acquisition - A'!K46 -> 137113.69 | F24: ='Customer & Loan Acquisition - A'!L46 -> 242795.54 | G24: ='Customer & Loan Acquisition - A'!M46 -> 380204.83 | H24: =sum(C24:G24) -> 842505.67 | J24: =H24/5 -> 168501.13
B25: Total Cash Outflow | C25: =Sum(C26:C28) -> 3000000 | D25: =Sum(D26:D28) -> 2000000 | E25: =Sum(E26:E28) -> 2000000 | F25: =Sum(F26:F28) -> 2000000 | G25: =Sum(G26:G28) -> 2000000 | H25: =sum(C25:G25) -> 11000000
B26: Customer licenses | C26: ='IT Cost Savings - Inputs and An'!E15 -> 1000000 | D26: ='IT Cost Savings - Inputs and An'!F15 -> 1500000 | E26: ='IT Cost Savings - Inputs and An'!G15 -> 1500000 | F26: ='IT Cost Savings - Inputs and An'!H15 -> 1500000 | G26: ='IT Cost Savings - Inputs and An'!I15 -> 1500000 | H26: =sum(C26:G26) -> 7000000
B27: Implementation costs (ITSS) | C27: ='IT Cost Savings - Inputs and An'!E16 -> 2000000 | D27: ='IT Cost Savings - Inputs and An'!F16 -> 500000 | E27: ='IT Cost Savings - Inputs and An'!G16 -> 500000 | F27: ='IT Cost Savings - Inputs and An'!H16 -> 500000 | G27: ='IT Cost Savings - Inputs and An'!I16 -> 500000 | H27: =sum(C27:G27) -> 4000000
B28: Manage and Hosting Costs | H28: =sum(C28:G28) -> 0
B30: Total Cash Flows | C30: =C14-C25 -> -2835467.4 | D30: =D14-D25 -> -294982.03 | E30: =E14-E25 -> 1331833.6 | F30: =F14-F25 -> 3895085.1 | G30: =G14-G25 -> 5178101.2 | H30: =sum(C30:G30) -> 7274570.4
B31: Present Value | C31: =C30/(1+$J$14)^0 -> -2835467.4 | D31: =D30/(1+$J$14)^1 -> -268165.48 | E31: =E30/(1+$J$14)^2 -> 1100689 | F31: =F30/(1+$J$14)^3 -> 2926435.1 | G31: =G30/(1+$J$14)^4 -> 3536712.8 | H31: =sum(C31:G31) -> 4460203.9
B32: Closing Balance | C32: =C30 -> -2835467.4 | D32: =C32+D30 -> -3130449.5 | E32: =D32+E30 -> -1798615.8 | F32: =E32+F30 -> 2096469.2 | G32: =F32+G30 -> 7274570.4 | H32: =sum(C32:G32) -> 1606506.9
C38: Year 1 | D38: Year 2 | E38: Year 3 | F38: Year 4 | G38: Year 5 | H38: Total
B39: Total Yearly Cash Inflow | C39: =C14 -> 164532.55 | D39: =D14 -> 1705018 | E39: =E14 -> 3331833.6 | F39: =F14 -> 5895085.1 | G39: =G14 -> 7178101.2 | H39: =sum(C39:G39) -> 18274570
B40: Total Cash Outflow | C40: =C30 -> -2835467.4 | D40: =D30 -> -294982.03 | E40: =E30 -> 1331833.6 | F40: =F30 -> 3895085.1 | G40: =G30 -> 5178101.2 | H40: =H30 -> 7274570.4
B41: Customer licenses | C41: =C26 -> 1000000 | D41: =D26 -> 1500000 | E41: =E26 -> 1500000 | F41: =F26 -> 1500000 | G41: =G26 -> 1500000 | H41: =sum(C41:G41) -> 7000000
B42: Implementation costs | C42: =C27 -> 2000000 | D42: =D27 -> 500000 | E42: =E27 -> 500000 | F42: =F27 -> 500000 | G42: =G27 -> 500000 | H42: =sum(C42:G42) -> 4000000
B43: Total Cash Flows | C43: =C29+C40 -> -2835467.4 | D43: =D29+D40 -> -294982.03 | E43: =E29+E40 -> 1331833.6 | F43: =F29+F40 -> 3895085.1 | G43: =G29+G40 -> 5178101.2 | H43: =sum(C43:G43) -> 7274570.4
B44: Present Value @ 10% | C44: =C43/(1+$J$14)^0 -> -2835467.4 | D44: =D43/(1+$J$14)^1 -> -268165.48 | E44: =E43/(1+$J$14)^2 -> 1100689 | F44: =F43/(1+$J$14)^3 -> 2926435.1 | G44: =G43/(1+$J$14)^4 -> 3536712.8 | H44: =sum(C44:G44) -> 4460203.9
B47: TOTAL RB+EB
C49: Year 1 | D49: Year 2 | E49: Year 3 | F49: Year 4 | G49: Year 5 | H49: Total
B50: RB:Total Yearly Cash Inflow | C50: =C39 -> 164532.55 | D50: =D39 -> 1705018 | E50: =E39 -> 3331833.6 | F50: =F39 -> 5895085.1 | G50: =G39 -> 7178101.2 | H50: =sum(C50:G50) -> 18274570
B51: EB:Total Yearly Cash Inflow | C51: =C63 -> 0 | D51: =D63 | E51: =E63 | F51: =F63 | G51: =G63 | H51: =sum(C51:G51) -> 0 | K51: ROI | L51: =H52+H53 -> 29274570 | M51: =L51/H53 -> 2.6613246
B52: Total Cash Inflow RB+EB | C52: =C50+C51 -> 164532.55 | D52: =D50+D51 -> 1705018 | E52: =E50+E51 -> 3331833.6 | F52: =F50+F51 -> 5895085.1 | G52: =G50+G51 -> 7178101.2 | H52: =sum(C52:G52) -> 18274570
B53: Total Cash Outflow | C53: =C54+C55 -> 3000000 | D53: =D54+D55 -> 2000000 | E53: =E54+E55 -> 2000000 | F53: =F54+F55 -> 2000000 | G53: =G54+G55 -> 2000000 | H53: =sum(C53:G53) -> 11000000
B54: Customer licenses | C54: =C41+C65 -> 1000000 | D54: =D41+D65 -> 1500000 | E54: =E41+E65 -> 1500000 | F54: =F41+F65 -> 1500000 | G54: =G41+G65 -> 1500000 | H54: =sum(C54:G54) -> 7000000
B55: Implementation costs | C55: =C42+C66 -> 2000000 | D55: =D42+D66 -> 500000 | E55: =E42+E66 -> 500000 | F55: =F42+F66 -> 500000 | G55: =G42+G66 -> 500000 | H55: =sum(C55:G55) -> 4000000
B56: Total Cash Flows | C56: =C52+C53 -> 3164532.6 | D56: =D52+D53 -> 3705018 | E56: =E52+E53 -> 5331833.6 | F56: =F52+F53 -> 7895085.1 | G56: =G52+G53 -> 9178101.2 | H56: =sum(C56:G56) -> 29274570
B57: Present Value @ 10% | C57: =C56/(1+$J$14)^0 -> 3164532.6 | D57: =D56/(1+$J$14)^1 -> 3368198.2 | E57: =E56/(1+$J$14)^2 -> 4406474.1 | F57: =F56/(1+$J$14)^3 -> 5931694.3 | G57: =G56/(1+$J$14)^4 -> 6268766.6 | H57: =sum(C57:G57) -> 23139666
B61: EB data - copy from EB sheet
C62: Year 1 | D62: Year 2 | E62: Year 3 | F62: Year 4 | G62: Year 5 | H62: Total
B63: Total Yearly Cash Inflow | C63: 0
B64: Total Cash Outflow | C64: 0
B65: Customer licenses
B66: Implementation costs
B67: Net Cash Flow | C67: 0
B68: Present Value @ 10% | C68: 0

Sheet Working sheets>>

Sheet Annual report data
B1: Rough working sheet
B2: Source: Annual report, specified if other
B3: Currency Units: VND millions
B6: Currency Conversion | C6: 2022 | D6: 2023 | E6: 2024
B7: VND/USD | C7: 23380 | D7: 23836 | E7: 25056
C9: VND millions | H9: USD actuals
B10: Inputs from Annual report | C10: 2022 | D10: 2023 | E10: 2024 | F10: YoY change | G10: CAGR 22-24 | H10: 2022 | I10: 2023 | J10: 2024 | K10: Impact sense check
B11: Operating Income - considered in ROI model | C11: =SUM(C13:C14) -> 8373244 | D11: =SUM(D13:D14) -> 8378576 | E11: =SUM(E13:E14) -> 11078105 | F11: =(E11-D11)/D11 -> 0.32219425 | G11: =((E11/C11)^(1/2)-1) -> 0.15023311 | I11: =(D11*10^6)/D$7 -> 3.5150931e+08 | J11: =(E11*10^6)/E$7 -> 4.4213382e+08 | K11: =('Cashflows - Analysis'!H15)/J11 -> 0.034886278
B12: Break-up | F12: =(D11-C11)/C11 -> 0.00063679023
B13: NII | C13: 7005927 | D13: 7070719 | E13: 9966410 | F13: =(E13-D13)/D13 -> 0.40953275
B14: Fee and Commission | C14: 1367317 | D14: 1307857 | E14: 1111695 | F14: =(E14-D14)/D14 -> -0.14998735
B15: Forex | D15: 602470 | E15: 570581
B16: Trading securities | D16: 109180 | E16: -172141
B17: Inv. Securities | D17: 128660 | E17: 321407
B18: Other Income | D18: 190721 | E18: 609602
B19: Cap contribution | D19: 1445 | E19: 14384
B22: Operating Expenses | D22: 8278781 | E22: 5816843 | F22: =(E22-D22)/D22 -> -0.29737929 | I22: =(D22*10^6)/D$7 -> 3.4732258e+08 | J22: =(E22*10^6)/E$7 -> 2.321537e+08 | K22: ='Cashflows - Analysis'!H20/J22 -> 0.01227707
B23: Staff costs | D23: 1856595 | E23: 2113460 | F23: =(E23-D23)/D23 -> 0.13835274 | I23: =(D23*10^6)/D$7 -> 77890376 | J23: =(E23*10^6)/E$7 -> 84349457
B27: Total Operating Income as reported | E27: 12409000 | J27: =(E27*10^6)/E$7 -> 4.9525064e+08
J28: =J27/'Customer Phases - Inputs and As'!F15 -> 135.45272
B30: Computations
B31: Customers | C31: 3656262
B32: Growth rate | C32: 0.2
B33: New customers | C33: =C31*C32 -> 731252.4
B34: Digitally onboarded | C34: 0.82
B35: In branch | C35: =C33*(1-C34) -> 131625.43

Sheet Sheet8
E6: Interests | F6: 100 | G6: 100
E7: Leakage | F7: 20 | G7: =G6-F12 -> 18.5
E8: Opened accounts | F8: 80
F9: 0.075
E10: BB Impact | F10: =F7*F9 -> 1.5
E12: Opened account after BB | F12: =SUM(F8+F10) -> 81.5

Sheet Sheet7
C5: Inputs from Annual report 2023, 2024
G6: Growth Rates
D7: VND millions | G7: YoY change | I7: CAGR
D8: 2022 | E8: 2023 | F8: 2024 | G8: 2022-23 | H8: 2023-24 | I8: 2022-24
C9: Operating Income - considered in financial model | D9: =SUM(D11:D12) -> 8373244 | E9: =SUM(E11:E12) -> 8378576 | F9: =SUM(F11:F12) -> 11078105 | G9: =(E9-D9)/D9 -> 0.00063679023 | H9: =(F9-E9)/E9 -> 0.32219425 | I9: =((F9/D9)^(1/2)-1) -> 0.15023311
C10: Sum of:
C11: Net Interest Income | D11: 7005927 | E11: 7070719 | F11: 9966410
C12: Net Fee and Commission | D12: 1367317 | E12: 1307857 | F12: 1111695

Sheet Funnel stats
B1: Funnel Stats for SeABank
B2: Source: SeABank Data
C4: Q4 2024 | D4: Annual | F4: Leakage in # | G4: CAC (Benchmark) | H4: CAC (Assumed for traditional bank) | I4: Value loss / customer
B5: App downloaded | C5: 76836 | D5: =C5*4 -> 307344 | G5: 6 | H5: 8 | I5: 39
B6: Register | C6: 52075 | D6: =C6*4 -> 208300 | E6: =(D5-D6)/D5 -> 0.3222578 | F6: =D5-D6 -> 99044 | G6: =$F6*G$5 -> 594264 | H6: =$F6*H$5 -> 792352 | I6: =$F6*I$5 -> 3862716 | J6: =D6*H5 -> 1666400 | K6: =J6*17% -> 283288
B7: ID, OTP | C7: 51646 | D7: =C7*4 -> 206584 | E7: =(D6-D7)/D6 -> 0.0082381181 | F7: =D6-D7 -> 1716 | G7: =$F7*G$5 -> 10296 | H7: =$F7*H$5 -> 13728 | I7: =$F7*I$5 -> 66924
B8: Opened account | C8: 43191 | D8: =C8*4 -> 172764 | E8: =(D7-D8)/D7 -> 0.16371065 | F8: =D7-D8 -> 33820 | G8: =$F8*G$5 -> 202920 | H8: =$F8*H$5 -> 270560 | I8: =$F8*I$5 -> 1318980
F9: =D5-D8 -> 134580 | G9: =$F9*G$5 -> 807480 | H9: =$F9*H$5 -> 1076640 | I9: =$F9*I$5 -> 5248620
B11: Leakage from lack of follow up | F11: =D6-D8 -> 35536 | G11: =$F11*G$5 -> 213216 | H11: =$F11*H$5 -> 284288 | I11: =$F11*I$5 -> 1385904
B13: Average Balance per customer Industry Benchmark
B14: Source: Industry report during similar exercise for VN customer
G15: Balance / customer | J15: Considering realistic customer activation rate
E16: Customers | F16: CASA Balance | G16: VND | H16: USD | J16: Number of Active Customers | K16: VND | L16: USD
D17: MSB | E17: 4000000 | F17: 20000000000000 | G17: =F17/E17 -> 5000000 | H17: =G17/'Annual report data'!$C$7 -> 213.858 | J17: =E17*$H$24 -> 1600000 | K17: =F17/J17 -> 12500000 | L17: =K17/'Annual report data'!$C$7 -> 534.645
D18: MB | E18: 20000000 | F18: 177000000000000 | G18: =F18/E18 -> 8850000 | H18: =G18/'Annual report data'!$C$7 -> 378.52866 | J18: =E18*$H$24 -> 8000000 | K18: =F18/J18 -> 22125000 | L18: =K18/'Annual report data'!$C$7 -> 946.32164
D19: Techom | E19: 10000000 | F19: 132000000000000 | G19: =F19/E19 -> 13200000 | H19: =G19/'Annual report data'!$C$7 -> 564.58512 | J19: =E19*$H$24 -> 4000000 | K19: =F19/J19 -> 33000000 | L19: =K19/'Annual report data'!$C$7 -> 1411.4628
D20: VPBank | E20: 5200000 | F20: 53000000000000 | G20: =F20/E20 -> 10192308 | H20: =G20/'Annual report data'!$C$7 -> 435.9413 | J20: =E20*$H$24 -> 2080000 | K20: =F20/J20 -> 25480769 | L20: =K20/'Annual report data'!$C$7 -> 1089.8533
D21: TPBank | E21: 6000000 | F21: 35000000000000 | G21: =F21/E21 -> 5833333.3 | H21: =G21/'Annual report data'!$C$7 -> 249.501 | J21: =E21*$H$24 -> 2400000 | K21: =F21/J21 -> 14583333 | L21: =K21/'Annual report data'!$C$7 -> 623.75249
G24: Customer Activation Rate (Assumed) | H24: 0.4 | J24: Simple Average | L24: =AVERAGE(L17:L21) -> 921.20704
J25: Weighted Average | L25: =SUMPRODUCT(J17:J21,L17:L21)/SUM(J17:J21) -> 986.49099

Sheet Cost Components
C3: Year 1 | D3: Year 2 | E3: Year 3 | F3: Year 4 | G3: Year 5 | H3: Totals
B4: Projected # users - RETAIL | C4: 35000 | D4: 150000 | E4: 178000 | F4: 197000 | G4: 215000 | H4: =SUM(C4:G4) -> 775000
B5: Retail banking license | C5: 204000 | D5: 530000 | E5: 625000 | F5: 622000 | G5: 660000 | H5: =SUM(C5:G5) -> 2641000
B6: Digital Onboarding license - retail | C6: 177000 | D6: 177000 | E6: 177000 | F6: 177000 | G6: 177000 | H6: =SUM(C6:G6) -> 885000
B7: Digital Lending license - retail | E7: 315000 | F7: 315000 | G7: 315000 | H7: 315000 | I7: 315000 | J7: =SUM(E7:I7) -> 1575000
B8: License cost per year | C8: =sum(C5:C7) -> 381000 | D8: =sum(D5:D7) -> 707000 | E8: =sum(E5:E7) -> 1117000 | F8: =sum(F5:F7) -> 1114000 | G8: =sum(G5:G7) -> 1152000 | H8: 315000 | I8: =sum(I5:I7) -> 315000 | J8: =sum(C8:I8) -> 5101000
B9: Implementation cost per year | C9: =4560*550 -> 2508000 | D9: =(680+(750/2)+(250/2))*550 -> 649000 | E9: =(1000/2)*550 -> 275000 | F9: =(1000/2)*550 -> 275000 | G9: =(1000/2)*550 -> 275000 | H9: =SUM(C9:G9) -> 3982000
B10: Investment / Net Cash Outflow | C10: =sum(C8:C9) -> 2889000 | D10: =sum(D8:D9) -> 1356000 | E10: =sum(E8:E9) -> 1392000 | F10: =sum(F8:F9) -> 1389000 | G10: =sum(G8:G9) -> 1427000 | H10: =H9+J8 -> 9083000
B11: Discounted Net Cash Flow | C11: =(C10)/(1+$C$12)^0 -> 2889000 | D11: =(D10)/(1+$C$12)^1 -> 1232727.3 | E11: =(E10)/(1+$C$12)^2 -> 1150413.2 | F11: =(F10)/(1+$C$12)^3 -> 1043576.3 | G11: =(G10)/(1+$C$12)^4 -> 974660.2 | H11: =SUM(C11:G11) -> 7290377 | I11: {=NPV(C12,D10:G10)+C10} -> 7290377
B12: WACC | C12: 0.1

Sheet 1.2 Servicing
A1: 1.2
B6: Servicing Journey Names | C6: Branch | G6: Call Center | K6: Back Office | P6: Benefits
C7: Yearly Volume | D7: Time Spent/Visit (Mins) | E7: Baseline (Annual Cost) | G7: Yearly Volume | H7: Time Spent/Visit (Mins) | I7: Baseline (Annual Cost) | K7: Yearly Volume | L7: Time Spent/Visit (Mins) | M7: Baseline (Annual Cost) | N7: ABK FTE/Hr rate (US$) | P7: Baseline (Annual Cost) | Q7: Backbase Impact | R7: Cost Avoidance (USD)
B8: Accounts & Balance | C8: 6000 | D8: 5 | E8: 7875 | G8: 3600 | H8: 5 | I8: 4725 | K8: 0 | L8: 0 | M8: $ - | N8: 15.75 | P8: =SUM(E8,I8,M8) -> 12600 | Q8: 0.25 | R8: =P8*Q8 -> 3150
B9: Account Statement | C9: 6000 | D9: 10 | E9: 15750 | G9: 6600 | H9: 10 | I9: 17325 | K9: 0 | L9: 0 | M9: $ - | N9: 15.75 | P9: =SUM(E9,I9,M9) -> 33075 | Q9: 0.35 | R9: =P9*Q9 -> 11576.25
B10: Transaction Dispute | C10: 3600 | D10: 15 | E10: 14175 | G10: 4800 | H10: 15 | I10: 18900 | K10: 8400 | L10: 20 | M10: 44100 | N10: 15.75 | P10: =SUM(E10,I10,M10) -> 77175 | Q10: 0.45 | R10: =P10*Q10 -> 34728.75
B11: ABK Internal Transfers | C11: 1370000 | D11: 5 | E11: 1798125 | G11: 2000 | H11: 5 | I11: 2625 | K11: 0 | L11: 0 | M11: $ - | N11: 15.75 | P11: =SUM(E11,I11,M11) -> 1800750 | Q11: 0.35 | R11: =P11*Q11 -> 630262.5
B12: Intra Bank Transfers | C12: 44000 | D12: 5 | E12: 57750 | G12: 1000 | H12: 10 | I12: 2625 | K12: 44000 | L12: 5 | M12: 57750 | N12: 15.75 | P12: =SUM(E12,I12,M12) -> 118125 | Q12: 0.35 | R12: =P12*Q12 -> 41343.75
B13: Link Payment | C13: 0 | D13: 0 | E13: $ - | G13: 0 | H13: 0 | I13: $ - | K13: 0 | L13: 0 | M13: $ - | N13: 15.75 | P13: =SUM(E13,I13,M13) -> 0 | Q13: 0.35 | R13: =P13*Q13 -> 0
B14: Bill Pay | C14: 0 | D14: 0 | E14: $ - | G14: 0 | H14: 0 | I14: $ - | K14: 0 | L14: 0 | M14: $ - | N14: 15.75 | P14: =SUM(E14,I14,M14) -> 0 | Q14: 0.35 | R14: =P14*Q14 -> 0
B15: Cheque Ordering | C15: 600 | D15: 10 | E15: 1575 | G15: 200 | H15: 5 | I15: 263 | K15: 800 | L15: 10 | M15: 2100 | N15: 15.75 | P15: =SUM(E15,I15,M15) -> 3938 | Q15: 0.5 | R15: =P15*Q15 -> 1969
B16: Cheque Deposits | C16: 257000 | D16: 5 | E16: 337313 | G16: 500 | H16: 5 | I16: 656 | K16: 0 | L16: 0 | M16: $ - | N16: 15.75 | P16: =SUM(E16,I16,M16) -> 337969 | Q16: 0.35 | R16: =P16*Q16 -> 118289.15
B17: Cards Management | C17: 15600 | D17: 10 | E17: 40950 | G17: 22000 | H17: 5 | I17: 28875 | K17: 12200 | L17: 10 | M17: 32025 | N17: 15.75 | P17: =SUM(E17,I17,M17) -> 101850 | Q17: 0.5 | R17: =P17*Q17 -> 50925
B18: Customer Details Update | C18: 7000 | D18: 10 | E18: 18375 | G18: 500 | H18: 10 | I18: 1313 | K18: 0 | L18: 0 | M18: $ - | N18: 15.75 | P18: =SUM(E18,I18,M18) -> 19688 | Q18: 0.35 | R18: =P18*Q18 -> 6890.8
B19: KYC | C19: 24000 | D19: 20 | E19: 126000 | G19: 200 | H19: 5 | I19: 263 | K19: 2400 | L19: 20 | M19: 12600 | N19: 15.75 | P19: =SUM(E19,I19,M19) -> 138863 | Q19: 0.5 | R19: =P19*Q19 -> 69431.5
B20: Loan Servicing | C20: 3780 | D20: 15 | E20: 14884 | G20: 12000 | H20: 10 | I20: 31500 | K20: 3000 | L20: 10 | M20: 7875 | N20: 15.75 | P20: =SUM(E20,I20,M20) -> 54259 | Q20: 0.35 | R20: =P20*Q20 -> 18990.65
B21: Online Banking Related | C21: 1500 | D21: 10 | E21: 3938 | G21: 5000 | H21: 5 | I21: 6563 | K21: 0 | L21: 0 | M21: $ - | N21: 15.75 | P21: =SUM(E21,I21,M21) -> 10501 | Q21: 0.35 | R21: =P21*Q21 -> 3675.35
B22: Total | C22: 1739080 | E22: 2436709 | G22: 58400 | I22: 115631 | K22: 70800 | M22: 156450 | P22: =sum(P8:P21) -> 2708793 | R22: =SUM(R8:R21) -> 991232.7
P23: =E22+I22+M22 -> 2708790
S28: =average(Q8:Q21) -> 0.38214286
S29: =P22*S28 -> 1035145.9

Sheet 3 Results
B2: Backbase VC-Business Case
B3: Results
B6: CUSTOMER NAME: | D6: BCP
B7: VC NAME: | D7: Nathalia Secin
B14: Financial Flows & Business Economics | L14: Financial Flows & Business Economics
B16: USD
C17: Year 1 | D17: Year 2 | E17: Year 3 | F17: Year 4 | G17: Year 5 | H17: Total
B18: Benefits | C18: ='1,2 Data and Calculations'!M301 -> #REF! | D18: ='1,2 Data and Calculations'!N301 -> #REF! | E18: ='1,2 Data and Calculations'!O301 -> #REF! | F18: ='1,2 Data and Calculations'!P301 -> #REF! | G18: ='1,2 Data and Calculations'!Q301 -> #REF! | H18: =SUM(C18:G18) -> #REF!
B19: Licences | C19: -4000000 | D19: -4000000 | E19: -4000000 | F19: -4000000 | G19: -4000000 | H19: =SUM(C19:G19) -> -20000000
B20: Implementation | C20: =C19*1.5 -> -6000000 | H20: =SUM(C20:G20) -> -6000000
B21: Manage Hosting | C21: -1000000 | D21: -1000000 | E21: -1000000 | F21: -1000000 | G21: -1000000 | H21: =SUM(C21:G21) -> -5000000
B22: Manage Service | C22: -500000 | D22: -500000 | E22: -500000 | F22: -500000 | G22: -500000 | H22: =SUM(C22:G22) -> -2500000
B26: Thousand USD
C27: Year 1 | D27: Year 2 | E27: Year 3 | F27: Year 4 | G27: Year 5 | H27: Total
B28: =B18 -> Benefits | C28: =C18/1000 -> #REF! | D28: =D18/1000 -> #REF! | E28: =E18/1000 -> #REF! | F28: =F18/1000 -> #REF! | G28: =G18/1000 -> #REF! | H28: =SUM(C28:G28) -> #REF!
B29: =B19 -> Licences | C29: =C19/1000 -> -4000 | D29: =D19/1000 -> -4000 | E29: =E19/1000 -> -4000 | F29: =F19/1000 -> -4000 | G29: =G19/1000 -> -4000 | H29: =SUM(C29:G29) -> -20000
B30: =B20 -> Implementation | C30: =C20/1000 -> -6000 | D30: =D20/1000 -> 0 | E30: =E20/1000 -> 0 | F30: =F20/1000 -> 0 | G30: =G20/1000 -> 0 | H30: =SUM(C30:G30) -> -6000
B31: =B21 -> Manage Hosting | C31: =C21/1000 -> -1000 | D31: =D21/1000 -> -1000 | E31: =E21/1000 -> -1000 | F31: =F21/1000 -> -1000 | G31: =G21/1000 -> -1000 | H31: =SUM(C31:G31) -> -5000
B32: =B22 -> Manage Service | C32: =C22/1000 -> -500 | D32: =D22/1000 -> -500 | E32: =E22/1000 -> -500 | F32: =F22/1000 -> -500 | G32: =G22/1000 -> -500 | H32: =SUM(C32:G32) -> -2500
B39: Total Benefits | C39: =SUM(C28) -> #REF! | D39: =SUM(D28) -> #REF! | E39: =SUM(E28) -> #REF! | F39: =SUM(F28) -> #REF! | G39: =SUM(G28) -> #REF! | H39: =SUM(H28) -> #REF!
B40: Total investment | C40: =SUM(C29:C32) -> -11500 | D40: =SUM(D29:D32) -> -5500 | E40: =SUM(E29:E32) -> -5500 | F40: =SUM(F29:F32) -> -5500 | G40: =SUM(G29:G32) -> -5500 | H40: =SUM(H29:H32) -> -33500
B49: Financial Investment Evaluation Metrics | L49: Financial Investment Evaluation Metrics
R51: How to read it
C52: Year 1 | D52: Year 2 | E52: Year 3 | F52: Year 4 | G52: Year 5 | H52: Total | N52: ROI | O52: =H53/H54 -> #REF! | R52: Return on Invesment ( Investment/Benefits)
B53: Benefits | C53: =C39 -> #REF! | D53: =D39 -> #REF! | E53: =E39 -> #REF! | F53: =F39 -> #REF! | G53: =G39 -> #REF! | H53: =SUM(C53:G53) -> #REF! | N53: Payback period | O53: =SUM(C58:G58) -> #REF! | R53: Time to recover the investment.The smallest the better.
B54: Investments | C54: =C40*-1 -> 11500 | D54: =D40*-1 -> 5500 | E54: =E40*-1 -> 5500 | F54: =F40*-1 -> 5500 | G54: =G40*-1 -> 5500 | H54: =SUM(C54:G54) -> 33500 | N54: NPV (Net Present Value) | O54: {=NPV(O56,C55:G55)} -> #REF! | R54: If positive it will be attractive. The greater the better.
B55: Net Flow | C55: =C53-C54 -> #REF! | D55: =D53-D54 -> #REF! | E55: =E53-E54 -> #REF! | F55: =F53-F54 -> #REF! | G55: =G53-G54 -> #REF! | N55: IRR (Internal Return Rate) | O55: =IRR(C55:G55) -> #REF! | R55: Discount rate in wich NPV=0 ; the greater the better
B56: Cumulative Net Cash Flow | C56: =C55 -> #REF! | D56: =C56+D55 -> #REF! | E56: =D56+E55 -> #REF! | F56: =E56+F55 -> #REF! | G56: =F56+G55 -> #REF! | N56: WAAC (Weighted Average Cost of Capital) | O56: 0.12 | R56: Discount rate. Average, validate with customer
B58: Payback | C58: =IF(C56<0,1,IF(B56<0,1-(-C56/(B56-C56)),0)) -> #REF! | D58: =IF(D56<0,1,IF(C56<0,1-(-D56/(C56-D56)),0)) -> #REF! | E58: =IF(E56<0,1,IF(D56<0,1-(-E56/(D56-E56)),0)) -> #REF! | F58: =IF(F56<0,1,IF(E56<0,1-(-F56/(E56-F56)),0)) -> #REF! | G58: =IF(G56<0,1,IF(F56<0,1-(-G56/(F56-G56)),0)) -> #REF!

Sheet Sheet1
C2: Parent | D2: Driver | E2: Baseline | F2: Impact | G2: Benefit | H2: Baseline formula | K2: Year 1 | L2: Year 2 | M2: Year 3 | N2: Year 4 | O2: Year 5 | Q2: Year 1 | R2: Year 2 | S2: Year 3 | T2: Year 4 | U2: Year 5
B3: Revenue | C3: AO | D3: Increase new customers per year by providing self service capabilities | E3: =E24*E21 -> 1696800 | F3: 0.1 | G3: =F3*E3 -> 169680 | H3: # of accounts open per year* average income/customer | K3: 0 | L3: 0.6 | M3: 0.8 | N3: 1 | O3: 1 | Q3: =K3*$G3 -> 0 | R3: =L3*$G3 -> 101808 | S3: =M3*$G3 -> 135744 | T3: =N3*$G3 -> 169680 | U3: =O3*$G3 -> 169680
B4: Revenue | C4: AO | D4: Reduce customer leakage by increasing digital channel | E4: =E23*E22*E21 -> 2545200 | F4: 0.3 | G4: =F4*E4 -> 763560 | H4: # of aplications*leakage*average income/customer | K4: 0 | L4: 0.6 | M4: 0.8 | N4: 1 | O4: 1 | Q4: =K4*$G4 -> 0 | R4: =L4*$G4 -> 458136 | S4: =M4*$G4 -> 610848 | T4: =N4*$G4 -> 763560 | U4: =O4*$G4 -> 763560
B5: Revenue | C5: Servicing ( payments , disputes) | D5: Reduce customer churn | E5: =E19*E20*E21 -> 37172958 | F5: 0.1 | G5: =F5*E5 -> 3717295.8 | H5: Number of customers*customer Churn*average income per customer | K5: 0 | L5: 0.6 | M5: 0.8 | N5: 1 | O5: 1 | Q5: =K5*$G5 -> 0 | R5: =L5*$G5 -> 2230377.5 | S5: =M5*$G5 -> 2973836.6 | T5: =N5*$G5 -> 3717295.8 | U5: =O5*$G5 -> 3717295.8
B6: Cost | D6: Reduce customer onboarding cost (branch, back office, paper based processes) by increasing self service | E6: =E59+E67 -> 78750 | F6: 0.45 | G6: =F6*E6 -> 35437.5 | H6: #calls/tasks | K6: 0 | L6: 0.6 | M6: 0.8 | N6: 1 | O6: 1 | Q6: =K6*$G6 -> 0 | R6: =L6*$G6 -> 21262.5 | S6: =M6*$G6 -> 28350 | T6: =N6*$G6 -> 35437.5 | U6: =O6*$G6 -> 35437.5
B7: Cost | D7: Reduce customer servicing cost - Disputes (reducing call center, branch , back office) | E7: =SUM(E34,E43,E51) -> 77175 | F7: 0.45 | G7: =F7*E7 -> 34728.75 | K7: 0 | L7: 0.6 | M7: 0.8 | N7: 1 | O7: 1 | Q7: =K7*$G7 -> 0 | R7: =L7*$G7 -> 20837.25 | S7: =M7*$G7 -> 27783 | T7: =N7*$G7 -> 34728.75 | U7: =O7*$G7 -> 34728.75
G8: =SUM(G3:G7) -> 4720702 | K8: =$G$8*K7 -> 0 | L8: =$G$8*L7 -> 2832421.2 | M8: =$G$8*M7 -> 3776561.6 | N8: =$G$8*N7 -> 4720702 | O8: =$G$8*O7 -> 4720702 | Q8: =SUM(Q3:Q7) -> 0 | XFD8: =SUM(XFD3:XFD7) -> 0
G10: =SUM(G3:G5) -> 4650535.8 | Q10: Year 1 | R10: Year 2 | S10: Year 3 | T10: Year 4 | U10: Year 5
G11: =SUM(G6:G7) -> 70166.25 | P11: Benfits | Q11: =SUM(Q3:Q7) -> 0 | R11: =SUM(R3:R7) -> 2832421.2 | S11: =SUM(S3:S7) -> 3776561.6 | T11: =SUM(T3:T7) -> 4720702 | U11: =SUM(U3:U7) -> 4720702
P12: Subscription | Q12: 1000000 | R12: 1000000 | S12: 1000000 | T12: 1000000 | U12: 1000000
P13: Implementation | Q13: 2500000
E14: Data
Q15: Year 1 | R15: Year 2 | S15: Year 3 | T15: Year 4 | U15: Year 5 | V15: Total
P16: Benefits | Q16: =SUM(Q3:Q7) -> 0 | R16: =SUM(R3:R7) -> 2832421.2 | S16: =SUM(S3:S7) -> 3776561.6 | T16: =SUM(T3:T7) -> 4720702 | U16: =SUM(U3:U7) -> 4720702 | V16: =SUM(Q16:U16) -> 16050387
D17: Revenue | P17: Investments | Q17: =SUM(Q12:Q13) -> 3500000 | R17: =SUM(R12:R13) -> 1000000 | S17: =SUM(S12:S13) -> 1000000 | T17: =SUM(T12:T13) -> 1000000 | U17: =SUM(U12:U13) -> 1000000 | V17: =SUM(Q17:U17) -> 7500000
P18: Net Flow | Q18: =Q16-Q17 -> -3500000 | R18: =R16-R17 -> 1832421.2 | S18: =S16-S17 -> 2776561.6 | T18: =T16-T17 -> 3720702 | U18: =U16-U17 -> 3720702
D19: Number of customers | E19: 1181538 | P19: Cumulative Net Cash Flow | Q19: =Q18 -> -3500000 | R19: =Q19+R18 -> -1667578.8 | S19: =R19+S18 -> 1108982.8 | T19: =S19+T18 -> 4829684.9 | U19: =T19+U18 -> 8550386.9
D20: Customer Churn | E20: 0.0445
D21: Average Income/Customer | E21: 707 | F21: ** | P21: Payback | Q21: =IF(Q19<0,1,IF(P19<0,1-(-Q19/(P19-Q19)),0)) -> 1 | R21: =IF(R19<0,1,IF(Q19<0,1-(-R19/(Q19-R19)),0)) -> 1 | S21: =IF(S19<0,1,IF(R19<0,1-(-S19/(R19-S19)),0)) -> 0.60059131 | T21: =IF(T19<0,1,IF(S19<0,1-(-T19/(S19-T19)),0)) -> 0 | U21: =IF(U19<0,1,IF(T19<0,1-(-U19/(T19-U19)),0)) -> 0
D22: Current Customer Leakage (%) in new account applications | E22: 0.6
D23: Average # of account opening aplications | E23: 6000 | P23: ROI
D24: Average # of accounts opened in a year | E24: 2400
Q25: 0 | R25: 2360351 | S25: 3776561.6 | T25: 4720702 | U25: 4720702
C28: Transactions D | D28: Cost call Center | Q28: 0 | R28: =Q28/1000 -> 0 | T28: 0
Q29: 2360351 | R29: =Q29/1000 -> 2360.351 | T29: 2360.351
D30: No of Visits/Calls/Tasks/Year | E30: 4800 | F30: Volume of physical interactions or back office tasks created | Q30: 3776561.6 | R30: =Q30/1000 -> 3776.5616 | T30: 3776.5616
D31: Average Time Spent /Interaction (hour) | E31: =15/60 -> 0.25 | F31: Time spent on1 visit, call or task | Q31: 4720702 | R31: =Q31/1000 -> 4720.702 | T31: 4720.702
D32: Average FTE Costs/Hour (USD) | E32: 15.75 | F32: Based on data provided 850 KD average monthly salary | Q32: 4720702 | R32: =Q32/1000 -> 4720.702 | T32: 4720.702
E34: =E30*E31*E32 -> 18900
C37: Transactions D | D37: Cost Branch
D39: No of Visits/Calls/Tasks/Year | E39: 3600 | F39: Volume of physical interactions or back office tasks created
D40: Average Time Spent /Interaction (hour) | E40: =15/60 -> 0.25 | F40: Time spent on1 visit, call or task
D41: Average FTE Costs/Hour (USD) | E41: 15.75 | F41: Based on data provided 850 KD average monthly salary
E43: =E39*E40*E41 -> 14175
C45: Transactions D | D45: Back Office
D47: No of Visits/Calls/Tasks/Year | E47: 8400 | F47: Volume of physical interactions or back office tasks created
D48: Average Time Spent /Interaction (hour) | E48: =20/60 -> 0.33333333 | F48: Time spent on1 visit, call or task
D49: Average FTE Costs/Hour (USD) | E49: 15.75 | F49: Based on data provided 850 KD average monthly salary
E51: =E47*E48*E49 -> 44100
C53: On Boarding | D53: Cost Branch
D55: No of Visits/Calls/Tasks/Year | E55: 6000
D56: Average Time Spent /Interaction (hour) | E56: =30/60 -> 0.5
D57: Average FTE Costs/Hour (USD) | E57: 15.75
E59: =E55*E56*E57 -> 47250
C61: On Boarding | D61: Back Office
D63: No of Visits/Calls/Tasks/Year | E63: 6000
D64: Average Time Spent /Interaction (hour) | E64: =20/60 -> 0.33333333
D65: Average FTE Costs/Hour (USD) | E65: 15.75
E67: =E63*E64*E65 -> 31500
